Workbook
Name Ejercicio_fiscal: #REF!
Name RAZÓN_SOCIAL: #REF!
Name RUC: #REF!

Sheet BC
A1: =RAZÓN_SOCIAL -> #REF!
A2: Balance de comprobación
A3: =Ejercicio_fiscal -> #REF! | U3: =SUM(U7:U347) -> 0
D4: Saldo | K4: Saldo ajustado
A5: Item # | B5: Código Cuenta | C5: Cuenta | D5: Año 2020 | E5: casillero | F5: Grupo | G5: nombre cuenta formulario 101 | H5: Mapeo EF | I5: Débito | J5: Crédito | K5: =CONCATENATE("Año ",RIGHT(Ejercicio_fiscal,4)) -> #REF! | L5: Sin mapear | M5: Observaciones
B6: Es importante que la información se ingrese solo en las celdas BLANCAS. Todas las demás celdas calcularán automáticamente en función de la información ingresada en las celdas BLANCAS. | D6: =SUM(D7:D347) -> #REF! | I6: =SUM(I7:I347) -> #REF! | J6: =SUM(J7:J347) -> #REF! | K6: =SUM(K7:K347) -> #REF! | L6: =SUM(L7:L347) -> #REF!
A7: =ROW(A7)-7 -> 0 | B7: 1.01.01.01.01 | C7: CAJA GENERAL | D7: =+#REF! -> #REF! | E7: 311 | F7: =IFERROR(VLOOKUP($E7,Casilleros!$A$4:$I$830,4,FALSE),"") -> ACTIVOS CORRIENTES | G7: =IFERROR(VLOOKUP($E7,Casilleros!$A$4:$I$830,9,FALSE),"") -> Efectivo y equivalentes al efectivo | H7: =IFERROR(VLOOKUP($E7,Casilleros!$A$4:$J$830,10,FALSE),"") -> Efectivo y equivalentes al efectivo | I7: =SUMIF(#REF!,$B7,#REF!) -> #REF! | J7: =SUMIF(#REF!,$B7,#REF!) -> #REF! | K7: =+D7+SUM(I7:J7) -> #REF! | L7: =IF(E7="",K7,0) -> 0
A8: =ROW(A8)-7 -> 1 | B8: 1.01.01.01.02 | C8: CAJA CHICA | D8: =+#REF! -> #REF! | E8: 311 | F8: =IFERROR(VLOOKUP($E8,Casilleros!$A$4:$I$830,4,FALSE),"") -> ACTIVOS CORRIENTES | G8: =IFERROR(VLOOKUP($E8,Casilleros!$A$4:$I$830,9,FALSE),"") -> Efectivo y equivalentes al efectivo | H8: =IFERROR(VLOOKUP($E8,Casilleros!$A$4:$J$830,10,FALSE),"") -> Efectivo y equivalentes al efectivo | I8: =SUMIF(#REF!,$B8,#REF!) -> #REF! | J8: =SUMIF(#REF!,$B8,#REF!) -> #REF! | K8: =+D8+SUM(I8:J8) -> #REF! | L8: =IF(E8="",K8,0) -> 0
A9: =ROW(A9)-7 -> 2 | B9: 1.01.01.01.08 | C9: CAJA-TARJETA DIFERIDOS #2 | D9: =+#REF! -> #REF! | E9: 311 | F9: =IFERROR(VLOOKUP($E9,Casilleros!$A$4:$I$830,4,FALSE),"") -> ACTIVOS CORRIENTES | G9: =IFERROR(VLOOKUP($E9,Casilleros!$A$4:$I$830,9,FALSE),"") -> Efectivo y equivalentes al efectivo | H9: =IFERROR(VLOOKUP($E9,Casilleros!$A$4:$J$830,10,FALSE),"") -> Efectivo y equivalentes al efectivo | I9: =SUMIF(#REF!,$B9,#REF!) -> #REF! | J9: =SUMIF(#REF!,$B9,#REF!) -> #REF! | K9: =+D9+SUM(I9:J9) -> #REF! | L9: =IF(E9="",K9,0) -> 0
A10: =ROW(A10)-7 -> 3 | B10: 1.01.01.01.08 | C10: CAJA-TARJETA DIFERIDOS #2 | D10: =+#REF! -> #REF! | E10: 311 | F10: =IFERROR(VLOOKUP($E10,Casilleros!$A$4:$I$830,4,FALSE),"") -> ACTIVOS CORRIENTES | G10: =IFERROR(VLOOKUP($E10,Casilleros!$A$4:$I$830,9,FALSE),"") -> Efectivo y equivalentes al efectivo | H10: =IFERROR(VLOOKUP($E10,Casilleros!$A$4:$J$830,10,FALSE),"") -> Efectivo y equivalentes al efectivo | I10: =SUMIF(#REF!,$B10,#REF!) -> #REF! | J10: =SUMIF(#REF!,$B10,#REF!) -> #REF! | K10: =+D10+SUM(I10:J10) -> #REF! | L10: =IF(E10="",K10,0) -> 0
A11: =ROW(A11)-7 -> 4 | B11: 1.01.01.02.02 | C11: PRODUBANCO CTA.CTE.01-04918600-3 | D11: =+#REF! -> #REF! | E11: 311 | F11: =IFERROR(VLOOKUP($E11,Casilleros!$A$4:$I$830,4,FALSE),"") -> ACTIVOS CORRIENTES | G11: =IFERROR(VLOOKUP($E11,Casilleros!$A$4:$I$830,9,FALSE),"") -> Efectivo y equivalentes al efectivo | H11: =IFERROR(VLOOKUP($E11,Casilleros!$A$4:$J$830,10,FALSE),"") -> Efectivo y equivalentes al efectivo | I11: =SUMIF(#REF!,$B11,#REF!) -> #REF! | J11: =SUMIF(#REF!,$B11,#REF!) -> #REF! | K11: =+D11+SUM(I11:J11) -> #REF! | L11: =IF(E11="",K11,0) -> 0
A12: =ROW(A12)-7 -> 5 | B12: 1.01.01.02.03 | C12: BANCO BOLIVARIANO CTA CTE 5025022482 | D12: =+#REF! -> #REF! | E12: 311 | F12: =IFERROR(VLOOKUP($E12,Casilleros!$A$4:$I$830,4,FALSE),"") -> ACTIVOS CORRIENTES | G12: =IFERROR(VLOOKUP($E12,Casilleros!$A$4:$I$830,9,FALSE),"") -> Efectivo y equivalentes al efectivo | H12: =IFERROR(VLOOKUP($E12,Casilleros!$A$4:$J$830,10,FALSE),"") -> Efectivo y equivalentes al efectivo | I12: =SUMIF(#REF!,$B12,#REF!) -> #REF! | J12: =SUMIF(#REF!,$B12,#REF!) -> #REF! | K12: =+D12+SUM(I12:J12) -> #REF! | L12: =IF(E12="",K12,0) -> 0
A13: =ROW(A13)-7 -> 6 | B13: 1.01.01.02.04 | C13: BOLIVARIANO INTERNACIONAL PANAMA - 01302005222 | D13: =+#REF! -> #REF! | E13: 311 | F13: =IFERROR(VLOOKUP($E13,Casilleros!$A$4:$I$830,4,FALSE),"") -> ACTIVOS CORRIENTES | G13: =IFERROR(VLOOKUP($E13,Casilleros!$A$4:$I$830,9,FALSE),"") -> Efectivo y equivalentes al efectivo | H13: =IFERROR(VLOOKUP($E13,Casilleros!$A$4:$J$830,10,FALSE),"") -> Efectivo y equivalentes al efectivo | I13: =SUMIF(#REF!,$B13,#REF!) -> #REF! | J13: =SUMIF(#REF!,$B13,#REF!) -> #REF! | K13: =+D13+SUM(I13:J13) -> #REF! | L13: =IF(E13="",K13,0) -> 0
A14: =ROW(A14)-7 -> 7 | B14: 1.01.01.02.06 | C14: GUAYAQUIL CTA CTE 49802005 | D14: =+#REF! -> #REF! | E14: 311 | F14: =IFERROR(VLOOKUP($E14,Casilleros!$A$4:$I$830,4,FALSE),"") -> ACTIVOS CORRIENTES | G14: =IFERROR(VLOOKUP($E14,Casilleros!$A$4:$I$830,9,FALSE),"") -> Efectivo y equivalentes al efectivo | H14: =IFERROR(VLOOKUP($E14,Casilleros!$A$4:$J$830,10,FALSE),"") -> Efectivo y equivalentes al efectivo | I14: =SUMIF(#REF!,$B14,#REF!) -> #REF! | J14: =SUMIF(#REF!,$B14,#REF!) -> #REF! | K14: =+D14+SUM(I14:J14) -> #REF! | L14: =IF(E14="",K14,0) -> 0
A15: =ROW(A15)-7 -> 8 | B15: =+#REF! -> #REF! | C15: =+#REF! -> #REF! | D15: =+#REF! -> #REF! | E15: 311 | F15: =IFERROR(VLOOKUP($E15,Casilleros!$A$4:$I$830,4,FALSE),"") -> ACTIVOS CORRIENTES | G15: =IFERROR(VLOOKUP($E15,Casilleros!$A$4:$I$830,9,FALSE),"") -> Efectivo y equivalentes al efectivo | H15: =IFERROR(VLOOKUP($E15,Casilleros!$A$4:$J$830,10,FALSE),"") -> Efectivo y equivalentes al efectivo | I15: =SUMIF(#REF!,$B15,#REF!) -> #REF! | J15: =SUMIF(#REF!,$B15,#REF!) -> #REF! | K15: =+D15+SUM(I15:J15) -> #REF! | L15: =IF(E15="",K15,0) -> 0
A16: =ROW(A16)-7 -> 9 | B16: 1.01.01.03.01 | C16: INVERSIONES BCO GUAYAQUIL | D16: =+#REF! -> #REF! | E16: 311 | F16: =IFERROR(VLOOKUP($E16,Casilleros!$A$4:$I$830,4,FALSE),"") -> ACTIVOS CORRIENTES | G16: =IFERROR(VLOOKUP($E16,Casilleros!$A$4:$I$830,9,FALSE),"") -> Efectivo y equivalentes al efectivo | H16: =IFERROR(VLOOKUP($E16,Casilleros!$A$4:$J$830,10,FALSE),"") -> Efectivo y equivalentes al efectivo | I16: =SUMIF(#REF!,$B16,#REF!) -> #REF! | J16: =SUMIF(#REF!,$B16,#REF!) -> #REF! | K16: =+D16+SUM(I16:J16) -> #REF! | L16: =IF(E16="",K16,0) -> 0
A17: =ROW(A17)-7 -> 10 | B17: 1.01.01.03.02 | C17: INVERSIONES PRODUBANCO | D17: =+#REF! -> #REF! | E17: 311 | F17: =IFERROR(VLOOKUP($E17,Casilleros!$A$4:$I$830,4,FALSE),"") -> ACTIVOS CORRIENTES | G17: =IFERROR(VLOOKUP($E17,Casilleros!$A$4:$I$830,9,FALSE),"") -> Efectivo y equivalentes al efectivo | H17: =IFERROR(VLOOKUP($E17,Casilleros!$A$4:$J$830,10,FALSE),"") -> Efectivo y equivalentes al efectivo | I17: =SUMIF(#REF!,$B17,#REF!) -> #REF! | J17: =SUMIF(#REF!,$B17,#REF!) -> #REF! | K17: =+D17+SUM(I17:J17) -> #REF! | L17: =IF(E17="",K17,0) -> 0
A18: =ROW(A18)-7 -> 11 | B18: 1.01.02.05.01 | C18: CLIENTES | D18: =+#REF! -> #REF! | E18: 315 | F18: =IFERROR(VLOOKUP($E18,Casilleros!$A$4:$I$830,4,FALSE),"") -> ACTIVOS CORRIENTES | G18: =IFERROR(VLOOKUP($E18,Casilleros!$A$4:$I$830,9,FALSE),"") -> CUENTAS Y DOCUMENTOS POR COBRAR CORRIENTES_CUENTAS Y DOCUMENTOS POR COBRAR COMERCIALES CORRIENTES_NO RELACIONADAS_Locales | H18: =IFERROR(VLOOKUP($E18,Casilleros!$A$4:$J$830,10,FALSE),"") -> Cuentas y Documentos por cobrar corrientes | I18: =SUMIF(#REF!,$B18,#REF!) -> #REF! | J18: =SUMIF(#REF!,$B18,#REF!) -> #REF! | K18: =+D18+SUM(I18:J18) -> #REF! | L18: =IF(E18="",K18,0) -> 0
A19: =ROW(A19)-7 -> 12 | B19: 1.01.02.05.99 | C19: DETERIORO CUENTAS PO COBRAR | D19: =+#REF! -> #REF! | E19: 317 | F19: =IFERROR(VLOOKUP($E19,Casilleros!$A$4:$I$830,4,FALSE),"") -> ACTIVOS CORRIENTES | G19: =IFERROR(VLOOKUP($E19,Casilleros!$A$4:$I$830,9,FALSE),"") -> CUENTAS Y DOCUMENTOS POR COBRAR CORRIENTES_CUENTAS Y DOCUMENTOS POR COBRAR COMERCIALES CORRIENTES_NO RELACIONADAS_(-) Deterioro acumulado del valor de cuentas y documentos por cobrar comerciales por incobrabilidad (provisiones para créditos incobrables) | H19: =IFERROR(VLOOKUP($E19,Casilleros!$A$4:$J$830,10,FALSE),"") -> Cuentas y Documentos por cobrar corrientes | I19: =SUMIF(#REF!,$B19,#REF!) -> #REF! | J19: =SUMIF(#REF!,$B19,#REF!) -> #REF! | K19: =+D19+SUM(I19:J19) -> #REF! | L19: =IF(E19="",K19,0) -> 0
A20: =ROW(A20)-7 -> 13 | B20: 1.01.02.07.01 | C20: CHEQUES PROTESTADOS | D20: =+#REF! -> #REF! | E20: 315 | F20: =IFERROR(VLOOKUP($E20,Casilleros!$A$4:$I$830,4,FALSE),"") -> ACTIVOS CORRIENTES | G20: =IFERROR(VLOOKUP($E20,Casilleros!$A$4:$I$830,9,FALSE),"") -> CUENTAS Y DOCUMENTOS POR COBRAR CORRIENTES_CUENTAS Y DOCUMENTOS POR COBRAR COMERCIALES CORRIENTES_NO RELACIONADAS_Locales | H20: =IFERROR(VLOOKUP($E20,Casilleros!$A$4:$J$830,10,FALSE),"") -> Cuentas y Documentos por cobrar corrientes | I20: =SUMIF(#REF!,$B20,#REF!) -> #REF! | J20: =SUMIF(#REF!,$B20,#REF!) -> #REF! | K20: =+D20+SUM(I20:J20) -> #REF! | L20: =IF(E20="",K20,0) -> 0
A21: =ROW(A21)-7 -> 14 | B21: 1.01.02.08.01 | C21: OTRAS CUENTAS POR COBRAR A TERCEROS | D21: =+#REF! -> #REF! | E21: 325 | F21: =IFERROR(VLOOKUP($E21,Casilleros!$A$4:$I$830,4,FALSE),"") -> ACTIVOS CORRIENTES | G21: =IFERROR(VLOOKUP($E21,Casilleros!$A$4:$I$830,9,FALSE),"") -> CUENTAS Y DOCUMENTOS POR COBRAR CORRIENTES_OTRAS CUENTAS Y DOCUMENTOS POR COBRAR CORRIENTES_OTRAS NO RELACIONADAS_Locales | H21: =IFERROR(VLOOKUP($E21,Casilleros!$A$4:$J$830,10,FALSE),"") -> Cuentas y Documentos por cobrar corrientes | I21: =SUMIF(#REF!,$B21,#REF!) -> #REF! | J21: =SUMIF(#REF!,$B21,#REF!) -> #REF! | K21: =+D21+SUM(I21:J21) -> #REF! | L21: =IF(E21="",K21,0) -> 0
A22: =ROW(A22)-7 -> 15 | B22: 1.01.02.08.02 | C22: ANTICIPO EMPLEADOS | D22: =+#REF! -> #REF! | E22: 325 | F22: =IFERROR(VLOOKUP($E22,Casilleros!$A$4:$I$830,4,FALSE),"") -> ACTIVOS CORRIENTES | G22: =IFERROR(VLOOKUP($E22,Casilleros!$A$4:$I$830,9,FALSE),"") -> CUENTAS Y DOCUMENTOS POR COBRAR CORRIENTES_OTRAS CUENTAS Y DOCUMENTOS POR COBRAR CORRIENTES_OTRAS NO RELACIONADAS_Locales | H22: =IFERROR(VLOOKUP($E22,Casilleros!$A$4:$J$830,10,FALSE),"") -> Cuentas y Documentos por cobrar corrientes | I22: =SUMIF(#REF!,$B22,#REF!) -> #REF! | J22: =SUMIF(#REF!,$B22,#REF!) -> #REF! | K22: =+D22+SUM(I22:J22) -> #REF! | L22: =IF(E22="",K22,0) -> 0
A23: =ROW(A23)-7 -> 16 | B23: 1.01.02.08.03 | C23: ANTICIPO SUELDOS | E23: 325 | F23: =IFERROR(VLOOKUP($E23,Casilleros!$A$4:$I$830,4,FALSE),"") -> ACTIVOS CORRIENTES | G23: =IFERROR(VLOOKUP($E23,Casilleros!$A$4:$I$830,9,FALSE),"") -> CUENTAS Y DOCUMENTOS POR COBRAR CORRIENTES_OTRAS CUENTAS Y DOCUMENTOS POR COBRAR CORRIENTES_OTRAS NO RELACIONADAS_Locales | H23: =IFERROR(VLOOKUP($E23,Casilleros!$A$4:$J$830,10,FALSE),"") -> Cuentas y Documentos por cobrar corrientes | I23: =SUMIF(#REF!,$B23,#REF!) -> #REF! | J23: =SUMIF(#REF!,$B23,#REF!) -> #REF! | K23: =+D23+SUM(I23:J23) -> #REF! | L23: =IF(E23="",K23,0) -> 0
A24: =ROW(A24)-7 -> 17 | B24: 1.01.04.03 | C24: ANTICIPOS A PROVEEDORES | D24: =+#REF! -> #REF! | E24: 325 | F24: =IFERROR(VLOOKUP($E24,Casilleros!$A$4:$I$830,4,FALSE),"") -> ACTIVOS CORRIENTES | G24: =IFERROR(VLOOKUP($E24,Casilleros!$A$4:$I$830,9,FALSE),"") -> CUENTAS Y DOCUMENTOS POR COBRAR CORRIENTES_OTRAS CUENTAS Y DOCUMENTOS POR COBRAR CORRIENTES_OTRAS NO RELACIONADAS_Locales | H24: =IFERROR(VLOOKUP($E24,Casilleros!$A$4:$J$830,10,FALSE),"") -> Cuentas y Documentos por cobrar corrientes | I24: =SUMIF(#REF!,$B24,#REF!) -> #REF! | J24: =SUMIF(#REF!,$B24,#REF!) -> #REF! | K24: =+D24+SUM(I24:J24) -> #REF! | L24: =IF(E24="",K24,0) -> 0
A25: =ROW(A25)-7 -> 18 | B25: =+#REF! -> #REF! | C25: =+#REF! -> #REF! | D25: =+#REF! -> #REF! | E25: 360 | F25: =IFERROR(VLOOKUP($E25,Casilleros!$A$4:$I$830,4,FALSE),"") -> ACTIVOS CORRIENTES | G25: =IFERROR(VLOOKUP($E25,Casilleros!$A$4:$I$830,9,FALSE),"") -> Otros Activos Corrientes | H25: =IFERROR(VLOOKUP($E25,Casilleros!$A$4:$J$830,10,FALSE),"") -> Otros activos corrientes | I25: =SUMIF(#REF!,$B25,#REF!) -> #REF! | J25: =SUMIF(#REF!,$B25,#REF!) -> #REF! | K25: =+D25+SUM(I25:J25) -> #REF! | L25: =IF(E25="",K25,0) -> 0
A26: =ROW(A26)-7 -> 19 | B26: 1.01.05.02 | C26: (IR) CRÉDITO TRIBUTARIO A FAVOR DE LA EMPRESA ( I. R.) | D26: 0 | E26: 337 | F26: =IFERROR(VLOOKUP($E26,Casilleros!$A$4:$I$830,4,FALSE),"") -> ACTIVOS CORRIENTES | G26: =IFERROR(VLOOKUP($E26,Casilleros!$A$4:$I$830,9,FALSE),"") -> ACTIVOS POR IMPUESTOS CORRIENTES_Crédito tributario a favor del sujeto pasivo (Impuesto a la Renta) __ | H26: =IFERROR(VLOOKUP($E26,Casilleros!$A$4:$J$830,10,FALSE),"") -> Activos por impuestos corrientes | I26: =SUMIF(#REF!,$B26,#REF!) -> #REF! | J26: =SUMIF(#REF!,$B26,#REF!) -> #REF! | K26: =+D26+SUM(I26:J26) -> #REF! | L26: =IF(E26="",K26,0) -> 0
A27: =ROW(A27)-7 -> 20 | B27: 1.02.01.01.01 | C27: TERRENOS | D27: =+#REF! -> #REF! | E27: 362 | F27: =IFERROR(VLOOKUP($E27,Casilleros!$A$4:$I$830,4,FALSE),"") -> ACTIVOS NO CORRIENTES | G27: =IFERROR(VLOOKUP($E27,Casilleros!$A$4:$I$830,9,FALSE),"") -> PROPIEDADES, PLANTA Y EQUIPO_TERRENOS_Costo histórico antes de reexpresiones o revaluaciones_ | H27: =IFERROR(VLOOKUP($E27,Casilleros!$A$4:$J$830,10,FALSE),"") -> Propiedades, planta y equipo | I27: =SUMIF(#REF!,$B27,#REF!) -> #REF! | J27: =SUMIF(#REF!,$B27,#REF!) -> #REF! | K27: =+D27+SUM(I27:J27) -> #REF! | L27: =IF(E27="",K27,0) -> 0
A28: =ROW(A28)-7 -> 21 | B28: 1.02.01.01.02 | C28: CANCHA SINTETICA | D28: =+#REF! -> #REF! | E28: 364 | F28: =IFERROR(VLOOKUP($E28,Casilleros!$A$4:$I$830,4,FALSE),"") -> ACTIVOS NO CORRIENTES | G28: =IFERROR(VLOOKUP($E28,Casilleros!$A$4:$I$830,9,FALSE),"") -> PROPIEDADES, PLANTA Y EQUIPO_EDIFICIOS Y OTROS INMUEBLES (EXCEPTO TERRENOS)_Costo histórico antes de reexpresiones o revaluaciones _ | H28: =IFERROR(VLOOKUP($E28,Casilleros!$A$4:$J$830,10,FALSE),"") -> Propiedades, planta y equipo | I28: =SUMIF(#REF!,$B28,#REF!) -> #REF! | J28: =SUMIF(#REF!,$B28,#REF!) -> #REF! | K28: =+D28+SUM(I28:J28) -> #REF! | L28: =IF(E28="",K28,0) -> 0
A29: =ROW(A29)-7 -> 22 | B29: 1.02.01.01.03 | C29: EDIFICIOS | D29: =+#REF! -> #REF! | E29: 364 | F29: =IFERROR(VLOOKUP($E29,Casilleros!$A$4:$I$830,4,FALSE),"") -> ACTIVOS NO CORRIENTES | G29: =IFERROR(VLOOKUP($E29,Casilleros!$A$4:$I$830,9,FALSE),"") -> PROPIEDADES, PLANTA Y EQUIPO_EDIFICIOS Y OTROS INMUEBLES (EXCEPTO TERRENOS)_Costo histórico antes de reexpresiones o revaluaciones _ | H29: =IFERROR(VLOOKUP($E29,Casilleros!$A$4:$J$830,10,FALSE),"") -> Propiedades, planta y equipo | I29: =SUMIF(#REF!,$B29,#REF!) -> #REF! | J29: =SUMIF(#REF!,$B29,#REF!) -> #REF! | K29: =+D29+SUM(I29:J29) -> #REF! | L29: =IF(E29="",K29,0) -> 0
A30: =ROW(A30)-7 -> 23 | B30: 1.02.01.01.05 | C30: MUEBLES Y ENSERES | D30: =+#REF! -> #REF! | E30: 373 | F30: =IFERROR(VLOOKUP($E30,Casilleros!$A$4:$I$830,4,FALSE),"") -> ACTIVOS NO CORRIENTES | G30: =IFERROR(VLOOKUP($E30,Casilleros!$A$4:$I$830,9,FALSE),"") -> PROPIEDADES, PLANTA Y EQUIPO_Muebles y enseres__ | H30: =IFERROR(VLOOKUP($E30,Casilleros!$A$4:$J$830,10,FALSE),"") -> Propiedades, planta y equipo | I30: =SUMIF(#REF!,$B30,#REF!) -> #REF! | J30: =SUMIF(#REF!,$B30,#REF!) -> #REF! | K30: =+D30+SUM(I30:J30) -> #REF! | L30: =IF(E30="",K30,0) -> 0
A31: =ROW(A31)-7 -> 24 | B31: 1.02.01.01.06 | C31: MAQUINARIA Y EQUIPO | D31: =+#REF! -> #REF! | E31: 368 | F31: =IFERROR(VLOOKUP($E31,Casilleros!$A$4:$I$830,4,FALSE),"") -> ACTIVOS NO CORRIENTES | G31: =IFERROR(VLOOKUP($E31,Casilleros!$A$4:$I$830,9,FALSE),"") -> PROPIEDADES, PLANTA Y EQUIPO_MAQUINARIA, EQUIPO, INSTALACIONES Y ADECUACIONES_Costo histórico antes de reexpresiones o revaluaciones _ | H31: =IFERROR(VLOOKUP($E31,Casilleros!$A$4:$J$830,10,FALSE),"") -> Propiedades, planta y equipo | I31: =SUMIF(#REF!,$B31,#REF!) -> #REF! | J31: =SUMIF(#REF!,$B31,#REF!) -> #REF! | K31: =+D31+SUM(I31:J31) -> #REF! | L31: =IF(E31="",K31,0) -> 0
A32: =ROW(A32)-7 -> 25 | B32: 1.02.01.01.08 | C32: EQUIPO DE COMPUTACIÓN | D32: =+#REF! -> #REF! | E32: 374 | F32: =IFERROR(VLOOKUP($E32,Casilleros!$A$4:$I$830,4,FALSE),"") -> ACTIVOS NO CORRIENTES | G32: =IFERROR(VLOOKUP($E32,Casilleros!$A$4:$I$830,9,FALSE),"") -> PROPIEDADES, PLANTA Y EQUIPO_Equipo de Computación__equipo de computación | H32: =IFERROR(VLOOKUP($E32,Casilleros!$A$4:$J$830,10,FALSE),"") -> Propiedades, planta y equipo | I32: =SUMIF(#REF!,$B32,#REF!) -> #REF! | J32: =SUMIF(#REF!,$B32,#REF!) -> #REF! | K32: =+D32+SUM(I32:J32) -> #REF! | L32: =IF(E32="",K32,0) -> 0
A33: =ROW(A33)-7 -> 26 | B33: 1.02.01.01.09 | C33: VEHÍCULOS, EQUIPOS DE TRANSPORTE Y EQUIPO CAMINERO MÓVIL | D33: =+#REF! -> #REF! | E33: 375 | F33: =IFERROR(VLOOKUP($E33,Casilleros!$A$4:$I$830,4,FALSE),"") -> ACTIVOS NO CORRIENTES | G33: =IFERROR(VLOOKUP($E33,Casilleros!$A$4:$I$830,9,FALSE),"") -> PROPIEDADES, PLANTA Y EQUIPO_Vehículos, Equipo de Transporte y Caminero Móvil__equipo de computación | H33: =IFERROR(VLOOKUP($E33,Casilleros!$A$4:$J$830,10,FALSE),"") -> Propiedades, planta y equipo | I33: =SUMIF(#REF!,$B33,#REF!) -> #REF! | J33: =SUMIF(#REF!,$B33,#REF!) -> #REF! | K33: =+D33+SUM(I33:J33) -> #REF! | L33: =IF(E33="",K33,0) -> 0
A34: =ROW(A34)-7 -> 27 | B34: 1.02.01.01.11 | C34: COSTO EQUIPOS | D34: =+#REF! -> #REF! | E34: 374 | F34: =IFERROR(VLOOKUP($E34,Casilleros!$A$4:$I$830,4,FALSE),"") -> ACTIVOS NO CORRIENTES | G34: =IFERROR(VLOOKUP($E34,Casilleros!$A$4:$I$830,9,FALSE),"") -> PROPIEDADES, PLANTA Y EQUIPO_Equipo de Computación__equipo de computación | H34: =IFERROR(VLOOKUP($E34,Casilleros!$A$4:$J$830,10,FALSE),"") -> Propiedades, planta y equipo | I34: =SUMIF(#REF!,$B34,#REF!) -> #REF! | J34: =SUMIF(#REF!,$B34,#REF!) -> #REF! | K34: =+D34+SUM(I34:J34) -> #REF! | L34: =IF(E34="",K34,0) -> 0
A35: =ROW(A35)-7 -> 28 | B35: 1.02.01.01.11 | C35: COSTO EQUIPOS | D35: =+#REF! -> #REF! | E35: 372 | F35: =IFERROR(VLOOKUP($E35,Casilleros!$A$4:$I$830,4,FALSE),"") -> ACTIVOS NO CORRIENTES | G35: =IFERROR(VLOOKUP($E35,Casilleros!$A$4:$I$830,9,FALSE),"") -> PROPIEDADES, PLANTA Y EQUIPO_Construcciones en Curso y Otros Activos en Tránsito__ | H35: =IFERROR(VLOOKUP($E35,Casilleros!$A$4:$J$830,10,FALSE),"") -> Propiedades, planta y equipo | I35: =SUMIF(#REF!,$B35,#REF!) -> #REF! | J35: =SUMIF(#REF!,$B35,#REF!) -> #REF! | K35: =+D35+SUM(I35:J35) -> #REF! | L35: =IF(E35="",K35,0) -> 0
A36: =ROW(A36)-7 -> 29 | B36: 1.02.01.12.01 | C36: DEPRECIACION EDIFICIOS | D36: =+#REF! -> #REF! | E36: 384 | F36: =IFERROR(VLOOKUP($E36,Casilleros!$A$4:$I$830,4,FALSE),"") -> ACTIVOS NO CORRIENTES | G36: =IFERROR(VLOOKUP($E36,Casilleros!$A$4:$I$830,9,FALSE),"") -> PROPIEDADES, PLANTA Y EQUIPO_(-) DEPRECIACIÒN ACUMULADA DE PROPIEDADES, PLANTA Y EQUIPO_Del costo histórico antes de reexpresiones o revaluaciones_ | H36: =IFERROR(VLOOKUP($E36,Casilleros!$A$4:$J$830,10,FALSE),"") -> Propiedades, planta y equipo | I36: =SUMIF(#REF!,$B36,#REF!) -> #REF! | J36: =SUMIF(#REF!,$B36,#REF!) -> #REF! | K36: =+D36+SUM(I36:J36) -> #REF! | L36: =IF(E36="",K36,0) -> 0
A37: =ROW(A37)-7 -> 30 | B37: 1.02.01.12.02 | C37: DEPRECIACION MUEBLES Y ENSERES | D37: =+#REF! -> #REF! | E37: 384 | F37: =IFERROR(VLOOKUP($E37,Casilleros!$A$4:$I$830,4,FALSE),"") -> ACTIVOS NO CORRIENTES | G37: =IFERROR(VLOOKUP($E37,Casilleros!$A$4:$I$830,9,FALSE),"") -> PROPIEDADES, PLANTA Y EQUIPO_(-) DEPRECIACIÒN ACUMULADA DE PROPIEDADES, PLANTA Y EQUIPO_Del costo histórico antes de reexpresiones o revaluaciones_ | H37: =IFERROR(VLOOKUP($E37,Casilleros!$A$4:$J$830,10,FALSE),"") -> Propiedades, planta y equipo | I37: =SUMIF(#REF!,$B37,#REF!) -> #REF! | J37: =SUMIF(#REF!,$B37,#REF!) -> #REF! | K37: =+D37+SUM(I37:J37) -> #REF! | L37: =IF(E37="",K37,0) -> 0
A38: =ROW(A38)-7 -> 31 | B38: 1.02.01.12.03 | C38: DEPRECIACION MAQUINARIA Y EQUIPOS | D38: =+#REF! -> #REF! | E38: 384 | F38: =IFERROR(VLOOKUP($E38,Casilleros!$A$4:$I$830,4,FALSE),"") -> ACTIVOS NO CORRIENTES | G38: =IFERROR(VLOOKUP($E38,Casilleros!$A$4:$I$830,9,FALSE),"") -> PROPIEDADES, PLANTA Y EQUIPO_(-) DEPRECIACIÒN ACUMULADA DE PROPIEDADES, PLANTA Y EQUIPO_Del costo histórico antes de reexpresiones o revaluaciones_ | H38: =IFERROR(VLOOKUP($E38,Casilleros!$A$4:$J$830,10,FALSE),"") -> Propiedades, planta y equipo | I38: =SUMIF(#REF!,$B38,#REF!) -> #REF! | J38: =SUMIF(#REF!,$B38,#REF!) -> #REF! | K38: =+D38+SUM(I38:J38) -> #REF! | L38: =IF(E38="",K38,0) -> 0
... A54: =ROW(A54)-7 -> 47 | B54: 2.01.04.08 | C54: VISA GUAYAQUIL | D54: =+#REF! -> #REF! | E54: 525 | F54: =IFERROR(VLOOKUP($E54,Casilleros!$A$4:$I$830,4,FALSE),"") -> PASIVOS CORRIENTES | G54: =IFERROR(VLOOKUP($E54,Casilleros!$A$4:$I$830,9,FALSE),"") -> OBLIGACIONES CON INSTITUCIONES FINANCIERAS - CORRIENTES_NO RELACIONADAS_Locales_ | H54: =IFERROR(VLOOKUP($E54,Casilleros!$A$4:$J$830,10,FALSE),"") -> Cbligaciones con instituciones financieras - corrientes | I54: =SUMIF(#REF!,$B54,#REF!) -> #REF! | J54: =SUMIF(#REF!,$B54,#REF!) -> #REF! | K54: =+D54+SUM(I54:J54) -> #REF! | L54: =IF(E54="",K54,0) -> 0
A55: =ROW(A55)-7 -> 48 | B55: 2.01.03.02 | C55: PRESTAMOS BANCARIOS | E55: 523 | F55: =IFERROR(VLOOKUP($E55,Casilleros!$A$4:$I$830,4,FALSE),"") -> PASIVOS CORRIENTES | G55: =IFERROR(VLOOKUP($E55,Casilleros!$A$4:$I$830,9,FALSE),"") -> OBLIGACIONES CON INSTITUCIONES FINANCIERAS - CORRIENTES_RELACIONADAS_Locales_ | H55: =IFERROR(VLOOKUP($E55,Casilleros!$A$4:$J$830,10,FALSE),"") -> Cbligaciones con instituciones financieras - corrientes | I55: =SUMIF(#REF!,$B55,#REF!) -> #REF! | J55: =SUMIF(#REF!,$B55,#REF!) -> #REF! | K55: =+D55+SUM(I55:J55) -> #REF! | L55: =IF(E55="",K55,0) -> 0
A56: =ROW(A56)-7 -> 49 | B56: 2.01.03.03 | C56: OTRAS CUENTAS POR PAGAR | E56: 511 | F56: =IFERROR(VLOOKUP($E56,Casilleros!$A$4:$I$830,4,FALSE),"") -> PASIVOS CORRIENTES | G56: =IFERROR(VLOOKUP($E56,Casilleros!$A$4:$I$830,9,FALSE),"") -> CUENTAS Y DOCUMENTOS POR PAGAR CORRIENTES_CUENTAS Y DOCUMENTOS POR PAGAR COMERCIALES CORRIENTES_RELACIONADAS_Locales | H56: =IFERROR(VLOOKUP($E56,Casilleros!$A$4:$J$830,10,FALSE),"") -> Cuentas y documentos por pagar corrientes | I56: =SUMIF(#REF!,$B56,#REF!) -> #REF! | J56: =SUMIF(#REF!,$B56,#REF!) -> #REF! | K56: =+D56+SUM(I56:J56) -> #REF! | L56: =IF(E56="",K56,0) -> 0
A57: =ROW(A57)-7 -> 50 | B57: 2.01.07.01.99 | C57: SRI POR PAGAR | D57: =+#REF! -> #REF! | E57: 511 | F57: =IFERROR(VLOOKUP($E57,Casilleros!$A$4:$I$830,4,FALSE),"") -> PASIVOS CORRIENTES | G57: =IFERROR(VLOOKUP($E57,Casilleros!$A$4:$I$830,9,FALSE),"") -> CUENTAS Y DOCUMENTOS POR PAGAR CORRIENTES_CUENTAS Y DOCUMENTOS POR PAGAR COMERCIALES CORRIENTES_RELACIONADAS_Locales | H57: =IFERROR(VLOOKUP($E57,Casilleros!$A$4:$J$830,10,FALSE),"") -> Cuentas y documentos por pagar corrientes | I57: =SUMIF(#REF!,$B57,#REF!) -> #REF! | J57: =SUMIF(#REF!,$B57,#REF!) -> #REF! | K57: =+D57+SUM(I57:J57) -> #REF! | L57: =IF(E57="",K57,0) -> 0
A58: =ROW(A58)-7 -> 51 | B58: 2.01.07.03.01 | C58: APORTES AL IESS | D58: =+#REF! -> #REF! | E58: 534 | F58: =IFERROR(VLOOKUP($E58,Casilleros!$A$4:$I$830,4,FALSE),"") -> PASIVOS CORRIENTES | G58: =IFERROR(VLOOKUP($E58,Casilleros!$A$4:$I$830,9,FALSE),"") -> PASIVOS CORRIENTES POR BENEFICIOS A LOS EMPLEADOS_Obligaciones con el IESS__ | H58: =IFERROR(VLOOKUP($E58,Casilleros!$A$4:$J$830,10,FALSE),"") -> Pasivos corrientes por beneficios a los empleados | I58: =SUMIF(#REF!,$B58,#REF!) -> #REF! | J58: =SUMIF(#REF!,$B58,#REF!) -> #REF! | K58: =+D58+SUM(I58:J58) -> #REF! | L58: =IF(E58="",K58,0) -> 0
A59: =ROW(A59)-7 -> 52 | B59: 2.01.07.03.02 | C59: PRESTAMO QUIROGRAFARIO | D59: =+#REF! -> #REF! | E59: 534 | F59: =IFERROR(VLOOKUP($E59,Casilleros!$A$4:$I$830,4,FALSE),"") -> PASIVOS CORRIENTES | G59: =IFERROR(VLOOKUP($E59,Casilleros!$A$4:$I$830,9,FALSE),"") -> PASIVOS CORRIENTES POR BENEFICIOS A LOS EMPLEADOS_Obligaciones con el IESS__ | H59: =IFERROR(VLOOKUP($E59,Casilleros!$A$4:$J$830,10,FALSE),"") -> Pasivos corrientes por beneficios a los empleados | I59: =SUMIF(#REF!,$B59,#REF!) -> #REF! | J59: =SUMIF(#REF!,$B59,#REF!) -> #REF! | K59: =+D59+SUM(I59:J59) -> #REF! | L59: =IF(E59="",K59,0) -> 0
A60: =ROW(A60)-7 -> 53 | B60: 2.01.07.03.03 | C60: PRESTAMO HIPOTECARIO | D60: =+#REF! -> #REF! | E60: 534 | F60: =IFERROR(VLOOKUP($E60,Casilleros!$A$4:$I$830,4,FALSE),"") -> PASIVOS CORRIENTES | G60: =IFERROR(VLOOKUP($E60,Casilleros!$A$4:$I$830,9,FALSE),"") -> PASIVOS CORRIENTES POR BENEFICIOS A LOS EMPLEADOS_Obligaciones con el IESS__ | H60: =IFERROR(VLOOKUP($E60,Casilleros!$A$4:$J$830,10,FALSE),"") -> Pasivos corrientes por beneficios a los empleados | I60: =SUMIF(#REF!,$B60,#REF!) -> #REF! | J60: =SUMIF(#REF!,$B60,#REF!) -> #REF! | K60: =+D60+SUM(I60:J60) -> #REF! | L60: =IF(E60="",K60,0) -> 0
A61: =ROW(A61)-7 -> 54 | B61: 2.01.07.03.04 | C61: FONDO RESERVA | D61: =+#REF! -> #REF! | E61: 534 | F61: =IFERROR(VLOOKUP($E61,Casilleros!$A$4:$I$830,4,FALSE),"") -> PASIVOS CORRIENTES | G61: =IFERROR(VLOOKUP($E61,Casilleros!$A$4:$I$830,9,FALSE),"") -> PASIVOS CORRIENTES POR BENEFICIOS A LOS EMPLEADOS_Obligaciones con el IESS__ | H61: =IFERROR(VLOOKUP($E61,Casilleros!$A$4:$J$830,10,FALSE),"") -> Pasivos corrientes por beneficios a los empleados | I61: =SUMIF(#REF!,$B61,#REF!) -> #REF! | J61: =SUMIF(#REF!,$B61,#REF!) -> #REF! | K61: =+D61+SUM(I61:J61) -> #REF! | L61: =IF(E61="",K61,0) -> 0
A62: =ROW(A62)-7 -> 55 | B62: 2.01.07.04.01 | C62: SUELDOS | D62: 0 | E62: 536 | F62: =IFERROR(VLOOKUP($E62,Casilleros!$A$4:$I$830,4,FALSE),"") -> PASIVOS CORRIENTES | G62: =IFERROR(VLOOKUP($E62,Casilleros!$A$4:$I$830,9,FALSE),"") -> PASIVOS CORRIENTES POR BENEFICIOS A LOS EMPLEADOS_Otros Pasivos Corrientes Por Beneficios a Empleados__ | H62: =IFERROR(VLOOKUP($E62,Casilleros!$A$4:$J$830,10,FALSE),"") -> Pasivos corrientes por beneficios a los empleados | I62: =SUMIF(#REF!,$B62,#REF!) -> #REF! | J62: =SUMIF(#REF!,$B62,#REF!) -> #REF! | K62: =+D62+SUM(I62:J62) -> #REF! | L62: =IF(E62="",K62,0) -> 0
A63: =ROW(A63)-7 -> 56 | B63: 2.01.07.04.02 | C63: DECIMOS TERCER SUELDO | D63: =+#REF! -> #REF! | E63: 536 | F63: =IFERROR(VLOOKUP($E63,Casilleros!$A$4:$I$830,4,FALSE),"") -> PASIVOS CORRIENTES | G63: =IFERROR(VLOOKUP($E63,Casilleros!$A$4:$I$830,9,FALSE),"") -> PASIVOS CORRIENTES POR BENEFICIOS A LOS EMPLEADOS_Otros Pasivos Corrientes Por Beneficios a Empleados__ | H63: =IFERROR(VLOOKUP($E63,Casilleros!$A$4:$J$830,10,FALSE),"") -> Pasivos corrientes por beneficios a los empleados | I63: =SUMIF(#REF!,$B63,#REF!) -> #REF! | J63: =SUMIF(#REF!,$B63,#REF!) -> #REF! | K63: =+D63+SUM(I63:J63) -> #REF! | L63: =IF(E63="",K63,0) -> 0
A64: =ROW(A64)-7 -> 57 | B64: 2.01.07.04.03 | C64: DECIMOS CUARTO SUELDO | D64: =+#REF! -> #REF! | E64: 536 | F64: =IFERROR(VLOOKUP($E64,Casilleros!$A$4:$I$830,4,FALSE),"") -> PASIVOS CORRIENTES | G64: =IFERROR(VLOOKUP($E64,Casilleros!$A$4:$I$830,9,FALSE),"") -> PASIVOS CORRIENTES POR BENEFICIOS A LOS EMPLEADOS_Otros Pasivos Corrientes Por Beneficios a Empleados__ | H64: =IFERROR(VLOOKUP($E64,Casilleros!$A$4:$J$830,10,FALSE),"") -> Pasivos corrientes por beneficios a los empleados | I64: =SUMIF(#REF!,$B64,#REF!) -> #REF! | J64: =SUMIF(#REF!,$B64,#REF!) -> #REF! | K64: =+D64+SUM(I64:J64) -> #REF! | L64: =IF(E64="",K64,0) -> 0
A65: =ROW(A65)-7 -> 58 | B65: 2.01.07.05 | C65: PARTICIPACIÓN TRABAJADORES POR PAGAR DEL EJERCICIO | D65: =+#REF! -> #REF! | E65: 533 | F65: =IFERROR(VLOOKUP($E65,Casilleros!$A$4:$I$830,4,FALSE),"") -> PASIVOS CORRIENTES | G65: =IFERROR(VLOOKUP($E65,Casilleros!$A$4:$I$830,9,FALSE),"") -> PASIVOS CORRIENTES POR BENEFICIOS A LOS EMPLEADOS_Participación trabajadores por pagar del ejercicio__ | H65: =IFERROR(VLOOKUP($E65,Casilleros!$A$4:$J$830,10,FALSE),"") -> Pasivos corrientes por beneficios a los empleados | I65: =SUMIF(#REF!,$B65,#REF!) -> #REF! | J65: =SUMIF(#REF!,$B65,#REF!) -> #REF! | K65: =+D65+SUM(I65:J65) -> #REF! | L65: =IF(E65="",K65,0) -> 0
A66: =ROW(A66)-7 -> 59 | B66: 2.01.07.06 | C66: IMPUESTO A LA RENTA POR PAGAR | D66: =+#REF! -> #REF! | E66: 532 | F66: =IFERROR(VLOOKUP($E66,Casilleros!$A$4:$I$830,4,FALSE),"") -> PASIVOS CORRIENTES | G66: =IFERROR(VLOOKUP($E66,Casilleros!$A$4:$I$830,9,FALSE),"") -> Impuesto A La Renta Por Pagar Del Ejercicio | H66: =IFERROR(VLOOKUP($E66,Casilleros!$A$4:$J$830,10,FALSE),"") -> Impuesto a la renta por pagar del ejercicio | I66: =SUMIF(#REF!,$B66,#REF!) -> #REF! | J66: =SUMIF(#REF!,$B66,#REF!) -> #REF! | K66: =+D66+SUM(I66:J66) -> #REF! | L66: =IF(E66="",K66,0) -> 0
A67: =ROW(A67)-7 -> 60 | B67: 2.01.13.01 | C67: DEPOSITO POR IDENTIFICAR | D67: =+#REF! -> #REF! | E67: 545 | F67: =IFERROR(VLOOKUP($E67,Casilleros!$A$4:$I$830,4,FALSE),"") -> PASIVOS CORRIENTES | G67: =IFERROR(VLOOKUP($E67,Casilleros!$A$4:$I$830,9,FALSE),"") -> PASIVOS POR INGRESOS DIFERIDOS_Anticipos de clientes__ | H67: =IFERROR(VLOOKUP($E67,Casilleros!$A$4:$J$830,10,FALSE),"") -> Pasivos por ingresos diferidos | I67: =SUMIF(#REF!,$B67,#REF!) -> #REF! | J67: =SUMIF(#REF!,$B67,#REF!) -> #REF! | K67: =+D67+SUM(I67:J67) -> #REF! | L67: =IF(E67="",K67,0) -> 0
A68: =ROW(A68)-7 -> 61 | B68: 2.01.13.02 | C68: DEPOSITO GARANTIA | D68: =+#REF! -> #REF! | E68: 537 | F68: =IFERROR(VLOOKUP($E68,Casilleros!$A$4:$I$830,4,FALSE),"") -> PASIVOS CORRIENTES | G68: =IFERROR(VLOOKUP($E68,Casilleros!$A$4:$I$830,9,FALSE),"") -> PROVISIONES CORRIENTES _Por garantías__ | H68: =IFERROR(VLOOKUP($E68,Casilleros!$A$4:$J$830,10,FALSE),"") -> Provisiones corrientes | I68: =SUMIF(#REF!,$B68,#REF!) -> #REF! | J68: =SUMIF(#REF!,$B68,#REF!) -> #REF! | K68: =+D68+SUM(I68:J68) -> #REF! | L68: =IF(E68="",K68,0) -> 0
A69: =ROW(A69)-7 -> 62 | B69: 2.02.01.03 | C69: JARAMILLO ARTURO | D69: -175552.95 | E69: 557 | F69: =IFERROR(VLOOKUP($E69,Casilleros!$A$4:$I$830,4,FALSE),"") -> PASIVOS NO CORRIENTES | G69: =IFERROR(VLOOKUP($E69,Casilleros!$A$4:$I$830,9,FALSE),"") -> CUENTAS Y DOCUMENTOS POR PAGAR NO CORRIENTES_OTRAS CUENTAS Y DOCUMENTOS POR PAGAR NO CORRIENTES_A ACCIONISTAS, SOCIOS, PARTÍCIPES. BENEFICIARIOS U OTROS TITULARES DE DERECHOS REPRESENTATIVOS DE CAPITAL_Locales | H69: =IFERROR(VLOOKUP($E69,Casilleros!$A$4:$J$830,10,FALSE),"") -> Cuentas y documentos por pagar no corrientes | I69: =SUMIF(#REF!,$B69,#REF!) -> #REF! | J69: =SUMIF(#REF!,$B69,#REF!) -> #REF! | K69: =+D69+SUM(I69:J69) -> #REF! | L69: =IF(E69="",K69,0) -> 0
A70: =ROW(A70)-7 -> 63 | B70: 2.02.01.04 | C70: JARAMILLO MARITZA | D70: -175552.95 | E70: 557 | F70: =IFERROR(VLOOKUP($E70,Casilleros!$A$4:$I$830,4,FALSE),"") -> PASIVOS NO CORRIENTES | G70: =IFERROR(VLOOKUP($E70,Casilleros!$A$4:$I$830,9,FALSE),"") -> CUENTAS Y DOCUMENTOS POR PAGAR NO CORRIENTES_OTRAS CUENTAS Y DOCUMENTOS POR PAGAR NO CORRIENTES_A ACCIONISTAS, SOCIOS, PARTÍCIPES. BENEFICIARIOS U OTROS TITULARES DE DERECHOS REPRESENTATIVOS DE CAPITAL_Locales | H70: =IFERROR(VLOOKUP($E70,Casilleros!$A$4:$J$830,10,FALSE),"") -> Cuentas y documentos por pagar no corrientes | I70: =SUMIF(#REF!,$B70,#REF!) -> #REF! | J70: =SUMIF(#REF!,$B70,#REF!) -> #REF! | K70: =+D70+SUM(I70:J70) -> #REF! | L70: =IF(E70="",K70,0) -> 0
A71: =ROW(A71)-7 -> 64 | B71: 2.02.02.07 | C71: ANTICIPO CLIENTES | D71: =+#REF! -> #REF! | E71: 584 | F71: =IFERROR(VLOOKUP($E71,Casilleros!$A$4:$I$830,4,FALSE),"") -> PASIVOS NO CORRIENTES | G71: =IFERROR(VLOOKUP($E71,Casilleros!$A$4:$I$830,9,FALSE),"") -> PASIVOS POR INGRESOS DIFERIDOS_Anticipos de clientes__ | H71: =IFERROR(VLOOKUP($E71,Casilleros!$A$4:$J$830,10,FALSE),"") -> Pasivos por ingresos diferidos no corrientes | I71: =SUMIF(#REF!,$B71,#REF!) -> #REF! | J71: =SUMIF(#REF!,$B71,#REF!) -> #REF! | K71: =+D71+SUM(I71:J71) -> #REF! | L71: =IF(E71="",K71,0) -> 0
A72: =ROW(A72)-7 -> 65 | B72: 2.02.04.02 | C72: JARAMILLO ARTURO | D72: =+#REF! -> #REF! | E72: 557 | F72: =IFERROR(VLOOKUP($E72,Casilleros!$A$4:$I$830,4,FALSE),"") -> PASIVOS NO CORRIENTES | G72: =IFERROR(VLOOKUP($E72,Casilleros!$A$4:$I$830,9,FALSE),"") -> CUENTAS Y DOCUMENTOS POR PAGAR NO CORRIENTES_OTRAS CUENTAS Y DOCUMENTOS POR PAGAR NO CORRIENTES_A ACCIONISTAS, SOCIOS, PARTÍCIPES. BENEFICIARIOS U OTROS TITULARES DE DERECHOS REPRESENTATIVOS DE CAPITAL_Locales | H72: =IFERROR(VLOOKUP($E72,Casilleros!$A$4:$J$830,10,FALSE),"") -> Cuentas y documentos por pagar no corrientes | I72: =SUMIF(#REF!,$B72,#REF!) -> #REF! | J72: =SUMIF(#REF!,$B72,#REF!) -> #REF! | K72: =+D72+SUM(I72:J72) -> #REF! | L72: =IF(E72="",K72,0) -> 0
A73: =ROW(A73)-7 -> 66 | B73: 2.02.04.03 | C73: JARAMILLO MARITZA | D73: =+#REF! -> #REF! | E73: 557 | F73: =IFERROR(VLOOKUP($E73,Casilleros!$A$4:$I$830,4,FALSE),"") -> PASIVOS NO CORRIENTES | G73: =IFERROR(VLOOKUP($E73,Casilleros!$A$4:$I$830,9,FALSE),"") -> CUENTAS Y DOCUMENTOS POR PAGAR NO CORRIENTES_OTRAS CUENTAS Y DOCUMENTOS POR PAGAR NO CORRIENTES_A ACCIONISTAS, SOCIOS, PARTÍCIPES. BENEFICIARIOS U OTROS TITULARES DE DERECHOS REPRESENTATIVOS DE CAPITAL_Locales | H73: =IFERROR(VLOOKUP($E73,Casilleros!$A$4:$J$830,10,FALSE),"") -> Cuentas y documentos por pagar no corrientes | I73: =SUMIF(#REF!,$B73,#REF!) -> #REF! | J73: =SUMIF(#REF!,$B73,#REF!) -> #REF! | K73: =+D73+SUM(I73:J73) -> #REF! | L73: =IF(E73="",K73,0) -> 0
A74: =ROW(A74)-7 -> 67 | B74: 2.02.07.01 | C74: JUBILACION PATRONAL | D74: =+#REF! -> #REF! | E74: 573 | F74: =IFERROR(VLOOKUP($E74,Casilleros!$A$4:$I$830,4,FALSE),"") -> PASIVOS NO CORRIENTES | G74: =IFERROR(VLOOKUP($E74,Casilleros!$A$4:$I$830,9,FALSE),"") -> PASIVOS NO CORRIENTES POR BENEFICIOS A LOS EMPLEADOS_Jubilación Patronal__ | H74: =IFERROR(VLOOKUP($E74,Casilleros!$A$4:$J$830,10,FALSE),"") -> Pasivos no corrientes por beneficios a los empleados | I74: =SUMIF(#REF!,$B74,#REF!) -> #REF! | J74: =SUMIF(#REF!,$B74,#REF!) -> #REF! | K74: =+D74+SUM(I74:J74) -> #REF! | L74: =IF(E74="",K74,0) -> 0
A75: =ROW(A75)-7 -> 68 | B75: 2.02.07.03 | C75: DESAHUCIO | D75: =+#REF! -> #REF! | E75: 574 | F75: =IFERROR(VLOOKUP($E75,Casilleros!$A$4:$I$830,4,FALSE),"") -> PASIVOS NO CORRIENTES | G75: =IFERROR(VLOOKUP($E75,Casilleros!$A$4:$I$830,9,FALSE),"") -> PASIVOS NO CORRIENTES POR BENEFICIOS A LOS EMPLEADOS_Desahucio__ | H75: =IFERROR(VLOOKUP($E75,Casilleros!$A$4:$J$830,10,FALSE),"") -> Pasivos no corrientes por beneficios a los empleados | I75: =SUMIF(#REF!,$B75,#REF!) -> #REF! | J75: =SUMIF(#REF!,$B75,#REF!) -> #REF! | K75: =+D75+SUM(I75:J75) -> #REF! | L75: =IF(E75="",K75,0) -> 0
A76: =ROW(A76)-7 -> 69 | B76: 2.02.09.02 | C76: PASIVOS POR IMPUESTOS DIFERIDOS | D76: =+#REF! -> #REF! | E76: 572 | F76: =IFERROR(VLOOKUP($E76,Casilleros!$A$4:$I$830,4,FALSE),"") -> PASIVOS NO CORRIENTES | G76: =IFERROR(VLOOKUP($E76,Casilleros!$A$4:$I$830,9,FALSE),"") -> Pasivo por Impuesto a la Renta diferido | H76: =IFERROR(VLOOKUP($E76,Casilleros!$A$4:$J$830,10,FALSE),"") -> Pasivo por impuesto a la renta diferido | I76: =SUMIF(#REF!,$B76,#REF!) -> #REF! | J76: =SUMIF(#REF!,$B76,#REF!) -> #REF! | K76: =+D76+SUM(I76:J76) -> #REF! | L76: =IF(E76="",K76,0) -> 0
A77: =ROW(A77)-7 -> 70 | B77: 3.01.01.03 | C77: JARAMILLO ARMIJOS ARTURO JAVIER | D77: =+#REF! -> #REF! | E77: 601 | F77: =IFERROR(VLOOKUP($E77,Casilleros!$A$4:$I$830,4,FALSE),"") -> Capital Suscrito y/o Asignado | G77: =IFERROR(VLOOKUP($E77,Casilleros!$A$4:$I$830,9,FALSE),"") -> Capital Suscrito y/o Asignado | H77: =IFERROR(VLOOKUP($E77,Casilleros!$A$4:$J$830,10,FALSE),"") -> Capital suscrito y/o asignado | I77: =SUMIF(#REF!,$B77,#REF!) -> #REF! | J77: =SUMIF(#REF!,$B77,#REF!) -> #REF! | K77: =+D77+SUM(I77:J77) -> #REF! | L77: =IF(E77="",K77,0) -> 0
A78: =ROW(A78)-7 -> 71 | B78: 3.01.01.06 | C78: JARAMILLO ARMIJOS MARITZA | D78: =+#REF! -> #REF! | E78: 601 | F78: =IFERROR(VLOOKUP($E78,Casilleros!$A$4:$I$830,4,FALSE),"") -> Capital Suscrito y/o Asignado | G78: =IFERROR(VLOOKUP($E78,Casilleros!$A$4:$I$830,9,FALSE),"") -> Capital Suscrito y/o Asignado | H78: =IFERROR(VLOOKUP($E78,Casilleros!$A$4:$J$830,10,FALSE),"") -> Capital suscrito y/o asignado | I78: =SUMIF(#REF!,$B78,#REF!) -> #REF! | J78: =SUMIF(#REF!,$B78,#REF!) -> #REF! | K78: =+D78+SUM(I78:J78) -> #REF! | L78: =IF(E78="",K78,0) -> 0
A79: =ROW(A79)-7 -> 72 | B79: 3.04.01 | C79: RESERVA LEGAL | D79: =+#REF! -> #REF! | E79: 604 | F79: =IFERROR(VLOOKUP($E79,Casilleros!$A$4:$I$830,4,FALSE),"") -> RESERVAS | G79: =IFERROR(VLOOKUP($E79,Casilleros!$A$4:$I$830,9,FALSE),"") -> RESERVAS Reserva legal | H79: =IFERROR(VLOOKUP($E79,Casilleros!$A$4:$J$830,10,FALSE),"") -> Reservas | I79: =SUMIF(#REF!,$B79,#REF!) -> #REF! | J79: =SUMIF(#REF!,$B79,#REF!) -> #REF! | K79: =+D79+SUM(I79:J79) -> #REF! | L79: =IF(E79="",K79,0) -> 0
A80: =ROW(A80)-7 -> 73 | B80: 3.04.02 | C80: RESERVAS FACULTATIVA Y ESTATUTARIA | D80: =+#REF! -> #REF! | E80: 605 | F80: =IFERROR(VLOOKUP($E80,Casilleros!$A$4:$I$830,4,FALSE),"") -> RESERVAS | G80: =IFERROR(VLOOKUP($E80,Casilleros!$A$4:$I$830,9,FALSE),"") -> RESERVAS Reserva facultativa | H80: =IFERROR(VLOOKUP($E80,Casilleros!$A$4:$J$830,10,FALSE),"") -> Reservas | I80: =SUMIF(#REF!,$B80,#REF!) -> #REF! | J80: =SUMIF(#REF!,$B80,#REF!) -> #REF! | K80: =+D80+SUM(I80:J80) -> #REF! | L80: =IF(E80="",K80,0) -> 0
A81: =ROW(A81)-7 -> 74 | B81: 3.04.03 | C81: RESERVA DE CAPITAL | D81: =+#REF! -> #REF! | E81: 607 | F81: =IFERROR(VLOOKUP($E81,Casilleros!$A$4:$I$830,4,FALSE),"") -> RESULTADOS ACUMULADOS | G81: =IFERROR(VLOOKUP($E81,Casilleros!$A$4:$I$830,9,FALSE),"") -> RESULTADOS ACUMULADOS Reserva de capital | H81: =IFERROR(VLOOKUP($E81,Casilleros!$A$4:$J$830,10,FALSE),"") -> Resultados acumulados | I81: =SUMIF(#REF!,$B81,#REF!) -> #REF! | J81: =SUMIF(#REF!,$B81,#REF!) -> #REF! | K81: =+D81+SUM(I81:J81) -> #REF! | L81: =IF(E81="",K81,0) -> 0
A82: =ROW(A82)-7 -> 75 | B82: 3.04.05 | C82: RESERVA POR REVALORIZACION DE ACTIVOS FIIJOS | D82: =+#REF! -> #REF! | E82: 618 | F82: =IFERROR(VLOOKUP($E82,Casilleros!$A$4:$I$830,4,FALSE),"") -> OTROS RESULTADOS INTEGRALES ACUMULADOS | G82: =IFERROR(VLOOKUP($E82,Casilleros!$A$4:$I$830,9,FALSE),"") -> SUPERÁVIT DE REVALUACIÓN ACUMULADO_Propiedades, Planta y Equipo__ | H82: =IFERROR(VLOOKUP($E82,Casilleros!$A$4:$J$830,10,FALSE),"") -> Otros resultados integrales | I82: =SUMIF(#REF!,$B82,#REF!) -> #REF! | J82: =SUMIF(#REF!,$B82,#REF!) -> #REF! | K82: =+D82+SUM(I82:J82) -> #REF! | L82: =IF(E82="",K82,0) -> 0
... A92: =ROW(A92)-7 -> 85 | B92: 3.07.13 | C92: RESULTADO DEL EJERCICIO 2023 | D92: =+#REF! -> #REF! | E92: 611 | F92: =IFERROR(VLOOKUP($E92,Casilleros!$A$4:$I$830,4,FALSE),"") -> RESULTADOS ACUMULADOS | G92: =IFERROR(VLOOKUP($E92,Casilleros!$A$4:$I$830,9,FALSE),"") -> RESULTADOS ACUMULADOS Utilidades acumuladas de ejercicios anteriores | H92: =IFERROR(VLOOKUP($E92,Casilleros!$A$4:$J$830,10,FALSE),"") -> Resultados acumulados | I92: =SUMIF(#REF!,$B92,#REF!) -> #REF! | J92: =SUMIF(#REF!,$B92,#REF!) -> #REF! | K92: =+D92+SUM(I92:J92) -> #REF! | L92: =IF(E92="",K92,0) -> 0
A93: =ROW(A93)-7 -> 86 | C93: =+#REF! -> #REF! | D93: =-+#REF! -> #REF! | E93: 615 | F93: =IFERROR(VLOOKUP($E93,Casilleros!$A$4:$I$830,4,FALSE),"") -> RESULTADOS ACUMULADOS | G93: =IFERROR(VLOOKUP($E93,Casilleros!$A$4:$I$830,9,FALSE),"") -> RESULTADOS ACUMULADOS Utilidad del ejercicio | H93: =IFERROR(VLOOKUP($E93,Casilleros!$A$4:$J$830,10,FALSE),"") -> Resultados acumulados | I93: =SUMIF(#REF!,$B93,#REF!) -> #REF! | J93: =SUMIF(#REF!,$B93,#REF!) -> #REF! | K93: =+D93+SUM(I93:J93) -> #REF! | L93: =IF(E93="",K93,0) -> 0
A94: =ROW(A94)-7 -> 87 | B94: 4.1.02.01.01 | C94: PENSIONES | D94: =+#REF! -> #REF! | E94: 6007 | F94: =IFERROR(VLOOKUP($E94,Casilleros!$A$4:$I$830,4,FALSE),"") -> INGRESOS DE ACTIVIDADES ORDINARIAS | G94: =IFERROR(VLOOKUP($E94,Casilleros!$A$4:$I$830,9,FALSE),"") -> PRESTACIONES LOCALES DE SERVICIOS_Gravadas con tarifa 0% de iva o exentas de IVA__ | H94: =IFERROR(VLOOKUP($E94,Casilleros!$A$4:$J$830,10,FALSE),"") -> Ingresos de actividades ordinarias | I94: =SUMIF(#REF!,$B94,#REF!) -> #REF! | J94: =SUMIF(#REF!,$B94,#REF!) -> #REF! | K94: =+D94+SUM(I94:J94) -> #REF! | L94: =IF(E94="",K94,0) -> 0
A95: =ROW(A95)-7 -> 88 | B95: 4.1.02.01.02 | C95: MATRICULAS | D95: =+#REF! -> #REF! | E95: 6007 | F95: =IFERROR(VLOOKUP($E95,Casilleros!$A$4:$I$830,4,FALSE),"") -> INGRESOS DE ACTIVIDADES ORDINARIAS | G95: =IFERROR(VLOOKUP($E95,Casilleros!$A$4:$I$830,9,FALSE),"") -> PRESTACIONES LOCALES DE SERVICIOS_Gravadas con tarifa 0% de iva o exentas de IVA__ | H95: =IFERROR(VLOOKUP($E95,Casilleros!$A$4:$J$830,10,FALSE),"") -> Ingresos de actividades ordinarias | I95: =SUMIF(#REF!,$B95,#REF!) -> #REF! | J95: =SUMIF(#REF!,$B95,#REF!) -> #REF! | K95: =+D95+SUM(I95:J95) -> #REF! | L95: =IF(E95="",K95,0) -> 0
A96: =ROW(A96)-7 -> 89 | B96: 4.1.02.01.03 | C96: TRANSPORTE | D96: =+#REF! -> #REF! | E96: 6007 | F96: =IFERROR(VLOOKUP($E96,Casilleros!$A$4:$I$830,4,FALSE),"") -> INGRESOS DE ACTIVIDADES ORDINARIAS | G96: =IFERROR(VLOOKUP($E96,Casilleros!$A$4:$I$830,9,FALSE),"") -> PRESTACIONES LOCALES DE SERVICIOS_Gravadas con tarifa 0% de iva o exentas de IVA__ | H96: =IFERROR(VLOOKUP($E96,Casilleros!$A$4:$J$830,10,FALSE),"") -> Ingresos de actividades ordinarias | I96: =SUMIF(#REF!,$B96,#REF!) -> #REF! | J96: =SUMIF(#REF!,$B96,#REF!) -> #REF! | K96: =+D96+SUM(I96:J96) -> #REF! | L96: =IF(E96="",K96,0) -> 0
A97: =ROW(A97)-7 -> 90 | B97: 4.1.02.02.01 | C97: PENSIONES | D97: =+#REF! -> #REF! | E97: 6007 | F97: =IFERROR(VLOOKUP($E97,Casilleros!$A$4:$I$830,4,FALSE),"") -> INGRESOS DE ACTIVIDADES ORDINARIAS | G97: =IFERROR(VLOOKUP($E97,Casilleros!$A$4:$I$830,9,FALSE),"") -> PRESTACIONES LOCALES DE SERVICIOS_Gravadas con tarifa 0% de iva o exentas de IVA__ | H97: =IFERROR(VLOOKUP($E97,Casilleros!$A$4:$J$830,10,FALSE),"") -> Ingresos de actividades ordinarias | I97: =SUMIF(#REF!,$B97,#REF!) -> #REF! | J97: =SUMIF(#REF!,$B97,#REF!) -> #REF! | K97: =+D97+SUM(I97:J97) -> #REF! | L97: =IF(E97="",K97,0) -> 0
A98: =ROW(A98)-7 -> 91 | B98: 4.1.02.03.01 | C98: PENSIONES | D98: =+#REF! -> #REF! | E98: 6007 | F98: =IFERROR(VLOOKUP($E98,Casilleros!$A$4:$I$830,4,FALSE),"") -> INGRESOS DE ACTIVIDADES ORDINARIAS | G98: =IFERROR(VLOOKUP($E98,Casilleros!$A$4:$I$830,9,FALSE),"") -> PRESTACIONES LOCALES DE SERVICIOS_Gravadas con tarifa 0% de iva o exentas de IVA__ | H98: =IFERROR(VLOOKUP($E98,Casilleros!$A$4:$J$830,10,FALSE),"") -> Ingresos de actividades ordinarias | I98: =SUMIF(#REF!,$B98,#REF!) -> #REF! | J98: =SUMIF(#REF!,$B98,#REF!) -> #REF! | K98: =+D98+SUM(I98:J98) -> #REF! | L98: =IF(E98="",K98,0) -> 0
A99: =ROW(A99)-7 -> 92 | B99: =+#REF! -> #REF! | C99: =+#REF! -> #REF! | D99: =+#REF! -> #REF! | E99: 6007 | F99: =IFERROR(VLOOKUP($E99,Casilleros!$A$4:$I$830,4,FALSE),"") -> INGRESOS DE ACTIVIDADES ORDINARIAS | G99: =IFERROR(VLOOKUP($E99,Casilleros!$A$4:$I$830,9,FALSE),"") -> PRESTACIONES LOCALES DE SERVICIOS_Gravadas con tarifa 0% de iva o exentas de IVA__ | H99: =IFERROR(VLOOKUP($E99,Casilleros!$A$4:$J$830,10,FALSE),"") -> Ingresos de actividades ordinarias | I99: =SUMIF(#REF!,$B99,#REF!) -> #REF! | J99: =SUMIF(#REF!,$B99,#REF!) -> #REF! | K99: =+D99+SUM(I99:J99) -> #REF! | L99: =IF(E99="",K99,0) -> 0
A100: =ROW(A100)-7 -> 93 | B100: 4.1.02.03.05 | C100: CERTIF.CARNET | D100: =+#REF! -> #REF! | E100: 6007 | F100: =IFERROR(VLOOKUP($E100,Casilleros!$A$4:$I$830,4,FALSE),"") -> INGRESOS DE ACTIVIDADES ORDINARIAS | G100: =IFERROR(VLOOKUP($E100,Casilleros!$A$4:$I$830,9,FALSE),"") -> PRESTACIONES LOCALES DE SERVICIOS_Gravadas con tarifa 0% de iva o exentas de IVA__ | H100: =IFERROR(VLOOKUP($E100,Casilleros!$A$4:$J$830,10,FALSE),"") -> Ingresos de actividades ordinarias | I100: =SUMIF(#REF!,$B100,#REF!) -> #REF! | J100: =SUMIF(#REF!,$B100,#REF!) -> #REF! | K100: =+D100+SUM(I100:J100) -> #REF! | L100: =IF(E100="",K100,0) -> 0
A101: =ROW(A101)-7 -> 94 | B101: 4.1.02.03.06 | C101: SERVICIOS EDUCATIVOS | D101: =+#REF! -> #REF! | E101: 6007 | F101: =IFERROR(VLOOKUP($E101,Casilleros!$A$4:$I$830,4,FALSE),"") -> INGRESOS DE ACTIVIDADES ORDINARIAS | G101: =IFERROR(VLOOKUP($E101,Casilleros!$A$4:$I$830,9,FALSE),"") -> PRESTACIONES LOCALES DE SERVICIOS_Gravadas con tarifa 0% de iva o exentas de IVA__ | H101: =IFERROR(VLOOKUP($E101,Casilleros!$A$4:$J$830,10,FALSE),"") -> Ingresos de actividades ordinarias | I101: =SUMIF(#REF!,$B101,#REF!) -> #REF! | J101: =SUMIF(#REF!,$B101,#REF!) -> #REF! | K101: =+D101+SUM(I101:J101) -> #REF! | L101: =IF(E101="",K101,0) -> 0
A102: =ROW(A102)-7 -> 95 | B102: 4.1.02.03.06 | C102: SERVICIOS EDUCATIVOS | D102: =+#REF! -> #REF! | E102: 6007 | F102: =IFERROR(VLOOKUP($E102,Casilleros!$A$4:$I$830,4,FALSE),"") -> INGRESOS DE ACTIVIDADES ORDINARIAS | G102: =IFERROR(VLOOKUP($E102,Casilleros!$A$4:$I$830,9,FALSE),"") -> PRESTACIONES LOCALES DE SERVICIOS_Gravadas con tarifa 0% de iva o exentas de IVA__ | H102: =IFERROR(VLOOKUP($E102,Casilleros!$A$4:$J$830,10,FALSE),"") -> Ingresos de actividades ordinarias | I102: =SUMIF(#REF!,$B102,#REF!) -> #REF! | J102: =SUMIF(#REF!,$B102,#REF!) -> #REF! | K102: =+D102+SUM(I102:J102) -> #REF! | L102: =IF(E102="",K102,0) -> 0
A103: =ROW(A103)-7 -> 96 | B103: 4.1.02.03.10 | C103: DESCUENTO EN VENTAS | D103: =+#REF! -> #REF! | E103: 6007 | F103: =IFERROR(VLOOKUP($E103,Casilleros!$A$4:$I$830,4,FALSE),"") -> INGRESOS DE ACTIVIDADES ORDINARIAS | G103: =IFERROR(VLOOKUP($E103,Casilleros!$A$4:$I$830,9,FALSE),"") -> PRESTACIONES LOCALES DE SERVICIOS_Gravadas con tarifa 0% de iva o exentas de IVA__ | H103: =IFERROR(VLOOKUP($E103,Casilleros!$A$4:$J$830,10,FALSE),"") -> Ingresos de actividades ordinarias | I103: =SUMIF(#REF!,$B103,#REF!) -> #REF! | J103: =SUMIF(#REF!,$B103,#REF!) -> #REF! | K103: =+D103+SUM(I103:J103) -> #REF! | L103: =IF(E103="",K103,0) -> 0
A104: =ROW(A104)-7 -> 97 | B104: =+#REF! -> #REF! | C104: =+#REF! -> #REF! | D104: =+#REF! -> #REF! | E104: 6007 | F104: =IFERROR(VLOOKUP($E104,Casilleros!$A$4:$I$830,4,FALSE),"") -> INGRESOS DE ACTIVIDADES ORDINARIAS | G104: =IFERROR(VLOOKUP($E104,Casilleros!$A$4:$I$830,9,FALSE),"") -> PRESTACIONES LOCALES DE SERVICIOS_Gravadas con tarifa 0% de iva o exentas de IVA__ | H104: =IFERROR(VLOOKUP($E104,Casilleros!$A$4:$J$830,10,FALSE),"") -> Ingresos de actividades ordinarias | I104: =SUMIF(#REF!,$B104,#REF!) -> #REF! | J104: =SUMIF(#REF!,$B104,#REF!) -> #REF! | K104: =+D104+SUM(I104:J104) -> #REF! | L104: =IF(E104="",K104,0) -> 0
A105: =ROW(A105)-7 -> 98 | B105: 4.2.01.01 | C105: AUSPICIOS | D105: =+#REF! -> #REF! | E105: 6005 | F105: =IFERROR(VLOOKUP($E105,Casilleros!$A$4:$I$830,4,FALSE),"") -> INGRESOS DE ACTIVIDADES ORDINARIAS | G105: =IFERROR(VLOOKUP($E105,Casilleros!$A$4:$I$830,9,FALSE),"") -> PRESTACIONES LOCALES DE SERVICIOS_Gravadas con tarifa diferente de 0% de IVA__ | H105: =IFERROR(VLOOKUP($E105,Casilleros!$A$4:$J$830,10,FALSE),"") -> Ingresos de actividades ordinarias | I105: =SUMIF(#REF!,$B105,#REF!) -> #REF! | J105: =SUMIF(#REF!,$B105,#REF!) -> #REF! | K105: =+D105+SUM(I105:J105) -> #REF! | L105: =IF(E105="",K105,0) -> 0
A106: =ROW(A106)-7 -> 99 | B106: 4.2.01.02 | C106: LICENCIA IDUKAY | D106: =+#REF! -> #REF! | E106: 6005 | F106: =IFERROR(VLOOKUP($E106,Casilleros!$A$4:$I$830,4,FALSE),"") -> INGRESOS DE ACTIVIDADES ORDINARIAS | G106: =IFERROR(VLOOKUP($E106,Casilleros!$A$4:$I$830,9,FALSE),"") -> PRESTACIONES LOCALES DE SERVICIOS_Gravadas con tarifa diferente de 0% de IVA__ | H106: =IFERROR(VLOOKUP($E106,Casilleros!$A$4:$J$830,10,FALSE),"") -> Ingresos de actividades ordinarias | I106: =SUMIF(#REF!,$B106,#REF!) -> #REF! | J106: =SUMIF(#REF!,$B106,#REF!) -> #REF! | K106: =+D106+SUM(I106:J106) -> #REF! | L106: =IF(E106="",K106,0) -> 0
A107: =ROW(A107)-7 -> 100 | B107: 4.2.01.05 | C107: ARRIENDO | D107: =+#REF! -> #REF! | E107: 6005 | F107: =IFERROR(VLOOKUP($E107,Casilleros!$A$4:$I$830,4,FALSE),"") -> INGRESOS DE ACTIVIDADES ORDINARIAS | G107: =IFERROR(VLOOKUP($E107,Casilleros!$A$4:$I$830,9,FALSE),"") -> PRESTACIONES LOCALES DE SERVICIOS_Gravadas con tarifa diferente de 0% de IVA__ | H107: =IFERROR(VLOOKUP($E107,Casilleros!$A$4:$J$830,10,FALSE),"") -> Ingresos de actividades ordinarias | I107: =SUMIF(#REF!,$B107,#REF!) -> #REF! | J107: =SUMIF(#REF!,$B107,#REF!) -> #REF! | K107: =+D107+SUM(I107:J107) -> #REF! | L107: =IF(E107="",K107,0) -> 0
A108: =ROW(A108)-7 -> 101 | B108: 4.2.01.06 | C108: VENTA DE ACTIVOS FIJOS 12% | D108: =+#REF! -> #REF! | E108: 6005 | F108: =IFERROR(VLOOKUP($E108,Casilleros!$A$4:$I$830,4,FALSE),"") -> INGRESOS DE ACTIVIDADES ORDINARIAS | G108: =IFERROR(VLOOKUP($E108,Casilleros!$A$4:$I$830,9,FALSE),"") -> PRESTACIONES LOCALES DE SERVICIOS_Gravadas con tarifa diferente de 0% de IVA__ | H108: =IFERROR(VLOOKUP($E108,Casilleros!$A$4:$J$830,10,FALSE),"") -> Ingresos de actividades ordinarias | I108: =SUMIF(#REF!,$B108,#REF!) -> #REF! | J108: =SUMIF(#REF!,$B108,#REF!) -> #REF! | K108: =+D108+SUM(I108:J108) -> #REF! | L108: =IF(E108="",K108,0) -> 0
A109: =ROW(A109)-7 -> 102 | B109: 4.3.02.01 | C109: INTERESES GANADOS | D109: =+#REF! -> #REF! | E109: 6115 | F109: =IFERROR(VLOOKUP($E109,Casilleros!$A$4:$I$830,4,FALSE),"") -> INGRESOS FINANCIEROS Y OTROS NO OPERACIONALES | G109: =IFERROR(VLOOKUP($E109,Casilleros!$A$4:$I$830,9,FALSE),"") -> INGRESOS FINANCIEROS_INTERESES CON INSTITUCIONES FINANCIERAS_NO RELACIONADAS_Local | H109: =IFERROR(VLOOKUP($E109,Casilleros!$A$4:$J$830,10,FALSE),"") -> Ingresos financieros y otros no operacionales | I109: =SUMIF(#REF!,$B109,#REF!) -> #REF! | J109: =SUMIF(#REF!,$B109,#REF!) -> #REF! | K109: =+D109+SUM(I109:J109) -> #REF! | L109: =IF(E109="",K109,0) -> 0
A110: =ROW(A110)-7 -> 103 | B110: 4.3.05.02 | C110: OTRAS RENTAS | D110: =+#REF! -> #REF! | E110: 6133 | F110: =IFERROR(VLOOKUP($E110,Casilleros!$A$4:$I$830,4,FALSE),"") -> INGRESOS FINANCIEROS Y OTROS NO OPERACIONALES | G110: =IFERROR(VLOOKUP($E110,Casilleros!$A$4:$I$830,9,FALSE),"") -> Otros | H110: =IFERROR(VLOOKUP($E110,Casilleros!$A$4:$J$830,10,FALSE),"") -> Ingresos financieros y otros no operacionales | I110: =SUMIF(#REF!,$B110,#REF!) -> #REF! | J110: =SUMIF(#REF!,$B110,#REF!) -> #REF! | K110: =+D110+SUM(I110:J110) -> #REF! | L110: =IF(E110="",K110,0) -> 0
A111: =ROW(A111)-7 -> 104 | B111: 5.1.1.01 | C111: TRANSPORTE ESCOLAR | D111: =+#REF! -> #REF! | E111: 7176 | F111: =IFERROR(VLOOKUP($E111,Casilleros!$A$4:$I$830,4,FALSE),"") -> OTROS GASTOS | G111: =IFERROR(VLOOKUP($E111,Casilleros!$A$4:$I$830,9,FALSE),"") -> OTROS GASTOS_Transporte_Gasto | H111: =IFERROR(VLOOKUP($E111,Casilleros!$A$4:$J$830,10,FALSE),"") -> Otros gastos_Gasto | I111: =SUMIF(#REF!,$B111,#REF!) -> #REF! | J111: =SUMIF(#REF!,$B111,#REF!) -> #REF! | K111: =+D111+SUM(I111:J111) -> #REF! | L111: =IF(E111="",K111,0) -> 0
A112: =ROW(A112)-7 -> 105 | B112: 5.2.02.01 | C112: SUELDOS, SALARIOS Y DEMÁS REMUNERACIONES | D112: =+#REF! -> #REF! | E112: 7041 | F112: =IFERROR(VLOOKUP($E112,Casilleros!$A$4:$I$830,4,FALSE),"") -> GASTOS POR BENEFICIOS A LOS EMPLEADOS Y HONORARIOS | G112: =IFERROR(VLOOKUP($E112,Casilleros!$A$4:$I$830,9,FALSE),"") -> GASTOS POR BENEFICIOS A LOS EMPLEADOS Y HONORARIOS_Sueldos, salarios y demás remuneraciones que constituyen materia gravada del iess_Gasto | H112: =IFERROR(VLOOKUP($E112,Casilleros!$A$4:$J$830,10,FALSE),"") -> Gastos por beneficios a los empleados_Gasto | I112: =SUMIF(#REF!,$B112,#REF!) -> #REF! | J112: =SUMIF(#REF!,$B112,#REF!) -> #REF! | K112: =+D112+SUM(I112:J112) -> #REF! | L112: =IF(E112="",K112,0) -> 0
A113: =ROW(A113)-7 -> 106 | B113: 5.2.02.02 | C113: APORTES A LA SEGURIDAD SOCIAL (incluido fondo de reserva) | D113: =+#REF! -> #REF! | E113: 7047 | F113: =IFERROR(VLOOKUP($E113,Casilleros!$A$4:$I$830,4,FALSE),"") -> GASTOS POR BENEFICIOS A LOS EMPLEADOS Y HONORARIOS | G113: =IFERROR(VLOOKUP($E113,Casilleros!$A$4:$I$830,9,FALSE),"") -> GASTOS POR BENEFICIOS A LOS EMPLEADOS Y HONORARIOS_Aporte a la seguridad social (incluye fondo de reserva)_Gasto | H113: =IFERROR(VLOOKUP($E113,Casilleros!$A$4:$J$830,10,FALSE),"") -> Gastos por beneficios a los empleados_Gasto | I113: =SUMIF(#REF!,$B113,#REF!) -> #REF! | J113: =SUMIF(#REF!,$B113,#REF!) -> #REF! | K113: =+D113+SUM(I113:J113) -> #REF! | L113: =IF(E113="",K113,0) -> 0
A114: =ROW(A114)-7 -> 107 | B114: 5.2.02.03.01 | C114: DECIMO TERCER SUELDO | D114: =+#REF! -> #REF! | E114: 7044 | F114: =IFERROR(VLOOKUP($E114,Casilleros!$A$4:$I$830,4,FALSE),"") -> GASTOS POR BENEFICIOS A LOS EMPLEADOS Y HONORARIOS | G114: =IFERROR(VLOOKUP($E114,Casilleros!$A$4:$I$830,9,FALSE),"") -> GASTOS POR BENEFICIOS A LOS EMPLEADOS Y HONORARIOS_Beneficios sociales, indemnizaciones y otras remuneraciones que no constituyen materia gravada del IESS_Gasto | H114: =IFERROR(VLOOKUP($E114,Casilleros!$A$4:$J$830,10,FALSE),"") -> Gastos por beneficios a los empleados_Gasto | I114: =SUMIF(#REF!,$B114,#REF!) -> #REF! | J114: =SUMIF(#REF!,$B114,#REF!) -> #REF! | K114: =+D114+SUM(I114:J114) -> #REF! | L114: =IF(E114="",K114,0) -> 0
A115: =ROW(A115)-7 -> 108 | B115: 5.2.02.03.02 | C115: DECIMO CUARTO SUELDO | D115: =+#REF! -> #REF! | E115: 7044 | F115: =IFERROR(VLOOKUP($E115,Casilleros!$A$4:$I$830,4,FALSE),"") -> GASTOS POR BENEFICIOS A LOS EMPLEADOS Y HONORARIOS | G115: =IFERROR(VLOOKUP($E115,Casilleros!$A$4:$I$830,9,FALSE),"") -> GASTOS POR BENEFICIOS A LOS EMPLEADOS Y HONORARIOS_Beneficios sociales, indemnizaciones y otras remuneraciones que no constituyen materia gravada del IESS_Gasto | H115: =IFERROR(VLOOKUP($E115,Casilleros!$A$4:$J$830,10,FALSE),"") -> Gastos por beneficios a los empleados_Gasto | I115: =SUMIF(#REF!,$B115,#REF!) -> #REF! | J115: =SUMIF(#REF!,$B115,#REF!) -> #REF! | K115: =+D115+SUM(I115:J115) -> #REF! | L115: =IF(E115="",K115,0) -> 0
A116: =ROW(A116)-7 -> 109 | B116: 5.2.02.03.03 | C116: FONDO DE RESERVA | D116: =+#REF! -> #REF! | E116: 7047 | F116: =IFERROR(VLOOKUP($E116,Casilleros!$A$4:$I$830,4,FALSE),"") -> GASTOS POR BENEFICIOS A LOS EMPLEADOS Y HONORARIOS | G116: =IFERROR(VLOOKUP($E116,Casilleros!$A$4:$I$830,9,FALSE),"") -> GASTOS POR BENEFICIOS A LOS EMPLEADOS Y HONORARIOS_Aporte a la seguridad social (incluye fondo de reserva)_Gasto | H116: =IFERROR(VLOOKUP($E116,Casilleros!$A$4:$J$830,10,FALSE),"") -> Gastos por beneficios a los empleados_Gasto | I116: =SUMIF(#REF!,$B116,#REF!) -> #REF! | J116: =SUMIF(#REF!,$B116,#REF!) -> #REF! | K116: =+D116+SUM(I116:J116) -> #REF! | L116: =IF(E116="",K116,0) -> 0
... A125: =ROW(A125)-7 -> 118 | B125: 5.2.02.06 | C125: SERVICIOS PRESTADOS POR TERCEROS | D125: =+#REF! -> #REF! | E125: 7050 | F125: =IFERROR(VLOOKUP($E125,Casilleros!$A$4:$I$830,4,FALSE),"") -> GASTOS POR BENEFICIOS A LOS EMPLEADOS Y HONORARIOS | G125: =IFERROR(VLOOKUP($E125,Casilleros!$A$4:$I$830,9,FALSE),"") -> GASTOS POR BENEFICIOS A LOS EMPLEADOS Y HONORARIOS_Honorarios profesionales y dietas_Gasto | H125: =IFERROR(VLOOKUP($E125,Casilleros!$A$4:$J$830,10,FALSE),"") -> Gastos por beneficios a los empleados_Gasto | I125: =SUMIF(#REF!,$B125,#REF!) -> #REF! | J125: =SUMIF(#REF!,$B125,#REF!) -> #REF! | K125: =+D125+SUM(I125:J125) -> #REF! | L125: =IF(E125="",K125,0) -> 0
A126: =ROW(A126)-7 -> 119 | B126: =+#REF! -> #REF! | C126: =+#REF! -> #REF! | D126: =+#REF! -> #REF! | E126: 7050 | F126: =IFERROR(VLOOKUP($E126,Casilleros!$A$4:$I$830,4,FALSE),"") -> GASTOS POR BENEFICIOS A LOS EMPLEADOS Y HONORARIOS | G126: =IFERROR(VLOOKUP($E126,Casilleros!$A$4:$I$830,9,FALSE),"") -> GASTOS POR BENEFICIOS A LOS EMPLEADOS Y HONORARIOS_Honorarios profesionales y dietas_Gasto | H126: =IFERROR(VLOOKUP($E126,Casilleros!$A$4:$J$830,10,FALSE),"") -> Gastos por beneficios a los empleados_Gasto | I126: =SUMIF(#REF!,$B126,#REF!) -> #REF! | J126: =SUMIF(#REF!,$B126,#REF!) -> #REF! | K126: =+D126+SUM(I126:J126) -> #REF! | L126: =IF(E126="",K126,0) -> 0
A127: =ROW(A127)-7 -> 120 | B127: =+#REF! -> #REF! | C127: =+#REF! -> #REF! | D127: =+#REF! -> #REF! | E127: 7050 | F127: =IFERROR(VLOOKUP($E127,Casilleros!$A$4:$I$830,4,FALSE),"") -> GASTOS POR BENEFICIOS A LOS EMPLEADOS Y HONORARIOS | G127: =IFERROR(VLOOKUP($E127,Casilleros!$A$4:$I$830,9,FALSE),"") -> GASTOS POR BENEFICIOS A LOS EMPLEADOS Y HONORARIOS_Honorarios profesionales y dietas_Gasto | H127: =IFERROR(VLOOKUP($E127,Casilleros!$A$4:$J$830,10,FALSE),"") -> Gastos por beneficios a los empleados_Gasto | I127: =SUMIF(#REF!,$B127,#REF!) -> #REF! | J127: =SUMIF(#REF!,$B127,#REF!) -> #REF! | K127: =+D127+SUM(I127:J127) -> #REF! | L127: =IF(E127="",K127,0) -> 0
A128: =ROW(A128)-7 -> 121 | B128: 5.2.02.08.01 | C128: MANTENIMIENTO EQUIPOS | D128: =+#REF! -> #REF! | E128: 7197 | F128: =IFERROR(VLOOKUP($E128,Casilleros!$A$4:$I$830,4,FALSE),"") -> OTROS GASTOS | G128: =IFERROR(VLOOKUP($E128,Casilleros!$A$4:$I$830,9,FALSE),"") -> OTROS GASTOS_Mantenimiento y reparaciones_Gasto | H128: =IFERROR(VLOOKUP($E128,Casilleros!$A$4:$J$830,10,FALSE),"") -> Otros gastos_Gasto | I128: =SUMIF(#REF!,$B128,#REF!) -> #REF! | J128: =SUMIF(#REF!,$B128,#REF!) -> #REF! | K128: =+D128+SUM(I128:J128) -> #REF! | L128: =IF(E128="",K128,0) -> 0
A129: =ROW(A129)-7 -> 122 | B129: 5.2.02.08.03 | C129: MANTENIMIENTO JARDINES | D129: =+#REF! -> #REF! | E129: 7197 | F129: =IFERROR(VLOOKUP($E129,Casilleros!$A$4:$I$830,4,FALSE),"") -> OTROS GASTOS | G129: =IFERROR(VLOOKUP($E129,Casilleros!$A$4:$I$830,9,FALSE),"") -> OTROS GASTOS_Mantenimiento y reparaciones_Gasto | H129: =IFERROR(VLOOKUP($E129,Casilleros!$A$4:$J$830,10,FALSE),"") -> Otros gastos_Gasto | I129: =SUMIF(#REF!,$B129,#REF!) -> #REF! | J129: =SUMIF(#REF!,$B129,#REF!) -> #REF! | K129: =+D129+SUM(I129:J129) -> #REF! | L129: =IF(E129="",K129,0) -> 0
A130: =ROW(A130)-7 -> 123 | B130: 5.2.02.08.05 | C130: EQUIPOS MENORES | D130: =+#REF! -> #REF! | E130: 7197 | F130: =IFERROR(VLOOKUP($E130,Casilleros!$A$4:$I$830,4,FALSE),"") -> OTROS GASTOS | G130: =IFERROR(VLOOKUP($E130,Casilleros!$A$4:$I$830,9,FALSE),"") -> OTROS GASTOS_Mantenimiento y reparaciones_Gasto | H130: =IFERROR(VLOOKUP($E130,Casilleros!$A$4:$J$830,10,FALSE),"") -> Otros gastos_Gasto | I130: =SUMIF(#REF!,$B130,#REF!) -> #REF! | J130: =SUMIF(#REF!,$B130,#REF!) -> #REF! | K130: =+D130+SUM(I130:J130) -> #REF! | L130: =IF(E130="",K130,0) -> 0
A131: =ROW(A131)-7 -> 124 | B131: 5.2.02.08.06 | C131: MANTENIMIENTO EDIFICIOS | D131: =+#REF! -> #REF! | E131: 7197 | F131: =IFERROR(VLOOKUP($E131,Casilleros!$A$4:$I$830,4,FALSE),"") -> OTROS GASTOS | G131: =IFERROR(VLOOKUP($E131,Casilleros!$A$4:$I$830,9,FALSE),"") -> OTROS GASTOS_Mantenimiento y reparaciones_Gasto | H131: =IFERROR(VLOOKUP($E131,Casilleros!$A$4:$J$830,10,FALSE),"") -> Otros gastos_Gasto | I131: =SUMIF(#REF!,$B131,#REF!) -> #REF! | J131: =SUMIF(#REF!,$B131,#REF!) -> #REF! | K131: =+D131+SUM(I131:J131) -> #REF! | L131: =IF(E131="",K131,0) -> 0
A132: =ROW(A132)-7 -> 125 | B132: 5.2.02.08.07 | C132: LICENCIAS YSOFPWARE | D132: =+#REF! -> #REF! | E132: 7248 | F132: =IFERROR(VLOOKUP($E132,Casilleros!$A$4:$I$830,4,FALSE),"") -> OTROS GASTOS | G132: =IFERROR(VLOOKUP($E132,Casilleros!$A$4:$I$830,9,FALSE),"") -> OTROS GASTOS_Otros_Gasto | H132: =IFERROR(VLOOKUP($E132,Casilleros!$A$4:$J$830,10,FALSE),"") -> Otros gastos_Gasto | I132: =SUMIF(#REF!,$B132,#REF!) -> #REF! | J132: =SUMIF(#REF!,$B132,#REF!) -> #REF! | K132: =+D132+SUM(I132:J132) -> #REF! | L132: =IF(E132="",K132,0) -> 0
...

Sheet F101
A1: =RAZÓN_SOCIAL -> #REF!
A2: Formulario Renta Sociedades
A3: =Ejercicio_fiscal -> #REF!
A5: FORMULARIO RENTA SOCIEDADES
S6: =+N6 -> 0 | T6: =IF(A6<>"",A6,T5) -> 0 | U6: =IF(T5<>T6,"",(IF(B6<>"",B6,U5))) -> 0 | V6: =IF(U5<>U6,"",(IF(C6<>"",C6,V5))) -> 0 | W6: =IF(V5<>V6,"",(IF(D6<>"",D6,W5))) -> 0 | X6: =IF(W5<>W6,"",(IF(E6<>"",E6,X5))) -> 0 | Y6: =IF(X5<>X6,"",(IF(F6<>"",F6,Y5))) -> 0 | Z6: =IF(Y5<>Y6,"",(IF(G6<>"",G6,Z5))) -> 0 | AA6: =IF(X6<>"",CONCATENATE(W6,"_",X6,"_",Y6,"_",Z6,""),CONCATENATE(U6,"_",V6, "_",W6,"")) -> 0_0_0_0
A7: OPERACIONES CON PARTES RELACIONADAS LOCALES Y/O DEL EXTERIOR | S7: =+N7 -> 0 | T7: =IF(A7<>"",A7,T6) -> OPERACIONES CON PARTES RELACIONADAS LOCALES Y/O DEL EXTERIOR | U7: =IF(T6<>T7,"",(IF(B7<>"",B7,U6))) | V7: =IF(U6<>U7,"",(IF(C7<>"",C7,V6))) | W7: =IF(V6<>V7,"",(IF(D7<>"",D7,W6))) | X7: =IF(W6<>W7,"",(IF(E7<>"",E7,X6))) | Y7: =IF(X6<>X7,"",(IF(F7<>"",F7,Y6))) | Z7: =IF(Y6<>Y7,"",(IF(G7<>"",G7,Z6))) | AA7: =IF(X7<>"",CONCATENATE(W7,"_",X7,"_",Y7,"_",Z7,""),CONCATENATE(U7,"_",V7, "_",W7,"")) -> __
B8: CON PARTES RELACIONADAS LOCALES | S8: =+N8 -> 0 | T8: =IF(A8<>"",A8,T7) -> OPERACIONES CON PARTES RELACIONADAS LOCALES Y/O DEL EXTERIOR | U8: =IF(T7<>T8,"",(IF(B8<>"",B8,U7))) -> CON PARTES RELACIONADAS LOCALES | V8: =IF(U7<>U8,"",(IF(C8<>"",C8,V7))) | W8: =IF(V7<>V8,"",(IF(D8<>"",D8,W7))) | X8: =IF(W7<>W8,"",(IF(E8<>"",E8,X7))) | Y8: =IF(X7<>X8,"",(IF(F8<>"",F8,Y7))) | Z8: =IF(Y7<>Y8,"",(IF(G8<>"",G8,Z7))) | AA8: =IF(X8<>"",CONCATENATE(W8,"_",X8,"_",Y8,"_",Z8,""),CONCATENATE(U8,"_",V8, "_",W8,"")) -> CON PARTES RELACIONADAS LOCALES__
C9: Operaciones de activo | N9: 003 | O9: =VLOOKUP(N9,Casilleros!$A$4:$Q$830,17,FALSE) -> #REF! | S9: =+N9 -> 003 | T9: =IF(A9<>"",A9,T8) -> OPERACIONES CON PARTES RELACIONADAS LOCALES Y/O DEL EXTERIOR | U9: =IF(T8<>T9,"",(IF(B9<>"",B9,U8))) -> CON PARTES RELACIONADAS LOCALES | V9: =IF(U8<>U9,"",(IF(C9<>"",C9,V8))) -> Operaciones de activo | W9: =IF(V8<>V9,"",(IF(D9<>"",D9,W8))) | X9: =IF(W8<>W9,"",(IF(E9<>"",E9,X8))) | Y9: =IF(X8<>X9,"",(IF(F9<>"",F9,Y8))) | Z9: =IF(Y8<>Y9,"",(IF(G9<>"",G9,Z8))) | AA9: =IF(X9<>"",CONCATENATE(W9,"_",X9,"_",Y9,"_",Z9,""),CONCATENATE(U9,"_",V9, "_",W9,"")) -> CON PARTES RELACIONADAS LOCALES_Operaciones de activo_
C10: Operaciones de pasivo | N10: 004 | O10: =VLOOKUP(N10,Casilleros!$A$4:$Q$830,17,FALSE) -> #REF! | S10: =+N10 -> 004 | T10: =IF(A10<>"",A10,T9) -> OPERACIONES CON PARTES RELACIONADAS LOCALES Y/O DEL EXTERIOR | U10: =IF(T9<>T10,"",(IF(B10<>"",B10,U9))) -> CON PARTES RELACIONADAS LOCALES | V10: =IF(U9<>U10,"",(IF(C10<>"",C10,V9))) -> Operaciones de pasivo | W10: =IF(V9<>V10,"",(IF(D10<>"",D10,W9))) | X10: =IF(W9<>W10,"",(IF(E10<>"",E10,X9))) | Y10: =IF(X9<>X10,"",(IF(F10<>"",F10,Y9))) | Z10: =IF(Y9<>Y10,"",(IF(G10<>"",G10,Z9))) | AA10: =IF(X10<>"",CONCATENATE(W10,"_",X10,"_",Y10,"_",Z10,""),CONCATENATE(U10,"_",V10, "_",W10,"")) -> CON PARTES RELACIONADAS LOCALES_Operaciones de pasivo_
C11: Operaciones de ingreso | N11: 005 | O11: =VLOOKUP(N11,Casilleros!$A$4:$Q$830,17,FALSE) -> #REF! | S11: =+N11 -> 005 | T11: =IF(A11<>"",A11,T10) -> OPERACIONES CON PARTES RELACIONADAS LOCALES Y/O DEL EXTERIOR | U11: =IF(T10<>T11,"",(IF(B11<>"",B11,U10))) -> CON PARTES RELACIONADAS LOCALES | V11: =IF(U10<>U11,"",(IF(C11<>"",C11,V10))) -> Operaciones de ingreso | W11: =IF(V10<>V11,"",(IF(D11<>"",D11,W10))) | X11: =IF(W10<>W11,"",(IF(E11<>"",E11,X10))) | Y11: =IF(X10<>X11,"",(IF(F11<>"",F11,Y10))) | Z11: =IF(Y10<>Y11,"",(IF(G11<>"",G11,Z10))) | AA11: =IF(X11<>"",CONCATENATE(W11,"_",X11,"_",Y11,"_",Z11,""),CONCATENATE(U11,"_",V11, "_",W11,"")) -> CON PARTES RELACIONADAS LOCALES_Operaciones de ingreso_
C12: Operaciones de egreso | N12: 006 | O12: =VLOOKUP(N12,Casilleros!$A$4:$Q$830,17,FALSE) -> #REF! | S12: =+N12 -> 006 | T12: =IF(A12<>"",A12,T11) -> OPERACIONES CON PARTES RELACIONADAS LOCALES Y/O DEL EXTERIOR | U12: =IF(T11<>T12,"",(IF(B12<>"",B12,U11))) -> CON PARTES RELACIONADAS LOCALES | V12: =IF(U11<>U12,"",(IF(C12<>"",C12,V11))) -> Operaciones de egreso | W12: =IF(V11<>V12,"",(IF(D12<>"",D12,W11))) | X12: =IF(W11<>W12,"",(IF(E12<>"",E12,X11))) | Y12: =IF(X11<>X12,"",(IF(F12<>"",F12,Y11))) | Z12: =IF(Y11<>Y12,"",(IF(G12<>"",G12,Z11))) | AA12: =IF(X12<>"",CONCATENATE(W12,"_",X12,"_",Y12,"_",Z12,""),CONCATENATE(U12,"_",V12, "_",W12,"")) -> CON PARTES RELACIONADAS LOCALES_Operaciones de egreso_
C13: Operaciones de regalías, servicios técnicos, administrativos, de consultoría y similares | N13: 007 | O13: =VLOOKUP(N13,Casilleros!$A$4:$Q$830,17,FALSE) -> #REF! | S13: =+N13 -> 007 | T13: =IF(A13<>"",A13,T12) -> OPERACIONES CON PARTES RELACIONADAS LOCALES Y/O DEL EXTERIOR | U13: =IF(T12<>T13,"",(IF(B13<>"",B13,U12))) -> CON PARTES RELACIONADAS LOCALES | V13: =IF(U12<>U13,"",(IF(C13<>"",C13,V12))) -> Operaciones de regalías, servicios técnicos, administrativos, de consultoría y similares | W13: =IF(V12<>V13,"",(IF(D13<>"",D13,W12))) | X13: =IF(W12<>W13,"",(IF(E13<>"",E13,X12))) | Y13: =IF(X12<>X13,"",(IF(F13<>"",F13,Y12))) | Z13: =IF(Y12<>Y13,"",(IF(G13<>"",G13,Z12))) | AA13: =IF(X13<>"",CONCATENATE(W13,"_",X13,"_",Y13,"_",Z13,""),CONCATENATE(U13,"_",V13, "_",W13,"")) -> CON PARTES RELACIONADAS LOCALES_Operaciones de regalías, servicios técnicos, administrativos, de consultoría y similares_
B14: CON PARTES RELACIONADAS EN PARAÍSOS FISCALES, JURISDICCIONES DE MENOR IMPOSICIÓN Y RÉGIMENES FISCALES PREFERENTES | S14: =+N14 -> 0 | T14: =IF(A14<>"",A14,T13) -> OPERACIONES CON PARTES RELACIONADAS LOCALES Y/O DEL EXTERIOR | U14: =IF(T13<>T14,"",(IF(B14<>"",B14,U13))) -> CON PARTES RELACIONADAS EN PARAÍSOS FISCALES, JURISDICCIONES DE MENOR IMPOSICIÓN Y RÉGIMENES FISCALES PREFERENTES | V14: =IF(U13<>U14,"",(IF(C14<>"",C14,V13))) | W14: =IF(V13<>V14,"",(IF(D14<>"",D14,W13))) | X14: =IF(W13<>W14,"",(IF(E14<>"",E14,X13))) | Y14: =IF(X13<>X14,"",(IF(F14<>"",F14,Y13))) | Z14: =IF(Y13<>Y14,"",(IF(G14<>"",G14,Z13))) | AA14: =IF(X14<>"",CONCATENATE(W14,"_",X14,"_",Y14,"_",Z14,""),CONCATENATE(U14,"_",V14, "_",W14,"")) -> CON PARTES RELACIONADAS EN PARAÍSOS FISCALES, JURISDICCIONES DE MENOR IMPOSICIÓN Y RÉGIMENES FISCALES PREFERENTES__
C15: Operaciones de activo | N15: 008 | O15: =VLOOKUP(N15,Casilleros!$A$4:$Q$830,17,FALSE) -> #REF! | S15: =+N15 -> 008 | T15: =IF(A15<>"",A15,T14) -> OPERACIONES CON PARTES RELACIONADAS LOCALES Y/O DEL EXTERIOR | U15: =IF(T14<>T15,"",(IF(B15<>"",B15,U14))) -> CON PARTES RELACIONADAS EN PARAÍSOS FISCALES, JURISDICCIONES DE MENOR IMPOSICIÓN Y RÉGIMENES FISCALES PREFERENTES | V15: =IF(U14<>U15,"",(IF(C15<>"",C15,V14))) -> Operaciones de activo | W15: =IF(V14<>V15,"",(IF(D15<>"",D15,W14))) | X15: =IF(W14<>W15,"",(IF(E15<>"",E15,X14))) | Y15: =IF(X14<>X15,"",(IF(F15<>"",F15,Y14))) | Z15: =IF(Y14<>Y15,"",(IF(G15<>"",G15,Z14))) | AA15: =IF(X15<>"",CONCATENATE(W15,"_",X15,"_",Y15,"_",Z15,""),CONCATENATE(U15,"_",V15, "_",W15,"")) -> CON PARTES RELACIONADAS EN PARAÍSOS FISCALES, JURISDICCIONES DE MENOR IMPOSICIÓN Y RÉGIMENES FISCALES PREFERENTES_Operaciones de activo_
C16: Operaciones de pasivo | N16: 009 | O16: =VLOOKUP(N16,Casilleros!$A$4:$Q$830,17,FALSE) -> #REF! | S16: =+N16 -> 009 | T16: =IF(A16<>"",A16,T15) -> OPERACIONES CON PARTES RELACIONADAS LOCALES Y/O DEL EXTERIOR | U16: =IF(T15<>T16,"",(IF(B16<>"",B16,U15))) -> CON PARTES RELACIONADAS EN PARAÍSOS FISCALES, JURISDICCIONES DE MENOR IMPOSICIÓN Y RÉGIMENES FISCALES PREFERENTES | V16: =IF(U15<>U16,"",(IF(C16<>"",C16,V15))) -> Operaciones de pasivo | W16: =IF(V15<>V16,"",(IF(D16<>"",D16,W15))) | X16: =IF(W15<>W16,"",(IF(E16<>"",E16,X15))) | Y16: =IF(X15<>X16,"",(IF(F16<>"",F16,Y15))) | Z16: =IF(Y15<>Y16,"",(IF(G16<>"",G16,Z15))) | AA16: =IF(X16<>"",CONCATENATE(W16,"_",X16,"_",Y16,"_",Z16,""),CONCATENATE(U16,"_",V16, "_",W16,"")) -> CON PARTES RELACIONADAS EN PARAÍSOS FISCALES, JURISDICCIONES DE MENOR IMPOSICIÓN Y RÉGIMENES FISCALES PREFERENTES_Operaciones de pasivo_
C17: Operaciones de ingreso | N17: 010 | O17: =VLOOKUP(N17,Casilleros!$A$4:$Q$830,17,FALSE) -> #REF! | S17: =+N17 -> 010 | T17: =IF(A17<>"",A17,T16) -> OPERACIONES CON PARTES RELACIONADAS LOCALES Y/O DEL EXTERIOR | U17: =IF(T16<>T17,"",(IF(B17<>"",B17,U16))) -> CON PARTES RELACIONADAS EN PARAÍSOS FISCALES, JURISDICCIONES DE MENOR IMPOSICIÓN Y RÉGIMENES FISCALES PREFERENTES | V17: =IF(U16<>U17,"",(IF(C17<>"",C17,V16))) -> Operaciones de ingreso | W17: =IF(V16<>V17,"",(IF(D17<>"",D17,W16))) | X17: =IF(W16<>W17,"",(IF(E17<>"",E17,X16))) | Y17: =IF(X16<>X17,"",(IF(F17<>"",F17,Y16))) | Z17: =IF(Y16<>Y17,"",(IF(G17<>"",G17,Z16))) | AA17: =IF(X17<>"",CONCATENATE(W17,"_",X17,"_",Y17,"_",Z17,""),CONCATENATE(U17,"_",V17, "_",W17,"")) -> CON PARTES RELACIONADAS EN PARAÍSOS FISCALES, JURISDICCIONES DE MENOR IMPOSICIÓN Y RÉGIMENES FISCALES PREFERENTES_Operaciones de ingreso_
C18: Operaciones de egreso | N18: 011 | O18: =VLOOKUP(N18,Casilleros!$A$4:$Q$830,17,FALSE) -> #REF! | S18: =+N18 -> 011 | T18: =IF(A18<>"",A18,T17) -> OPERACIONES CON PARTES RELACIONADAS LOCALES Y/O DEL EXTERIOR | U18: =IF(T17<>T18,"",(IF(B18<>"",B18,U17))) -> CON PARTES RELACIONADAS EN PARAÍSOS FISCALES, JURISDICCIONES DE MENOR IMPOSICIÓN Y RÉGIMENES FISCALES PREFERENTES | V18: =IF(U17<>U18,"",(IF(C18<>"",C18,V17))) -> Operaciones de egreso | W18: =IF(V17<>V18,"",(IF(D18<>"",D18,W17))) | X18: =IF(W17<>W18,"",(IF(E18<>"",E18,X17))) | Y18: =IF(X17<>X18,"",(IF(F18<>"",F18,Y17))) | Z18: =IF(Y17<>Y18,"",(IF(G18<>"",G18,Z17))) | AA18: =IF(X18<>"",CONCATENATE(W18,"_",X18,"_",Y18,"_",Z18,""),CONCATENATE(U18,"_",V18, "_",W18,"")) -> CON PARTES RELACIONADAS EN PARAÍSOS FISCALES, JURISDICCIONES DE MENOR IMPOSICIÓN Y RÉGIMENES FISCALES PREFERENTES_Operaciones de egreso_
C19: Operaciones de regalías, servicios técnicos, administrativos, de consultoría y similares | N19: 012 | O19: =VLOOKUP(N19,Casilleros!$A$4:$Q$830,17,FALSE) -> #REF! | S19: =+N19 -> 012 | T19: =IF(A19<>"",A19,T18) -> OPERACIONES CON PARTES RELACIONADAS LOCALES Y/O DEL EXTERIOR | U19: =IF(T18<>T19,"",(IF(B19<>"",B19,U18))) -> CON PARTES RELACIONADAS EN PARAÍSOS FISCALES, JURISDICCIONES DE MENOR IMPOSICIÓN Y RÉGIMENES FISCALES PREFERENTES | V19: =IF(U18<>U19,"",(IF(C19<>"",C19,V18))) -> Operaciones de regalías, servicios técnicos, administrativos, de consultoría y similares | W19: =IF(V18<>V19,"",(IF(D19<>"",D19,W18))) | X19: =IF(W18<>W19,"",(IF(E19<>"",E19,X18))) | Y19: =IF(X18<>X19,"",(IF(F19<>"",F19,Y18))) | Z19: =IF(Y18<>Y19,"",(IF(G19<>"",G19,Z18))) | AA19: =IF(X19<>"",CONCATENATE(W19,"_",X19,"_",Y19,"_",Z19,""),CONCATENATE(U19,"_",V19, "_",W19,"")) -> CON PARTES RELACIONADAS EN PARAÍSOS FISCALES, JURISDICCIONES DE MENOR IMPOSICIÓN Y RÉGIMENES FISCALES PREFERENTES_Operaciones de regalías, servicios técnicos, administrativos, de consultoría y similares_
B20: CON PARTES RELACIONADAS EN OTRAS JURISDICCIONES O RÉGIMENES DEL EXTERIOR | S20: =+N20 -> 0 | T20: =IF(A20<>"",A20,T19) -> OPERACIONES CON PARTES RELACIONADAS LOCALES Y/O DEL EXTERIOR | U20: =IF(T19<>T20,"",(IF(B20<>"",B20,U19))) -> CON PARTES RELACIONADAS EN OTRAS JURISDICCIONES O RÉGIMENES DEL EXTERIOR | V20: =IF(U19<>U20,"",(IF(C20<>"",C20,V19))) | W20: =IF(V19<>V20,"",(IF(D20<>"",D20,W19))) | X20: =IF(W19<>W20,"",(IF(E20<>"",E20,X19))) | Y20: =IF(X19<>X20,"",(IF(F20<>"",F20,Y19))) | Z20: =IF(Y19<>Y20,"",(IF(G20<>"",G20,Z19))) | AA20: =IF(X20<>"",CONCATENATE(W20,"_",X20,"_",Y20,"_",Z20,""),CONCATENATE(U20,"_",V20, "_",W20,"")) -> CON PARTES RELACIONADAS EN OTRAS JURISDICCIONES O RÉGIMENES DEL EXTERIOR__
C21: Operaciones de activo | N21: 013 | O21: =VLOOKUP(N21,Casilleros!$A$4:$Q$830,17,FALSE) -> #REF! | S21: =+N21 -> 013 | T21: =IF(A21<>"",A21,T20) -> OPERACIONES CON PARTES RELACIONADAS LOCALES Y/O DEL EXTERIOR | U21: =IF(T20<>T21,"",(IF(B21<>"",B21,U20))) -> CON PARTES RELACIONADAS EN OTRAS JURISDICCIONES O RÉGIMENES DEL EXTERIOR | V21: =IF(U20<>U21,"",(IF(C21<>"",C21,V20))) -> Operaciones de activo | W21: =IF(V20<>V21,"",(IF(D21<>"",D21,W20))) | X21: =IF(W20<>W21,"",(IF(E21<>"",E21,X20))) | Y21: =IF(X20<>X21,"",(IF(F21<>"",F21,Y20))) | Z21: =IF(Y20<>Y21,"",(IF(G21<>"",G21,Z20))) | AA21: =IF(X21<>"",CONCATENATE(W21,"_",X21,"_",Y21,"_",Z21,""),CONCATENATE(U21,"_",V21, "_",W21,"")) -> CON PARTES RELACIONADAS EN OTRAS JURISDICCIONES O RÉGIMENES DEL EXTERIOR_Operaciones de activo_
C22: Operaciones de pasivo | N22: 014 | O22: =VLOOKUP(N22,Casilleros!$A$4:$Q$830,17,FALSE) -> #REF! | S22: =+N22 -> 014 | T22: =IF(A22<>"",A22,T21) -> OPERACIONES CON PARTES RELACIONADAS LOCALES Y/O DEL EXTERIOR | U22: =IF(T21<>T22,"",(IF(B22<>"",B22,U21))) -> CON PARTES RELACIONADAS EN OTRAS JURISDICCIONES O RÉGIMENES DEL EXTERIOR | V22: =IF(U21<>U22,"",(IF(C22<>"",C22,V21))) -> Operaciones de pasivo | W22: =IF(V21<>V22,"",(IF(D22<>"",D22,W21))) | X22: =IF(W21<>W22,"",(IF(E22<>"",E22,X21))) | Y22: =IF(X21<>X22,"",(IF(F22<>"",F22,Y21))) | Z22: =IF(Y21<>Y22,"",(IF(G22<>"",G22,Z21))) | AA22: =IF(X22<>"",CONCATENATE(W22,"_",X22,"_",Y22,"_",Z22,""),CONCATENATE(U22,"_",V22, "_",W22,"")) -> CON PARTES RELACIONADAS EN OTRAS JURISDICCIONES O RÉGIMENES DEL EXTERIOR_Operaciones de pasivo_
C23: Operaciones de ingreso | N23: 015 | O23: =VLOOKUP(N23,Casilleros!$A$4:$Q$830,17,FALSE) -> #REF! | S23: =+N23 -> 015 | T23: =IF(A23<>"",A23,T22) -> OPERACIONES CON PARTES RELACIONADAS LOCALES Y/O DEL EXTERIOR | U23: =IF(T22<>T23,"",(IF(B23<>"",B23,U22))) -> CON PARTES RELACIONADAS EN OTRAS JURISDICCIONES O RÉGIMENES DEL EXTERIOR | V23: =IF(U22<>U23,"",(IF(C23<>"",C23,V22))) -> Operaciones de ingreso | W23: =IF(V22<>V23,"",(IF(D23<>"",D23,W22))) | X23: =IF(W22<>W23,"",(IF(E23<>"",E23,X22))) | Y23: =IF(X22<>X23,"",(IF(F23<>"",F23,Y22))) | Z23: =IF(Y22<>Y23,"",(IF(G23<>"",G23,Z22))) | AA23: =IF(X23<>"",CONCATENATE(W23,"_",X23,"_",Y23,"_",Z23,""),CONCATENATE(U23,"_",V23, "_",W23,"")) -> CON PARTES RELACIONADAS EN OTRAS JURISDICCIONES O RÉGIMENES DEL EXTERIOR_Operaciones de ingreso_
C24: Operaciones de egreso | N24: 016 | O24: =VLOOKUP(N24,Casilleros!$A$4:$Q$830,17,FALSE) -> #REF! | S24: =+N24 -> 016 | T24: =IF(A24<>"",A24,T23) -> OPERACIONES CON PARTES RELACIONADAS LOCALES Y/O DEL EXTERIOR | U24: =IF(T23<>T24,"",(IF(B24<>"",B24,U23))) -> CON PARTES RELACIONADAS EN OTRAS JURISDICCIONES O RÉGIMENES DEL EXTERIOR | V24: =IF(U23<>U24,"",(IF(C24<>"",C24,V23))) -> Operaciones de egreso | W24: =IF(V23<>V24,"",(IF(D24<>"",D24,W23))) | X24: =IF(W23<>W24,"",(IF(E24<>"",E24,X23))) | Y24: =IF(X23<>X24,"",(IF(F24<>"",F24,Y23))) | Z24: =IF(Y23<>Y24,"",(IF(G24<>"",G24,Z23))) | AA24: =IF(X24<>"",CONCATENATE(W24,"_",X24,"_",Y24,"_",Z24,""),CONCATENATE(U24,"_",V24, "_",W24,"")) -> CON PARTES RELACIONADAS EN OTRAS JURISDICCIONES O RÉGIMENES DEL EXTERIOR_Operaciones de egreso_
C25: Operaciones de regalías, servicios técnicos, administrativos, de consultoría y similares | N25: 017 | O25: =VLOOKUP(N25,Casilleros!$A$4:$Q$830,17,FALSE) -> #REF! | S25: =+N25 -> 017 | T25: =IF(A25<>"",A25,T24) -> OPERACIONES CON PARTES RELACIONADAS LOCALES Y/O DEL EXTERIOR | U25: =IF(T24<>T25,"",(IF(B25<>"",B25,U24))) -> CON PARTES RELACIONADAS EN OTRAS JURISDICCIONES O RÉGIMENES DEL EXTERIOR | V25: =IF(U24<>U25,"",(IF(C25<>"",C25,V24))) -> Operaciones de regalías, servicios técnicos, administrativos, de consultoría y similares | W25: =IF(V24<>V25,"",(IF(D25<>"",D25,W24))) | X25: =IF(W24<>W25,"",(IF(E25<>"",E25,X24))) | Y25: =IF(X24<>X25,"",(IF(F25<>"",F25,Y24))) | Z25: =IF(Y24<>Y25,"",(IF(G25<>"",G25,Z24))) | AA25: =IF(X25<>"",CONCATENATE(W25,"_",X25,"_",Y25,"_",Z25,""),CONCATENATE(U25,"_",V25, "_",W25,"")) -> CON PARTES RELACIONADAS EN OTRAS JURISDICCIONES O RÉGIMENES DEL EXTERIOR_Operaciones de regalías, servicios técnicos, administrativos, de consultoría y similares_
B26: TOTAL OPERACIONES CON PARTES RELACIONADAS | N26: 029 | O26: =SUM(O9:O13)+SUM(O15:O19)+SUM(O21:O25) -> #REF! | S26: =+N26 -> 029 | T26: =IF(A26<>"",A26,T25) -> OPERACIONES CON PARTES RELACIONADAS LOCALES Y/O DEL EXTERIOR | U26: =IF(T25<>T26,"",(IF(B26<>"",B26,U25))) -> TOTAL OPERACIONES CON PARTES RELACIONADAS | V26: =IF(U25<>U26,"",(IF(C26<>"",C26,V25))) | W26: =IF(V25<>V26,"",(IF(D26<>"",D26,W25))) | X26: =IF(W25<>W26,"",(IF(E26<>"",E26,X25))) | Y26: =IF(X25<>X26,"",(IF(F26<>"",F26,Y25))) | Z26: =IF(Y25<>Y26,"",(IF(G26<>"",G26,Z25))) | AA26: =IF(X26<>"",CONCATENATE(W26,"_",X26,"_",Y26,"_",Z26,""),CONCATENATE(U26,"_",V26, "_",W26,"")) -> TOTAL OPERACIONES CON PARTES RELACIONADAS__
B27: ¿Sujeto pasivo exento de aplicación del régimen de precios de transferencia? | N27: 030 | S27: =+N27 -> 030 | T27: =IF(A27<>"",A27,T26) -> OPERACIONES CON PARTES RELACIONADAS LOCALES Y/O DEL EXTERIOR | U27: =IF(T26<>T27,"",(IF(B27<>"",B27,U26))) -> ¿Sujeto pasivo exento de aplicación del régimen de precios de transferencia? | V27: =IF(U26<>U27,"",(IF(C27<>"",C27,V26))) | W27: =IF(V26<>V27,"",(IF(D27<>"",D27,W26))) | X27: =IF(W26<>W27,"",(IF(E27<>"",E27,X26))) | Y27: =IF(X26<>X27,"",(IF(F27<>"",F27,Y26))) | Z27: =IF(Y26<>Y27,"",(IF(G27<>"",G27,Z26))) | AA27: =IF(X27<>"",CONCATENATE(W27,"_",X27,"_",Y27,"_",Z27,""),CONCATENATE(U27,"_",V27, "_",W27,"")) -> ¿Sujeto pasivo exento de aplicación del régimen de precios de transferencia?__
A28: ESTADO DE SITUACIÓN FINANCIERA | S28: =+N28 -> 0 | T28: =IF(A28<>"",A28,T27) -> ESTADO DE SITUACIÓN FINANCIERA | U28: =IF(T27<>T28,"",(IF(B28<>"",B28,U27))) | V28: =IF(U27<>U28,"",(IF(C28<>"",C28,V27))) | W28: =IF(V27<>V28,"",(IF(D28<>"",D28,W27))) | X28: =IF(W27<>W28,"",(IF(E28<>"",E28,X27))) | Y28: =IF(X27<>X28,"",(IF(F28<>"",F28,Y27))) | Z28: =IF(Y27<>Y28,"",(IF(G28<>"",G28,Z27))) | AA28: =IF(X28<>"",CONCATENATE(W28,"_",X28,"_",Y28,"_",Z28,""),CONCATENATE(U28,"_",V28, "_",W28,"")) -> __
B29: ACTIVO | S29: =+N29 -> 0 | T29: =IF(A29<>"",A29,T28) -> ESTADO DE SITUACIÓN FINANCIERA | U29: =IF(T28<>T29,"",(IF(B29<>"",B29,U28))) -> ACTIVO | V29: =IF(U28<>U29,"",(IF(C29<>"",C29,V28))) | W29: =IF(V28<>V29,"",(IF(D29<>"",D29,W28))) | X29: =IF(W28<>W29,"",(IF(E29<>"",E29,X28))) | Y29: =IF(X28<>X29,"",(IF(F29<>"",F29,Y28))) | Z29: =IF(Y28<>Y29,"",(IF(G29<>"",G29,Z28))) | AA29: =IF(X29<>"",CONCATENATE(W29,"_",X29,"_",Y29,"_",Z29,""),CONCATENATE(U29,"_",V29, "_",W29,"")) -> ACTIVO__
C30: ACTIVOS CORRIENTES | S30: =+N30 -> 0 | T30: =IF(A30<>"",A30,T29) -> ESTADO DE SITUACIÓN FINANCIERA | U30: =IF(T29<>T30,"",(IF(B30<>"",B30,U29))) -> ACTIVO | V30: =IF(U29<>U30,"",(IF(C30<>"",C30,V29))) -> ACTIVOS CORRIENTES | W30: =IF(V29<>V30,"",(IF(D30<>"",D30,W29))) | X30: =IF(W29<>W30,"",(IF(E30<>"",E30,X29))) | Y30: =IF(X29<>X30,"",(IF(F30<>"",F30,Y29))) | Z30: =IF(Y29<>Y30,"",(IF(G30<>"",G30,Z29))) | AA30: =IF(X30<>"",CONCATENATE(W30,"_",X30,"_",Y30,"_",Z30,""),CONCATENATE(U30,"_",V30, "_",W30,"")) -> ACTIVO_ACTIVOS CORRIENTES_
D31: Efectivo y equivalentes al efectivo | N31: 311 | O31: =VLOOKUP(N31,Casilleros!$A$4:$Q$830,17,FALSE) -> #REF! | S31: =+N31 -> 311 | T31: =IF(A31<>"",A31,T30) -> ESTADO DE SITUACIÓN FINANCIERA | U31: =IF(T30<>T31,"",(IF(B31<>"",B31,U30))) -> ACTIVO | V31: =IF(U30<>U31,"",(IF(C31<>"",C31,V30))) -> ACTIVOS CORRIENTES | W31: =IF(V30<>V31,"",(IF(D31<>"",D31,W30))) -> Efectivo y equivalentes al efectivo | X31: =IF(W30<>W31,"",(IF(E31<>"",E31,X30))) | Y31: =IF(X30<>X31,"",(IF(F31<>"",F31,Y30))) | Z31: =IF(Y30<>Y31,"",(IF(G31<>"",G31,Z30))) | AA31: =IF(X31<>"",CONCATENATE(W31,"_",X31,"_",Y31,"_",Z31),W31) -> Efectivo y equivalentes al efectivo
D32: CUENTAS Y DOCUMENTOS POR COBRAR CORRIENTES | S32: =+N32 -> 0 | T32: =IF(A32<>"",A32,T31) -> ESTADO DE SITUACIÓN FINANCIERA | U32: =IF(T31<>T32,"",(IF(B32<>"",B32,U31))) -> ACTIVO | V32: =IF(U31<>U32,"",(IF(C32<>"",C32,V31))) -> ACTIVOS CORRIENTES | W32: =IF(V31<>V32,"",(IF(D32<>"",D32,W31))) -> CUENTAS Y DOCUMENTOS POR COBRAR CORRIENTES | X32: =IF(W31<>W32,"",(IF(E32<>"",E32,X31))) | Y32: =IF(X31<>X32,"",(IF(F32<>"",F32,Y31))) | Z32: =IF(Y31<>Y32,"",(IF(G32<>"",G32,Z31))) | AA32: =IF(X32<>"",CONCATENATE(W32,"_",X32,"_",Y32,"_",Z32),W32) -> CUENTAS Y DOCUMENTOS POR COBRAR CORRIENTES
E33: CUENTAS Y DOCUMENTOS POR COBRAR COMERCIALES CORRIENTES | S33: =+N33 -> 0 | T33: =IF(A33<>"",A33,T32) -> ESTADO DE SITUACIÓN FINANCIERA | U33: =IF(T32<>T33,"",(IF(B33<>"",B33,U32))) -> ACTIVO | V33: =IF(U32<>U33,"",(IF(C33<>"",C33,V32))) -> ACTIVOS CORRIENTES | W33: =IF(V32<>V33,"",(IF(D33<>"",D33,W32))) -> CUENTAS Y DOCUMENTOS POR COBRAR CORRIENTES | X33: =IF(W32<>W33,"",(IF(E33<>"",E33,X32))) -> CUENTAS Y DOCUMENTOS POR COBRAR COMERCIALES CORRIENTES | Y33: =IF(X32<>X33,"",(IF(F33<>"",F33,Y32))) | Z33: =IF(Y32<>Y33,"",(IF(G33<>"",G33,Z32))) | AA33: =IF(X33<>"",CONCATENATE(W33,"_",X33,"_",Y33,"_",Z33),W33) -> CUENTAS Y DOCUMENTOS POR COBRAR CORRIENTES_CUENTAS Y DOCUMENTOS POR COBRAR COMERCIALES CORRIENTES__
F34: RELACIONADAS | S34: =+N34 -> 0 | T34: =IF(A34<>"",A34,T33) -> ESTADO DE SITUACIÓN FINANCIERA | U34: =IF(T33<>T34,"",(IF(B34<>"",B34,U33))) -> ACTIVO | V34: =IF(U33<>U34,"",(IF(C34<>"",C34,V33))) -> ACTIVOS CORRIENTES | W34: =IF(V33<>V34,"",(IF(D34<>"",D34,W33))) -> CUENTAS Y DOCUMENTOS POR COBRAR CORRIENTES | X34: =IF(W33<>W34,"",(IF(E34<>"",E34,X33))) -> CUENTAS Y DOCUMENTOS POR COBRAR COMERCIALES CORRIENTES | Y34: =IF(X33<>X34,"",(IF(F34<>"",F34,Y33))) -> RELACIONADAS | Z34: =IF(Y33<>Y34,"",(IF(G34<>"",G34,Z33))) | AA34: =IF(X34<>"",CONCATENATE(W34,"_",X34,"_",Y34,"_",Z34),W34) -> CUENTAS Y DOCUMENTOS POR COBRAR CORRIENTES_CUENTAS Y DOCUMENTOS POR COBRAR COMERCIALES CORRIENTES_RELACIONADAS_
G35: Locales | N35: 312 | O35: =VLOOKUP(N35,Casilleros!$A$4:$Q$830,17,FALSE) -> #REF! | S35: =+N35 -> 312 | T35: =IF(A35<>"",A35,T34) -> ESTADO DE SITUACIÓN FINANCIERA | U35: =IF(T34<>T35,"",(IF(B35<>"",B35,U34))) -> ACTIVO | V35: =IF(U34<>U35,"",(IF(C35<>"",C35,V34))) -> ACTIVOS CORRIENTES | W35: =IF(V34<>V35,"",(IF(D35<>"",D35,W34))) -> CUENTAS Y DOCUMENTOS POR COBRAR CORRIENTES | X35: =IF(W34<>W35,"",(IF(E35<>"",E35,X34))) -> CUENTAS Y DOCUMENTOS POR COBRAR COMERCIALES CORRIENTES | Y35: =IF(X34<>X35,"",(IF(F35<>"",F35,Y34))) -> RELACIONADAS | Z35: =IF(Y34<>Y35,"",(IF(G35<>"",G35,Z34))) -> Locales | AA35: =IF(X35<>"",CONCATENATE(W35,"_",X35,"_",Y35,"_",Z35),W35) -> CUENTAS Y DOCUMENTOS POR COBRAR CORRIENTES_CUENTAS Y DOCUMENTOS POR COBRAR COMERCIALES CORRIENTES_RELACIONADAS_Locales
G36: Del exterior | N36: 313 | O36: =VLOOKUP(N36,Casilleros!$A$4:$Q$830,17,FALSE) -> #REF! | S36: =+N36 -> 313 | T36: =IF(A36<>"",A36,T35) -> ESTADO DE SITUACIÓN FINANCIERA | U36: =IF(T35<>T36,"",(IF(B36<>"",B36,U35))) -> ACTIVO | V36: =IF(U35<>U36,"",(IF(C36<>"",C36,V35))) -> ACTIVOS CORRIENTES | W36: =IF(V35<>V36,"",(IF(D36<>"",D36,W35))) -> CUENTAS Y DOCUMENTOS POR COBRAR CORRIENTES | X36: =IF(W35<>W36,"",(IF(E36<>"",E36,X35))) -> CUENTAS Y DOCUMENTOS POR COBRAR COMERCIALES CORRIENTES | Y36: =IF(X35<>X36,"",(IF(F36<>"",F36,Y35))) -> RELACIONADAS | Z36: =IF(Y35<>Y36,"",(IF(G36<>"",G36,Z35))) -> Del exterior | AA36: =IF(X36<>"",CONCATENATE(W36,"_",X36,"_",Y36,"_",Z36),W36) -> CUENTAS Y DOCUMENTOS POR COBRAR CORRIENTES_CUENTAS Y DOCUMENTOS POR COBRAR COMERCIALES CORRIENTES_RELACIONADAS_Del exterior
G37: (-) Deterioro acumulado del valor de cuentas y documentos por cobrar comerciales por incobrabilidad (provisiones para créditos incobrables) | N37: 314 | O37: =VLOOKUP(N37,Casilleros!$A$4:$Q$830,17,FALSE) -> #REF! | S37: =+N37 -> 314 | T37: =IF(A37<>"",A37,T36) -> ESTADO DE SITUACIÓN FINANCIERA | U37: =IF(T36<>T37,"",(IF(B37<>"",B37,U36))) -> ACTIVO | V37: =IF(U36<>U37,"",(IF(C37<>"",C37,V36))) -> ACTIVOS CORRIENTES | W37: =IF(V36<>V37,"",(IF(D37<>"",D37,W36))) -> CUENTAS Y DOCUMENTOS POR COBRAR CORRIENTES | X37: =IF(W36<>W37,"",(IF(E37<>"",E37,X36))) -> CUENTAS Y DOCUMENTOS POR COBRAR COMERCIALES CORRIENTES | Y37: =IF(X36<>X37,"",(IF(F37<>"",F37,Y36))) -> RELACIONADAS | Z37: =IF(Y36<>Y37,"",(IF(G37<>"",G37,Z36))) -> (-) Deterioro acumulado del valor de cuentas y documentos por cobrar comerciales por incobrabilidad (provisiones para créditos incobrables) | AA37: =IF(X37<>"",CONCATENATE(W37,"_",X37,"_",Y37,"_",Z37),W37) -> CUENTAS Y DOCUMENTOS POR COBRAR CORRIENTES_CUENTAS Y DOCUMENTOS POR COBRAR COMERCIALES CORRIENTES_RELACIONADAS_(-) Deterioro acumulado del valor de cuentas y documentos por cobrar comerciales por incobrabilidad (provisiones para créditos incobrables)
F38: NO RELACIONADAS | S38: =+N38 -> 0 | T38: =IF(A38<>"",A38,T37) -> ESTADO DE SITUACIÓN FINANCIERA | U38: =IF(T37<>T38,"",(IF(B38<>"",B38,U37))) -> ACTIVO | V38: =IF(U37<>U38,"",(IF(C38<>"",C38,V37))) -> ACTIVOS CORRIENTES | W38: =IF(V37<>V38,"",(IF(D38<>"",D38,W37))) -> CUENTAS Y DOCUMENTOS POR COBRAR CORRIENTES | X38: =IF(W37<>W38,"",(IF(E38<>"",E38,X37))) -> CUENTAS Y DOCUMENTOS POR COBRAR COMERCIALES CORRIENTES | Y38: =IF(X37<>X38,"",(IF(F38<>"",F38,Y37))) -> NO RELACIONADAS | Z38: =IF(Y37<>Y38,"",(IF(G38<>"",G38,Z37))) | AA38: =IF(X38<>"",CONCATENATE(W38,"_",X38,"_",Y38,"_",Z38),W38) -> CUENTAS Y DOCUMENTOS POR COBRAR CORRIENTES_CUENTAS Y DOCUMENTOS POR COBRAR COMERCIALES CORRIENTES_NO RELACIONADAS_
G39: Locales | N39: 315 | O39: =VLOOKUP(N39,Casilleros!$A$4:$Q$830,17,FALSE) -> #REF! | S39: =+N39 -> 315 | T39: =IF(A39<>"",A39,T38) -> ESTADO DE SITUACIÓN FINANCIERA | U39: =IF(T38<>T39,"",(IF(B39<>"",B39,U38))) -> ACTIVO | V39: =IF(U38<>U39,"",(IF(C39<>"",C39,V38))) -> ACTIVOS CORRIENTES | W39: =IF(V38<>V39,"",(IF(D39<>"",D39,W38))) -> CUENTAS Y DOCUMENTOS POR COBRAR CORRIENTES | X39: =IF(W38<>W39,"",(IF(E39<>"",E39,X38))) -> CUENTAS Y DOCUMENTOS POR COBRAR COMERCIALES CORRIENTES | Y39: =IF(X38<>X39,"",(IF(F39<>"",F39,Y38))) -> NO RELACIONADAS | Z39: =IF(Y38<>Y39,"",(IF(G39<>"",G39,Z38))) -> Locales | AA39: =IF(X39<>"",CONCATENATE(W39,"_",X39,"_",Y39,"_",Z39),W39) -> CUENTAS Y DOCUMENTOS POR COBRAR CORRIENTES_CUENTAS Y DOCUMENTOS POR COBRAR COMERCIALES CORRIENTES_NO RELACIONADAS_Locales
G40: Del exterior | N40: 316 | O40: =VLOOKUP(N40,Casilleros!$A$4:$Q$830,17,FALSE) -> #REF! | S40: =+N40 -> 316 | T40: =IF(A40<>"",A40,T39) -> ESTADO DE SITUACIÓN FINANCIERA | U40: =IF(T39<>T40,"",(IF(B40<>"",B40,U39))) -> ACTIVO | V40: =IF(U39<>U40,"",(IF(C40<>"",C40,V39))) -> ACTIVOS CORRIENTES | W40: =IF(V39<>V40,"",(IF(D40<>"",D40,W39))) -> CUENTAS Y DOCUMENTOS POR COBRAR CORRIENTES | X40: =IF(W39<>W40,"",(IF(E40<>"",E40,X39))) -> CUENTAS Y DOCUMENTOS POR COBRAR COMERCIALES CORRIENTES | Y40: =IF(X39<>X40,"",(IF(F40<>"",F40,Y39))) -> NO RELACIONADAS | Z40: =IF(Y39<>Y40,"",(IF(G40<>"",G40,Z39))) -> Del exterior | AA40: =IF(X40<>"",CONCATENATE(W40,"_",X40,"_",Y40,"_",Z40),W40) -> CUENTAS Y DOCUMENTOS POR COBRAR CORRIENTES_CUENTAS Y DOCUMENTOS POR COBRAR COMERCIALES CORRIENTES_NO RELACIONADAS_Del exterior
G41: (-) Deterioro acumulado del valor de cuentas y documentos por cobrar comerciales por incobrabilidad (provisiones para créditos incobrables) | N41: 317 | O41: =VLOOKUP(N41,Casilleros!$A$4:$Q$830,17,FALSE) -> #REF! | S41: =+N41 -> 317 | T41: =IF(A41<>"",A41,T40) -> ESTADO DE SITUACIÓN FINANCIERA | U41: =IF(T40<>T41,"",(IF(B41<>"",B41,U40))) -> ACTIVO | V41: =IF(U40<>U41,"",(IF(C41<>"",C41,V40))) -> ACTIVOS CORRIENTES | W41: =IF(V40<>V41,"",(IF(D41<>"",D41,W40))) -> CUENTAS Y DOCUMENTOS POR COBRAR CORRIENTES | X41: =IF(W40<>W41,"",(IF(E41<>"",E41,X40))) -> CUENTAS Y DOCUMENTOS POR COBRAR COMERCIALES CORRIENTES | Y41: =IF(X40<>X41,"",(IF(F41<>"",F41,Y40))) -> NO RELACIONADAS | Z41: =IF(Y40<>Y41,"",(IF(G41<>"",G41,Z40))) -> (-) Deterioro acumulado del valor de cuentas y documentos por cobrar comerciales por incobrabilidad (provisiones para créditos incobrables) | AA41: =IF(X41<>"",CONCATENATE(W41,"_",X41,"_",Y41,"_",Z41),W41) -> CUENTAS Y DOCUMENTOS POR COBRAR CORRIENTES_CUENTAS Y DOCUMENTOS POR COBRAR COMERCIALES CORRIENTES_NO RELACIONADAS_(-) Deterioro acumulado del valor de cuentas y documentos por cobrar comerciales por incobrabilidad (provisiones para créditos incobrables)
E42: OTRAS CUENTAS Y DOCUMENTOS POR COBRAR CORRIENTES | S42: =+N42 -> 0 | T42: =IF(A42<>"",A42,T41) -> ESTADO DE SITUACIÓN FINANCIERA | U42: =IF(T41<>T42,"",(IF(B42<>"",B42,U41))) -> ACTIVO | V42: =IF(U41<>U42,"",(IF(C42<>"",C42,V41))) -> ACTIVOS CORRIENTES | W42: =IF(V41<>V42,"",(IF(D42<>"",D42,W41))) -> CUENTAS Y DOCUMENTOS POR COBRAR CORRIENTES | X42: =IF(W41<>W42,"",(IF(E42<>"",E42,X41))) -> OTRAS CUENTAS Y DOCUMENTOS POR COBRAR CORRIENTES | Y42: =IF(X41<>X42,"",(IF(F42<>"",F42,Y41))) | Z42: =IF(Y41<>Y42,"",(IF(G42<>"",G42,Z41))) | AA42: =IF(X42<>"",CONCATENATE(W42,"_",X42,"_",Y42,"_",Z42),W42) -> CUENTAS Y DOCUMENTOS POR COBRAR CORRIENTES_OTRAS CUENTAS Y DOCUMENTOS POR COBRAR CORRIENTES__
F43: A ACCIONISTAS, SOCIOS, PARTICIPES, BENEFICIARIOS U OTROS TITULARES DE DERECHOS REPRESENTATIVOS DE CAPITAL | S43: =+N43 -> 0 | T43: =IF(A43<>"",A43,T42) -> ESTADO DE SITUACIÓN FINANCIERA | U43: =IF(T42<>T43,"",(IF(B43<>"",B43,U42))) -> ACTIVO | V43: =IF(U42<>U43,"",(IF(C43<>"",C43,V42))) -> ACTIVOS CORRIENTES | W43: =IF(V42<>V43,"",(IF(D43<>"",D43,W42))) -> CUENTAS Y DOCUMENTOS POR COBRAR CORRIENTES | X43: =IF(W42<>W43,"",(IF(E43<>"",E43,X42))) -> OTRAS CUENTAS Y DOCUMENTOS POR COBRAR CORRIENTES | Y43: =IF(X42<>X43,"",(IF(F43<>"",F43,Y42))) -> A ACCIONISTAS, SOCIOS, PARTICIPES, BENEFICIARIOS U OTROS TITULARES DE DERECHOS REPRESENTATIVOS DE CAPITAL | Z43: =IF(Y42<>Y43,"",(IF(G43<>"",G43,Z42))) | AA43: =IF(X43<>"",CONCATENATE(W43,"_",X43,"_",Y43,"_",Z43),W43) -> CUENTAS Y DOCUMENTOS POR COBRAR CORRIENTES_OTRAS CUENTAS Y DOCUMENTOS POR COBRAR CORRIENTES_A ACCIONISTAS, SOCIOS, PARTICIPES, BENEFICIARIOS U OTROS TITULARES DE DERECHOS REPRESENTATIVOS DE CAPITAL_
G44: Locales | N44: 318 | O44: =VLOOKUP(N44,Casilleros!$A$4:$Q$830,17,FALSE) -> #REF! | S44: =+N44 -> 318 | T44: =IF(A44<>"",A44,T43) -> ESTADO DE SITUACIÓN FINANCIERA | U44: =IF(T43<>T44,"",(IF(B44<>"",B44,U43))) -> ACTIVO | V44: =IF(U43<>U44,"",(IF(C44<>"",C44,V43))) -> ACTIVOS CORRIENTES | W44: =IF(V43<>V44,"",(IF(D44<>"",D44,W43))) -> CUENTAS Y DOCUMENTOS POR COBRAR CORRIENTES | X44: =IF(W43<>W44,"",(IF(E44<>"",E44,X43))) -> OTRAS CUENTAS Y DOCUMENTOS POR COBRAR CORRIENTES | Y44: =IF(X43<>X44,"",(IF(F44<>"",F44,Y43))) -> A ACCIONISTAS, SOCIOS, PARTICIPES, BENEFICIARIOS U OTROS TITULARES DE DERECHOS REPRESENTATIVOS DE CAPITAL | Z44: =IF(Y43<>Y44,"",(IF(G44<>"",G44,Z43))) -> Locales | AA44: =IF(X44<>"",CONCATENATE(W44,"_",X44,"_",Y44,"_",Z44),W44) -> CUENTAS Y DOCUMENTOS POR COBRAR CORRIENTES_OTRAS CUENTAS Y DOCUMENTOS POR COBRAR CORRIENTES_A ACCIONISTAS, SOCIOS, PARTICIPES, BENEFICIARIOS U OTROS TITULARES DE DERECHOS REPRESENTATIVOS DE CAPITAL_Locales
G45: Del exterior | N45: 319 | O45: =VLOOKUP(N45,Casilleros!$A$4:$Q$830,17,FALSE) -> #REF! | S45: =+N45 -> 319 | T45: =IF(A45<>"",A45,T44) -> ESTADO DE SITUACIÓN FINANCIERA | U45: =IF(T44<>T45,"",(IF(B45<>"",B45,U44))) -> ACTIVO | V45: =IF(U44<>U45,"",(IF(C45<>"",C45,V44))) -> ACTIVOS CORRIENTES | W45: =IF(V44<>V45,"",(IF(D45<>"",D45,W44))) -> CUENTAS Y DOCUMENTOS POR COBRAR CORRIENTES | X45: =IF(W44<>W45,"",(IF(E45<>"",E45,X44))) -> OTRAS CUENTAS Y DOCUMENTOS POR COBRAR CORRIENTES | Y45: =IF(X44<>X45,"",(IF(F45<>"",F45,Y44))) -> A ACCIONISTAS, SOCIOS, PARTICIPES, BENEFICIARIOS U OTROS TITULARES DE DERECHOS REPRESENTATIVOS DE CAPITAL | Z45: =IF(Y44<>Y45,"",(IF(G45<>"",G45,Z44))) -> Del exterior | AA45: =IF(X45<>"",CONCATENATE(W45,"_",X45,"_",Y45,"_",Z45),W45) -> CUENTAS Y DOCUMENTOS POR COBRAR CORRIENTES_OTRAS CUENTAS Y DOCUMENTOS POR COBRAR CORRIENTES_A ACCIONISTAS, SOCIOS, PARTICIPES, BENEFICIARIOS U OTROS TITULARES DE DERECHOS REPRESENTATIVOS DE CAPITAL_Del exterior
F46: DIVIDENDOS POR COBRAR | S46: =+N46 -> 0 | T46: =IF(A46<>"",A46,T45) -> ESTADO DE SITUACIÓN FINANCIERA | U46: =IF(T45<>T46,"",(IF(B46<>"",B46,U45))) -> ACTIVO | V46: =IF(U45<>U46,"",(IF(C46<>"",C46,V45))) -> ACTIVOS CORRIENTES | W46: =IF(V45<>V46,"",(IF(D46<>"",D46,W45))) -> CUENTAS Y DOCUMENTOS POR COBRAR CORRIENTES | X46: =IF(W45<>W46,"",(IF(E46<>"",E46,X45))) -> OTRAS CUENTAS Y DOCUMENTOS POR COBRAR CORRIENTES | Y46: =IF(X45<>X46,"",(IF(F46<>"",F46,Y45))) -> DIVIDENDOS POR COBRAR | Z46: =IF(Y45<>Y46,"",(IF(G46<>"",G46,Z45))) | AA46: =IF(X46<>"",CONCATENATE(W46,"_",X46,"_",Y46,"_",Z46),W46) -> CUENTAS Y DOCUMENTOS POR COBRAR CORRIENTES_OTRAS CUENTAS Y DOCUMENTOS POR COBRAR CORRIENTES_DIVIDENDOS POR COBRAR_
G47: En efectivo | N47: 320 | O47: =VLOOKUP(N47,Casilleros!$A$4:$Q$830,17,FALSE) -> #REF! | S47: =+N47 -> 320 | T47: =IF(A47<>"",A47,T46) -> ESTADO DE SITUACIÓN FINANCIERA | U47: =IF(T46<>T47,"",(IF(B47<>"",B47,U46))) -> ACTIVO | V47: =IF(U46<>U47,"",(IF(C47<>"",C47,V46))) -> ACTIVOS CORRIENTES | W47: =IF(V46<>V47,"",(IF(D47<>"",D47,W46))) -> CUENTAS Y DOCUMENTOS POR COBRAR CORRIENTES | X47: =IF(W46<>W47,"",(IF(E47<>"",E47,X46))) -> OTRAS CUENTAS Y DOCUMENTOS POR COBRAR CORRIENTES | Y47: =IF(X46<>X47,"",(IF(F47<>"",F47,Y46))) -> DIVIDENDOS POR COBRAR | Z47: =IF(Y46<>Y47,"",(IF(G47<>"",G47,Z46))) -> En efectivo | AA47: =IF(X47<>"",CONCATENATE(W47,"_",X47,"_",Y47,"_",Z47),W47) -> CUENTAS Y DOCUMENTOS POR COBRAR CORRIENTES_OTRAS CUENTAS Y DOCUMENTOS POR COBRAR CORRIENTES_DIVIDENDOS POR COBRAR_En efectivo
G48: En activos diferentes del efectivo | N48: 321 | O48: =VLOOKUP(N48,Casilleros!$A$4:$Q$830,17,FALSE) -> #REF! | S48: =+N48 -> 321 | T48: =IF(A48<>"",A48,T47) -> ESTADO DE SITUACIÓN FINANCIERA | U48: =IF(T47<>T48,"",(IF(B48<>"",B48,U47))) -> ACTIVO | V48: =IF(U47<>U48,"",(IF(C48<>"",C48,V47))) -> ACTIVOS CORRIENTES | W48: =IF(V47<>V48,"",(IF(D48<>"",D48,W47))) -> CUENTAS Y DOCUMENTOS POR COBRAR CORRIENTES | X48: =IF(W47<>W48,"",(IF(E48<>"",E48,X47))) -> OTRAS CUENTAS Y DOCUMENTOS POR COBRAR CORRIENTES | Y48: =IF(X47<>X48,"",(IF(F48<>"",F48,Y47))) -> DIVIDENDOS POR COBRAR | Z48: =IF(Y47<>Y48,"",(IF(G48<>"",G48,Z47))) -> En activos diferentes del efectivo | AA48: =IF(X48<>"",CONCATENATE(W48,"_",X48,"_",Y48,"_",Z48),W48) -> CUENTAS Y DOCUMENTOS POR COBRAR CORRIENTES_OTRAS CUENTAS Y DOCUMENTOS POR COBRAR CORRIENTES_DIVIDENDOS POR COBRAR_En activos diferentes del efectivo
F49: OTRAS RELACIONADAS | S49: =+N49 -> 0 | T49: =IF(A49<>"",A49,T48) -> ESTADO DE SITUACIÓN FINANCIERA | U49: =IF(T48<>T49,"",(IF(B49<>"",B49,U48))) -> ACTIVO | V49: =IF(U48<>U49,"",(IF(C49<>"",C49,V48))) -> ACTIVOS CORRIENTES | W49: =IF(V48<>V49,"",(IF(D49<>"",D49,W48))) -> CUENTAS Y DOCUMENTOS POR COBRAR CORRIENTES | X49: =IF(W48<>W49,"",(IF(E49<>"",E49,X48))) -> OTRAS CUENTAS Y DOCUMENTOS POR COBRAR CORRIENTES | Y49: =IF(X48<>X49,"",(IF(F49<>"",F49,Y48))) -> OTRAS RELACIONADAS | Z49: =IF(Y48<>Y49,"",(IF(G49<>"",G49,Z48))) | AA49: =IF(X49<>"",CONCATENATE(W49,"_",X49,"_",Y49,"_",Z49),W49) -> CUENTAS Y DOCUMENTOS POR COBRAR CORRIENTES_OTRAS CUENTAS Y DOCUMENTOS POR COBRAR CORRIENTES_OTRAS RELACIONADAS_
G50: Locales | N50: 322 | O50: =VLOOKUP(N50,Casilleros!$A$4:$Q$830,17,FALSE) -> #REF! | S50: =+N50 -> 322 | T50: =IF(A50<>"",A50,T49) -> ESTADO DE SITUACIÓN FINANCIERA | U50: =IF(T49<>T50,"",(IF(B50<>"",B50,U49))) -> ACTIVO | V50: =IF(U49<>U50,"",(IF(C50<>"",C50,V49))) -> ACTIVOS CORRIENTES | W50: =IF(V49<>V50,"",(IF(D50<>"",D50,W49))) -> CUENTAS Y DOCUMENTOS POR COBRAR CORRIENTES | X50: =IF(W49<>W50,"",(IF(E50<>"",E50,X49))) -> OTRAS CUENTAS Y DOCUMENTOS POR COBRAR CORRIENTES | Y50: =IF(X49<>X50,"",(IF(F50<>"",F50,Y49))) -> OTRAS RELACIONADAS | Z50: =IF(Y49<>Y50,"",(IF(G50<>"",G50,Z49))) -> Locales | AA50: =IF(X50<>"",CONCATENATE(W50,"_",X50,"_",Y50,"_",Z50),W50) -> CUENTAS Y DOCUMENTOS POR COBRAR CORRIENTES_OTRAS CUENTAS Y DOCUMENTOS POR COBRAR CORRIENTES_OTRAS RELACIONADAS_Locales
G51: Del exterior | N51: 323 | O51: =VLOOKUP(N51,Casilleros!$A$4:$Q$830,17,FALSE) -> #REF! | S51: =+N51 -> 323 | T51: =IF(A51<>"",A51,T50) -> ESTADO DE SITUACIÓN FINANCIERA | U51: =IF(T50<>T51,"",(IF(B51<>"",B51,U50))) -> ACTIVO | V51: =IF(U50<>U51,"",(IF(C51<>"",C51,V50))) -> ACTIVOS CORRIENTES | W51: =IF(V50<>V51,"",(IF(D51<>"",D51,W50))) -> CUENTAS Y DOCUMENTOS POR COBRAR CORRIENTES | X51: =IF(W50<>W51,"",(IF(E51<>"",E51,X50))) -> OTRAS CUENTAS Y DOCUMENTOS POR COBRAR CORRIENTES | Y51: =IF(X50<>X51,"",(IF(F51<>"",F51,Y50))) -> OTRAS RELACIONADAS | Z51: =IF(Y50<>Y51,"",(IF(G51<>"",G51,Z50))) -> Del exterior | AA51: =IF(X51<>"",CONCATENATE(W51,"_",X51,"_",Y51,"_",Z51),W51) -> CUENTAS Y DOCUMENTOS POR COBRAR CORRIENTES_OTRAS CUENTAS Y DOCUMENTOS POR COBRAR CORRIENTES_OTRAS RELACIONADAS_Del exterior
G52: (-) Deterioro acumulado del valor de otras cuentas y documentos por cobrar por incobrabilidad (provisiones para créditos incobrables) | N52: 324 | O52: =VLOOKUP(N52,Casilleros!$A$4:$Q$830,17,FALSE) -> #REF! | S52: =+N52 -> 324 | T52: =IF(A52<>"",A52,T51) -> ESTADO DE SITUACIÓN FINANCIERA | U52: =IF(T51<>T52,"",(IF(B52<>"",B52,U51))) -> ACTIVO | V52: =IF(U51<>U52,"",(IF(C52<>"",C52,V51))) -> ACTIVOS CORRIENTES | W52: =IF(V51<>V52,"",(IF(D52<>"",D52,W51))) -> CUENTAS Y DOCUMENTOS POR COBRAR CORRIENTES | X52: =IF(W51<>W52,"",(IF(E52<>"",E52,X51))) -> OTRAS CUENTAS Y DOCUMENTOS POR COBRAR CORRIENTES | Y52: =IF(X51<>X52,"",(IF(F52<>"",F52,Y51))) -> OTRAS RELACIONADAS | Z52: =IF(Y51<>Y52,"",(IF(G52<>"",G52,Z51))) -> (-) Deterioro acumulado del valor de otras cuentas y documentos por cobrar por incobrabilidad (provisiones para créditos incobrables) | AA52: =IF(X52<>"",CONCATENATE(W52,"_",X52,"_",Y52,"_",Z52),W52) -> CUENTAS Y DOCUMENTOS POR COBRAR CORRIENTES_OTRAS CUENTAS Y DOCUMENTOS POR COBRAR CORRIENTES_OTRAS RELACIONADAS_(-) Deterioro acumulado del valor de otras cuentas y documentos por cobrar por incobrabilidad (provisiones para créditos incobrables)
F53: OTRAS NO RELACIONADAS | S53: =+N53 -> 0 | T53: =IF(A53<>"",A53,T52) -> ESTADO DE SITUACIÓN FINANCIERA | U53: =IF(T52<>T53,"",(IF(B53<>"",B53,U52))) -> ACTIVO | V53: =IF(U52<>U53,"",(IF(C53<>"",C53,V52))) -> ACTIVOS CORRIENTES | W53: =IF(V52<>V53,"",(IF(D53<>"",D53,W52))) -> CUENTAS Y DOCUMENTOS POR COBRAR CORRIENTES | X53: =IF(W52<>W53,"",(IF(E53<>"",E53,X52))) -> OTRAS CUENTAS Y DOCUMENTOS POR COBRAR CORRIENTES | Y53: =IF(X52<>X53,"",(IF(F53<>"",F53,Y52))) -> OTRAS NO RELACIONADAS | Z53: =IF(Y52<>Y53,"",(IF(G53<>"",G53,Z52))) | AA53: =IF(X53<>"",CONCATENATE(W53,"_",X53,"_",Y53,"_",Z53),W53) -> CUENTAS Y DOCUMENTOS POR COBRAR CORRIENTES_OTRAS CUENTAS Y DOCUMENTOS POR COBRAR CORRIENTES_OTRAS NO RELACIONADAS_
G54: Locales | N54: 325 | O54: =VLOOKUP(N54,Casilleros!$A$4:$Q$830,17,FALSE) -> #REF! | S54: =+N54 -> 325 | T54: =IF(A54<>"",A54,T53) -> ESTADO DE SITUACIÓN FINANCIERA | U54: =IF(T53<>T54,"",(IF(B54<>"",B54,U53))) -> ACTIVO | V54: =IF(U53<>U54,"",(IF(C54<>"",C54,V53))) -> ACTIVOS CORRIENTES | W54: =IF(V53<>V54,"",(IF(D54<>"",D54,W53))) -> CUENTAS Y DOCUMENTOS POR COBRAR CORRIENTES | X54: =IF(W53<>W54,"",(IF(E54<>"",E54,X53))) -> OTRAS CUENTAS Y DOCUMENTOS POR COBRAR CORRIENTES | Y54: =IF(X53<>X54,"",(IF(F54<>"",F54,Y53))) -> OTRAS NO RELACIONADAS | Z54: =IF(Y53<>Y54,"",(IF(G54<>"",G54,Z53))) -> Locales | AA54: =IF(X54<>"",CONCATENATE(W54,"_",X54,"_",Y54,"_",Z54),W54) -> CUENTAS Y DOCUMENTOS POR COBRAR CORRIENTES_OTRAS CUENTAS Y DOCUMENTOS POR COBRAR CORRIENTES_OTRAS NO RELACIONADAS_Locales
G55: Del exterior | N55: 326 | O55: =VLOOKUP(N55,Casilleros!$A$4:$Q$830,17,FALSE) -> #REF! | S55: =+N55 -> 326 | T55: =IF(A55<>"",A55,T54) -> ESTADO DE SITUACIÓN FINANCIERA | U55: =IF(T54<>T55,"",(IF(B55<>"",B55,U54))) -> ACTIVO | V55: =IF(U54<>U55,"",(IF(C55<>"",C55,V54))) -> ACTIVOS CORRIENTES | W55: =IF(V54<>V55,"",(IF(D55<>"",D55,W54))) -> CUENTAS Y DOCUMENTOS POR COBRAR CORRIENTES | X55: =IF(W54<>W55,"",(IF(E55<>"",E55,X54))) -> OTRAS CUENTAS Y DOCUMENTOS POR COBRAR CORRIENTES | Y55: =IF(X54<>X55,"",(IF(F55<>"",F55,Y54))) -> OTRAS NO RELACIONADAS | Z55: =IF(Y54<>Y55,"",(IF(G55<>"",G55,Z54))) -> Del exterior | AA55: =IF(X55<>"",CONCATENATE(W55,"_",X55,"_",Y55,"_",Z55),W55) -> CUENTAS Y DOCUMENTOS POR COBRAR CORRIENTES_OTRAS CUENTAS Y DOCUMENTOS POR COBRAR CORRIENTES_OTRAS NO RELACIONADAS_Del exterior
G56: (-) Deterioro acumulado del valor de otras cuentas y documentos por cobrar por incobrabilidad (provisiones para créditos incobrables) | N56: 327 | O56: =VLOOKUP(N56,Casilleros!$A$4:$Q$830,17,FALSE) -> #REF! | S56: =+N56 -> 327 | T56: =IF(A56<>"",A56,T55) -> ESTADO DE SITUACIÓN FINANCIERA | U56: =IF(T55<>T56,"",(IF(B56<>"",B56,U55))) -> ACTIVO | V56: =IF(U55<>U56,"",(IF(C56<>"",C56,V55))) -> ACTIVOS CORRIENTES | W56: =IF(V55<>V56,"",(IF(D56<>"",D56,W55))) -> CUENTAS Y DOCUMENTOS POR COBRAR CORRIENTES | X56: =IF(W55<>W56,"",(IF(E56<>"",E56,X55))) -> OTRAS CUENTAS Y DOCUMENTOS POR COBRAR CORRIENTES | Y56: =IF(X55<>X56,"",(IF(F56<>"",F56,Y55))) -> OTRAS NO RELACIONADAS | Z56: =IF(Y55<>Y56,"",(IF(G56<>"",G56,Z55))) -> (-) Deterioro acumulado del valor de otras cuentas y documentos por cobrar por incobrabilidad (provisiones para créditos incobrables) | AA56: =IF(X56<>"",CONCATENATE(W56,"_",X56,"_",Y56,"_",Z56),W56) -> CUENTAS Y DOCUMENTOS POR COBRAR CORRIENTES_OTRAS CUENTAS Y DOCUMENTOS POR COBRAR CORRIENTES_OTRAS NO RELACIONADAS_(-) Deterioro acumulado del valor de otras cuentas y documentos por cobrar por incobrabilidad (provisiones para créditos incobrables)
D57: OTROS ACTIVOS FINANCIEROS CORRIENTES | S57: =+N57 -> 0 | T57: =IF(A57<>"",A57,T56) -> ESTADO DE SITUACIÓN FINANCIERA | U57: =IF(T56<>T57,"",(IF(B57<>"",B57,U56))) -> ACTIVO | V57: =IF(U56<>U57,"",(IF(C57<>"",C57,V56))) -> ACTIVOS CORRIENTES | W57: =IF(V56<>V57,"",(IF(D57<>"",D57,W56))) -> OTROS ACTIVOS FINANCIEROS CORRIENTES | X57: =IF(W56<>W57,"",(IF(E57<>"",E57,X56))) | Y57: =IF(X56<>X57,"",(IF(F57<>"",F57,Y56))) | Z57: =IF(Y56<>Y57,"",(IF(G57<>"",G57,Z56))) | AA57: =IF(X57<>"",CONCATENATE(W57,"_",X57,"_",Y57,"_",Z57),W57) -> OTROS ACTIVOS FINANCIEROS CORRIENTES
E58: A costo amortizado | N58: 328 | O58: =VLOOKUP(N58,Casilleros!$A$4:$Q$830,17,FALSE) -> #REF! | S58: =+N58 -> 328 | T58: =IF(A58<>"",A58,T57) -> ESTADO DE SITUACIÓN FINANCIERA | U58: =IF(T57<>T58,"",(IF(B58<>"",B58,U57))) -> ACTIVO | V58: =IF(U57<>U58,"",(IF(C58<>"",C58,V57))) -> ACTIVOS CORRIENTES | W58: =IF(V57<>V58,"",(IF(D58<>"",D58,W57))) -> OTROS ACTIVOS FINANCIEROS CORRIENTES | X58: =IF(W57<>W58,"",(IF(E58<>"",E58,X57))) -> A costo amortizado | Y58: =IF(X57<>X58,"",(IF(F58<>"",F58,Y57))) | Z58: =IF(Y57<>Y58,"",(IF(G58<>"",G58,Z57))) | AA58: =IF(X58<>"",CONCATENATE(W58,"_",X58,"_",Y58,"_",Z58),W58) -> OTROS ACTIVOS FINANCIEROS CORRIENTES_A costo amortizado__
E59: (-) Deterioro acumulado del valor de otros activos financieros corrientes medidos a costo amortizado (provisiones para créditos incobrables) | N59: 329 | O59: =VLOOKUP(N59,Casilleros!$A$4:$Q$830,17,FALSE) -> #REF! | S59: =+N59 -> 329 | T59: =IF(A59<>"",A59,T58) -> ESTADO DE SITUACIÓN FINANCIERA | U59: =IF(T58<>T59,"",(IF(B59<>"",B59,U58))) -> ACTIVO | V59: =IF(U58<>U59,"",(IF(C59<>"",C59,V58))) -> ACTIVOS CORRIENTES | W59: =IF(V58<>V59,"",(IF(D59<>"",D59,W58))) -> OTROS ACTIVOS FINANCIEROS CORRIENTES | X59: =IF(W58<>W59,"",(IF(E59<>"",E59,X58))) -> (-) Deterioro acumulado del valor de otros activos financieros corrientes medidos a costo amortizado (provisiones para créditos incobrables) | Y59: =IF(X58<>X59,"",(IF(F59<>"",F59,Y58))) | Z59: =IF(Y58<>Y59,"",(IF(G59<>"",G59,Z58))) | AA59: =IF(X59<>"",CONCATENATE(W59,"_",X59,"_",Y59,"_",Z59),W59) -> OTROS ACTIVOS FINANCIEROS CORRIENTES_(-) Deterioro acumulado del valor de otros activos financieros corrientes medidos a costo amortizado (provisiones para créditos incobrables)__
E60: A valor razonable | N60: 330 | O60: =VLOOKUP(N60,Casilleros!$A$4:$Q$830,17,FALSE) -> #REF! | S60: =+N60 -> 330 | T60: =IF(A60<>"",A60,T59) -> ESTADO DE SITUACIÓN FINANCIERA | U60: =IF(T59<>T60,"",(IF(B60<>"",B60,U59))) -> ACTIVO | V60: =IF(U59<>U60,"",(IF(C60<>"",C60,V59))) -> ACTIVOS CORRIENTES | W60: =IF(V59<>V60,"",(IF(D60<>"",D60,W59))) -> OTROS ACTIVOS FINANCIEROS CORRIENTES | X60: =IF(W59<>W60,"",(IF(E60<>"",E60,X59))) -> A valor razonable | Y60: =IF(X59<>X60,"",(IF(F60<>"",F60,Y59))) | Z60: =IF(Y59<>Y60,"",(IF(G60<>"",G60,Z59))) | AA60: =IF(X60<>"",CONCATENATE(W60,"_",X60,"_",Y60,"_",Z60),W60) -> OTROS ACTIVOS FINANCIEROS CORRIENTES_A valor razonable__
D61: PORCIÓN CORRIENTE DE ARRENDAMIENTOS FINANCIEROS POR COBRAR | S61: =+N61 -> 0 | T61: =IF(A61<>"",A61,T60) -> ESTADO DE SITUACIÓN FINANCIERA | U61: =IF(T60<>T61,"",(IF(B61<>"",B61,U60))) -> ACTIVO | V61: =IF(U60<>U61,"",(IF(C61<>"",C61,V60))) -> ACTIVOS CORRIENTES | W61: =IF(V60<>V61,"",(IF(D61<>"",D61,W60))) -> PORCIÓN CORRIENTE DE ARRENDAMIENTOS FINANCIEROS POR COBRAR | X61: =IF(W60<>W61,"",(IF(E61<>"",E61,X60))) | Y61: =IF(X60<>X61,"",(IF(F61<>"",F61,Y60))) | Z61: =IF(Y60<>Y61,"",(IF(G61<>"",G61,Z60))) | AA61: =IF(X61<>"",CONCATENATE(W61,"_",X61,"_",Y61,"_",Z61),W61) -> PORCIÓN CORRIENTE DE ARRENDAMIENTOS FINANCIEROS POR COBRAR
E62: Relacionadas | N62: 331 | O62: =VLOOKUP(N62,Casilleros!$A$4:$Q$830,17,FALSE) -> #REF! | S62: =+N62 -> 331 | T62: =IF(A62<>"",A62,T61) -> ESTADO DE SITUACIÓN FINANCIERA | U62: =IF(T61<>T62,"",(IF(B62<>"",B62,U61))) -> ACTIVO | V62: =IF(U61<>U62,"",(IF(C62<>"",C62,V61))) -> ACTIVOS CORRIENTES | W62: =IF(V61<>V62,"",(IF(D62<>"",D62,W61))) -> PORCIÓN CORRIENTE DE ARRENDAMIENTOS FINANCIEROS POR COBRAR | X62: =IF(W61<>W62,"",(IF(E62<>"",E62,X61))) -> Relacionadas | Y62: =IF(X61<>X62,"",(IF(F62<>"",F62,Y61))) | Z62: =IF(Y61<>Y62,"",(IF(G62<>"",G62,Z61))) | AA62: =IF(X62<>"",CONCATENATE(W62,"_",X62,"_",Y62,"_",Z62),W62) -> PORCIÓN CORRIENTE DE ARRENDAMIENTOS FINANCIEROS POR COBRAR_Relacionadas__
E63: No relacionadas | N63: 332 | O63: =VLOOKUP(N63,Casilleros!$A$4:$Q$830,17,FALSE) -> #REF! | S63: =+N63 -> 332 | T63: =IF(A63<>"",A63,T62) -> ESTADO DE SITUACIÓN FINANCIERA | U63: =IF(T62<>T63,"",(IF(B63<>"",B63,U62))) -> ACTIVO | V63: =IF(U62<>U63,"",(IF(C63<>"",C63,V62))) -> ACTIVOS CORRIENTES | W63: =IF(V62<>V63,"",(IF(D63<>"",D63,W62))) -> PORCIÓN CORRIENTE DE ARRENDAMIENTOS FINANCIEROS POR COBRAR | X63: =IF(W62<>W63,"",(IF(E63<>"",E63,X62))) -> No relacionadas | Y63: =IF(X62<>X63,"",(IF(F63<>"",F63,Y62))) | Z63: =IF(Y62<>Y63,"",(IF(G63<>"",G63,Z62))) | AA63: =IF(X63<>"",CONCATENATE(W63,"_",X63,"_",Y63,"_",Z63),W63) -> PORCIÓN CORRIENTE DE ARRENDAMIENTOS FINANCIEROS POR COBRAR_No relacionadas__
D64: IMPORTE BRUTO ADEUDADO POR LOS CLIENTES POR EL TRABAJO EJECUTADO EN CONTRATOS DE CONSTRUCCIÓN | S64: =+N64 -> 0 | T64: =IF(A64<>"",A64,T63) -> ESTADO DE SITUACIÓN FINANCIERA | U64: =IF(T63<>T64,"",(IF(B64<>"",B64,U63))) -> ACTIVO | V64: =IF(U63<>U64,"",(IF(C64<>"",C64,V63))) -> ACTIVOS CORRIENTES | W64: =IF(V63<>V64,"",(IF(D64<>"",D64,W63))) -> IMPORTE BRUTO ADEUDADO POR LOS CLIENTES POR EL TRABAJO EJECUTADO EN CONTRATOS DE CONSTRUCCIÓN | X64: =IF(W63<>W64,"",(IF(E64<>"",E64,X63))) | Y64: =IF(X63<>X64,"",(IF(F64<>"",F64,Y63))) | Z64: =IF(Y63<>Y64,"",(IF(G64<>"",G64,Z63))) | AA64: =IF(X64<>"",CONCATENATE(W64,"_",X64,"_",Y64,"_",Z64),W64) -> IMPORTE BRUTO ADEUDADO POR LOS CLIENTES POR EL TRABAJO EJECUTADO EN CONTRATOS DE CONSTRUCCIÓN
E65: Relacionadas | N65: 333 | O65: =VLOOKUP(N65,Casilleros!$A$4:$Q$830,17,FALSE) -> #REF! | S65: =+N65 -> 333 | T65: =IF(A65<>"",A65,T64) -> ESTADO DE SITUACIÓN FINANCIERA | U65: =IF(T64<>T65,"",(IF(B65<>"",B65,U64))) -> ACTIVO | V65: =IF(U64<>U65,"",(IF(C65<>"",C65,V64))) -> ACTIVOS CORRIENTES | W65: =IF(V64<>V65,"",(IF(D65<>"",D65,W64))) -> IMPORTE BRUTO ADEUDADO POR LOS CLIENTES POR EL TRABAJO EJECUTADO EN CONTRATOS DE CONSTRUCCIÓN | X65: =IF(W64<>W65,"",(IF(E65<>"",E65,X64))) -> Relacionadas | Y65: =IF(X64<>X65,"",(IF(F65<>"",F65,Y64))) | Z65: =IF(Y64<>Y65,"",(IF(G65<>"",G65,Z64))) | AA65: =IF(X65<>"",CONCATENATE(W65,"_",X65,"_",Y65,"_",Z65),W65) -> IMPORTE BRUTO ADEUDADO POR LOS CLIENTES POR EL TRABAJO EJECUTADO EN CONTRATOS DE CONSTRUCCIÓN_Relacionadas__
E66: No relacionadas | N66: 334 | O66: =VLOOKUP(N66,Casilleros!$A$4:$Q$830,17,FALSE) -> #REF! | S66: =+N66 -> 334 | T66: =IF(A66<>"",A66,T65) -> ESTADO DE SITUACIÓN FINANCIERA | U66: =IF(T65<>T66,"",(IF(B66<>"",B66,U65))) -> ACTIVO | V66: =IF(U65<>U66,"",(IF(C66<>"",C66,V65))) -> ACTIVOS CORRIENTES | W66: =IF(V65<>V66,"",(IF(D66<>"",D66,W65))) -> IMPORTE BRUTO ADEUDADO POR LOS CLIENTES POR EL TRABAJO EJECUTADO EN CONTRATOS DE CONSTRUCCIÓN | X66: =IF(W65<>W66,"",(IF(E66<>"",E66,X65))) -> No relacionadas | Y66: =IF(X65<>X66,"",(IF(F66<>"",F66,Y65))) | Z66: =IF(Y65<>Y66,"",(IF(G66<>"",G66,Z65))) | AA66: =IF(X66<>"",CONCATENATE(W66,"_",X66,"_",Y66,"_",Z66),W66) -> IMPORTE BRUTO ADEUDADO POR LOS CLIENTES POR EL TRABAJO EJECUTADO EN CONTRATOS DE CONSTRUCCIÓN_No relacionadas__
D67: ACTIVOS POR IMPUESTOS CORRIENTES | S67: =+N67 -> 0 | T67: =IF(A67<>"",A67,T66) -> ESTADO DE SITUACIÓN FINANCIERA | U67: =IF(T66<>T67,"",(IF(B67<>"",B67,U66))) -> ACTIVO | V67: =IF(U66<>U67,"",(IF(C67<>"",C67,V66))) -> ACTIVOS CORRIENTES | W67: =IF(V66<>V67,"",(IF(D67<>"",D67,W66))) -> ACTIVOS POR IMPUESTOS CORRIENTES | X67: =IF(W66<>W67,"",(IF(E67<>"",E67,X66))) | Y67: =IF(X66<>X67,"",(IF(F67<>"",F67,Y66))) | Z67: =IF(Y66<>Y67,"",(IF(G67<>"",G67,Z66))) | AA67: =IF(X67<>"",CONCATENATE(W67,"_",X67,"_",Y67,"_",Z67),W67) -> ACTIVOS POR IMPUESTOS CORRIENTES
E68: Crédito tributario a favor del sujeto pasivo (ISD) | N68: 335 | O68: =VLOOKUP(N68,Casilleros!$A$4:$Q$830,17,FALSE) -> #REF! | S68: =+N68 -> 335 | T68: =IF(A68<>"",A68,T67) -> ESTADO DE SITUACIÓN FINANCIERA | U68: =IF(T67<>T68,"",(IF(B68<>"",B68,U67))) -> ACTIVO | V68: =IF(U67<>U68,"",(IF(C68<>"",C68,V67))) -> ACTIVOS CORRIENTES | W68: =IF(V67<>V68,"",(IF(D68<>"",D68,W67))) -> ACTIVOS POR IMPUESTOS CORRIENTES | X68: =IF(W67<>W68,"",(IF(E68<>"",E68,X67))) -> Crédito tributario a favor del sujeto pasivo (ISD) | Y68: =IF(X67<>X68,"",(IF(F68<>"",F68,Y67))) | Z68: =IF(Y67<>Y68,"",(IF(G68<>"",G68,Z67))) | AA68: =IF(X68<>"",CONCATENATE(W68,"_",X68,"_",Y68,"_",Z68),W68) -> ACTIVOS POR IMPUESTOS CORRIENTES_Crédito tributario a favor del sujeto pasivo (ISD)__
E69: Crédito tributario a favor del sujeto pasivo (IVA) | N69: 336 | O69: =VLOOKUP(N69,Casilleros!$A$4:$Q$830,17,FALSE) -> #REF! | S69: =+N69 -> 336 | T69: =IF(A69<>"",A69,T68) -> ESTADO DE SITUACIÓN FINANCIERA | U69: =IF(T68<>T69,"",(IF(B69<>"",B69,U68))) -> ACTIVO | V69: =IF(U68<>U69,"",(IF(C69<>"",C69,V68))) -> ACTIVOS CORRIENTES | W69: =IF(V68<>V69,"",(IF(D69<>"",D69,W68))) -> ACTIVOS POR IMPUESTOS CORRIENTES | X69: =IF(W68<>W69,"",(IF(E69<>"",E69,X68))) -> Crédito tributario a favor del sujeto pasivo (IVA) | Y69: =IF(X68<>X69,"",(IF(F69<>"",F69,Y68))) | Z69: =IF(Y68<>Y69,"",(IF(G69<>"",G69,Z68))) | AA69: =IF(X69<>"",CONCATENATE(W69,"_",X69,"_",Y69,"_",Z69),W69) -> ACTIVOS POR IMPUESTOS CORRIENTES_Crédito tributario a favor del sujeto pasivo (IVA)__
E70: Crédito tributario a favor del sujeto pasivo (Impuesto a la Renta) | N70: 337 | O70: =VLOOKUP(N70,Casilleros!$A$4:$Q$830,17,FALSE) -> #REF! | S70: =+N70 -> 337 | T70: =IF(A70<>"",A70,T69) -> ESTADO DE SITUACIÓN FINANCIERA | U70: =IF(T69<>T70,"",(IF(B70<>"",B70,U69))) -> ACTIVO | V70: =IF(U69<>U70,"",(IF(C70<>"",C70,V69))) -> ACTIVOS CORRIENTES | W70: =IF(V69<>V70,"",(IF(D70<>"",D70,W69))) -> ACTIVOS POR IMPUESTOS CORRIENTES | X70: =IF(W69<>W70,"",(IF(E70<>"",E70,X69))) -> Crédito tributario a favor del sujeto pasivo (Impuesto a la Renta) | Y70: =IF(X69<>X70,"",(IF(F70<>"",F70,Y69))) | Z70: =IF(Y69<>Y70,"",(IF(G70<>"",G70,Z69))) | AA70: =IF(X70<>"",CONCATENATE(W70,"_",X70,"_",Y70,"_",Z70),W70) -> ACTIVOS POR IMPUESTOS CORRIENTES_Crédito tributario a favor del sujeto pasivo (Impuesto a la Renta) __
E71: Otros | N71: 338 | O71: =VLOOKUP(N71,Casilleros!$A$4:$Q$830,17,FALSE) -> #REF! | S71: =+N71 -> 338 | T71: =IF(A71<>"",A71,T70) -> ESTADO DE SITUACIÓN FINANCIERA | U71: =IF(T70<>T71,"",(IF(B71<>"",B71,U70))) -> ACTIVO | V71: =IF(U70<>U71,"",(IF(C71<>"",C71,V70))) -> ACTIVOS CORRIENTES | W71: =IF(V70<>V71,"",(IF(D71<>"",D71,W70))) -> ACTIVOS POR IMPUESTOS CORRIENTES | X71: =IF(W70<>W71,"",(IF(E71<>"",E71,X70))) -> Otros | Y71: =IF(X70<>X71,"",(IF(F71<>"",F71,Y70))) | Z71: =IF(Y70<>Y71,"",(IF(G71<>"",G71,Z70))) | AA71: =IF(X71<>"",CONCATENATE(W71,"_",X71,"_",Y71,"_",Z71),W71) -> ACTIVOS POR IMPUESTOS CORRIENTES_Otros__
D72: INVENTARIOS | S72: =+N72 -> 0 | T72: =IF(A72<>"",A72,T71) -> ESTADO DE SITUACIÓN FINANCIERA | U72: =IF(T71<>T72,"",(IF(B72<>"",B72,U71))) -> ACTIVO | V72: =IF(U71<>U72,"",(IF(C72<>"",C72,V71))) -> ACTIVOS CORRIENTES | W72: =IF(V71<>V72,"",(IF(D72<>"",D72,W71))) -> INVENTARIOS | X72: =IF(W71<>W72,"",(IF(E72<>"",E72,X71))) | Y72: =IF(X71<>X72,"",(IF(F72<>"",F72,Y71))) | Z72: =IF(Y71<>Y72,"",(IF(G72<>"",G72,Z71))) | AA72: =IF(X72<>"",CONCATENATE(W72,"_",X72,"_",Y72,"_",Z72),W72) -> INVENTARIOS
E73: Mercaderías en tránsito | N73: 339 | O73: =VLOOKUP(N73,Casilleros!$A$4:$Q$830,17,FALSE) -> #REF! | S73: =+N73 -> 339 | T73: =IF(A73<>"",A73,T72) -> ESTADO DE SITUACIÓN FINANCIERA | U73: =IF(T72<>T73,"",(IF(B73<>"",B73,U72))) -> ACTIVO | V73: =IF(U72<>U73,"",(IF(C73<>"",C73,V72))) -> ACTIVOS CORRIENTES | W73: =IF(V72<>V73,"",(IF(D73<>"",D73,W72))) -> INVENTARIOS | X73: =IF(W72<>W73,"",(IF(E73<>"",E73,X72))) -> Mercaderías en tránsito | Y73: =IF(X72<>X73,"",(IF(F73<>"",F73,Y72))) | Z73: =IF(Y72<>Y73,"",(IF(G73<>"",G73,Z72))) | AA73: =IF(X73<>"",CONCATENATE(W73,"_",X73,"_",Y73,"_",Z73),W73) -> INVENTARIOS_Mercaderías en tránsito__
E74: Inventario de materia prima (no para la construcción) | N74: 340 | O74: =VLOOKUP(N74,Casilleros!$A$4:$Q$830,17,FALSE) -> #REF! | S74: =+N74 -> 340 | T74: =IF(A74<>"",A74,T73) -> ESTADO DE SITUACIÓN FINANCIERA | U74: =IF(T73<>T74,"",(IF(B74<>"",B74,U73))) -> ACTIVO | V74: =IF(U73<>U74,"",(IF(C74<>"",C74,V73))) -> ACTIVOS CORRIENTES | W74: =IF(V73<>V74,"",(IF(D74<>"",D74,W73))) -> INVENTARIOS | X74: =IF(W73<>W74,"",(IF(E74<>"",E74,X73))) -> Inventario de materia prima (no para la construcción) | Y74: =IF(X73<>X74,"",(IF(F74<>"",F74,Y73))) | Z74: =IF(Y73<>Y74,"",(IF(G74<>"",G74,Z73))) | AA74: =IF(X74<>"",CONCATENATE(W74,"_",X74,"_",Y74,"_",Z74),W74) -> INVENTARIOS_Inventario de materia prima (no para la construcción)__
E75: Inventario de productos en proceso (excluyendo obras/inmuebles en construcción para la venta) | N75: 341 | O75: =VLOOKUP(N75,Casilleros!$A$4:$Q$830,17,FALSE) -> #REF! | S75: =+N75 -> 341 | T75: =IF(A75<>"",A75,T74) -> ESTADO DE SITUACIÓN FINANCIERA | U75: =IF(T74<>T75,"",(IF(B75<>"",B75,U74))) -> ACTIVO | V75: =IF(U74<>U75,"",(IF(C75<>"",C75,V74))) -> ACTIVOS CORRIENTES | W75: =IF(V74<>V75,"",(IF(D75<>"",D75,W74))) -> INVENTARIOS | X75: =IF(W74<>W75,"",(IF(E75<>"",E75,X74))) -> Inventario de productos en proceso (excluyendo obras/inmuebles en construcción para la venta) | Y75: =IF(X74<>X75,"",(IF(F75<>"",F75,Y74))) | Z75: =IF(Y74<>Y75,"",(IF(G75<>"",G75,Z74))) | AA75: =IF(X75<>"",CONCATENATE(W75,"_",X75,"_",Y75,"_",Z75),W75) -> INVENTARIOS_Inventario de productos en proceso (excluyendo obras/inmuebles en construcción para la venta)__
E76: Inventario de prod. term. y mercad. en almacén (excluyendo obras/inmuebles terminados para la venta) | N76: 342 | O76: =VLOOKUP(N76,Casilleros!$A$4:$Q$830,17,FALSE) -> #REF! | S76: =+N76 -> 342 | T76: =IF(A76<>"",A76,T75) -> ESTADO DE SITUACIÓN FINANCIERA | U76: =IF(T75<>T76,"",(IF(B76<>"",B76,U75))) -> ACTIVO | V76: =IF(U75<>U76,"",(IF(C76<>"",C76,V75))) -> ACTIVOS CORRIENTES | W76: =IF(V75<>V76,"",(IF(D76<>"",D76,W75))) -> INVENTARIOS | X76: =IF(W75<>W76,"",(IF(E76<>"",E76,X75))) -> Inventario de prod. term. y mercad. en almacén (excluyendo obras/inmuebles terminados para la venta) | Y76: =IF(X75<>X76,"",(IF(F76<>"",F76,Y75))) | Z76: =IF(Y75<>Y76,"",(IF(G76<>"",G76,Z75))) | AA76: =IF(X76<>"",CONCATENATE(W76,"_",X76,"_",Y76,"_",Z76),W76) -> INVENTARIOS_Inventario de prod. term. y mercad. en almacén (excluyendo obras/inmuebles terminados para la venta)__
E77: Inventario de suministros, herramientas, repuestos y materiales (no para la construcción) | N77: 343 | O77: =VLOOKUP(N77,Casilleros!$A$4:$Q$830,17,FALSE) -> #REF! | S77: =+N77 -> 343 | T77: =IF(A77<>"",A77,T76) -> ESTADO DE SITUACIÓN FINANCIERA | U77: =IF(T76<>T77,"",(IF(B77<>"",B77,U76))) -> ACTIVO | V77: =IF(U76<>U77,"",(IF(C77<>"",C77,V76))) -> ACTIVOS CORRIENTES | W77: =IF(V76<>V77,"",(IF(D77<>"",D77,W76))) -> INVENTARIOS | X77: =IF(W76<>W77,"",(IF(E77<>"",E77,X76))) -> Inventario de suministros, herramientas, repuestos y materiales (no para la construcción) | Y77: =IF(X76<>X77,"",(IF(F77<>"",F77,Y76))) | Z77: =IF(Y76<>Y77,"",(IF(G77<>"",G77,Z76))) | AA77: =IF(X77<>"",CONCATENATE(W77,"_",X77,"_",Y77,"_",Z77),W77) -> INVENTARIOS_Inventario de suministros, herramientas, repuestos y materiales (no para la construcción)__
E78: Inventario de materia prima, suministros y materiales para la construcción | N78: 344 | O78: =VLOOKUP(N78,Casilleros!$A$4:$Q$830,17,FALSE) -> #REF! | S78: =+N78 -> 344 | T78: =IF(A78<>"",A78,T77) -> ESTADO DE SITUACIÓN FINANCIERA | U78: =IF(T77<>T78,"",(IF(B78<>"",B78,U77))) -> ACTIVO | V78: =IF(U77<>U78,"",(IF(C78<>"",C78,V77))) -> ACTIVOS CORRIENTES | W78: =IF(V77<>V78,"",(IF(D78<>"",D78,W77))) -> INVENTARIOS | X78: =IF(W77<>W78,"",(IF(E78<>"",E78,X77))) -> Inventario de materia prima, suministros y materiales para la construcción | Y78: =IF(X77<>X78,"",(IF(F78<>"",F78,Y77))) | Z78: =IF(Y77<>Y78,"",(IF(G78<>"",G78,Z77))) | AA78: =IF(X78<>"",CONCATENATE(W78,"_",X78,"_",Y78,"_",Z78),W78) -> INVENTARIOS_Inventario de materia prima, suministros y materiales para la construcción__
E79: Inventario de obras/inmuebles en construcción para la venta | N79: 345 | O79: =VLOOKUP(N79,Casilleros!$A$4:$Q$830,17,FALSE) -> #REF! | S79: =+N79 -> 345 | T79: =IF(A79<>"",A79,T78) -> ESTADO DE SITUACIÓN FINANCIERA | U79: =IF(T78<>T79,"",(IF(B79<>"",B79,U78))) -> ACTIVO | V79: =IF(U78<>U79,"",(IF(C79<>"",C79,V78))) -> ACTIVOS CORRIENTES | W79: =IF(V78<>V79,"",(IF(D79<>"",D79,W78))) -> INVENTARIOS | X79: =IF(W78<>W79,"",(IF(E79<>"",E79,X78))) -> Inventario de obras/inmuebles en construcción para la venta | Y79: =IF(X78<>X79,"",(IF(F79<>"",F79,Y78))) | Z79: =IF(Y78<>Y79,"",(IF(G79<>"",G79,Z78))) | AA79: =IF(X79<>"",CONCATENATE(W79,"_",X79,"_",Y79,"_",Z79),W79) -> INVENTARIOS_Inventario de obras/inmuebles en construcción para la venta__
E80: Inventario de obras/inmuebles terminados para la venta | N80: 346 | O80: =VLOOKUP(N80,Casilleros!$A$4:$Q$830,17,FALSE) -> #REF! | S80: =+N80 -> 346 | T80: =IF(A80<>"",A80,T79) -> ESTADO DE SITUACIÓN FINANCIERA | U80: =IF(T79<>T80,"",(IF(B80<>"",B80,U79))) -> ACTIVO | V80: =IF(U79<>U80,"",(IF(C80<>"",C80,V79))) -> ACTIVOS CORRIENTES | W80: =IF(V79<>V80,"",(IF(D80<>"",D80,W79))) -> INVENTARIOS | X80: =IF(W79<>W80,"",(IF(E80<>"",E80,X79))) -> Inventario de obras/inmuebles terminados para la venta | Y80: =IF(X79<>X80,"",(IF(F80<>"",F80,Y79))) | Z80: =IF(Y79<>Y80,"",(IF(G80<>"",G80,Z79))) | AA80: =IF(X80<>"",CONCATENATE(W80,"_",X80,"_",Y80,"_",Z80),W80) -> INVENTARIOS_Inventario de obras/inmuebles terminados para la venta__
E81: (-) Deterioro acumulado del valor de inventarios por ajuste al valor neto realizable | N81: 347 | O81: =VLOOKUP(N81,Casilleros!$A$4:$Q$830,17,FALSE) -> #REF! | S81: =+N81 -> 347 | T81: =IF(A81<>"",A81,T80) -> ESTADO DE SITUACIÓN FINANCIERA | U81: =IF(T80<>T81,"",(IF(B81<>"",B81,U80))) -> ACTIVO | V81: =IF(U80<>U81,"",(IF(C81<>"",C81,V80))) -> ACTIVOS CORRIENTES | W81: =IF(V80<>V81,"",(IF(D81<>"",D81,W80))) -> INVENTARIOS | X81: =IF(W80<>W81,"",(IF(E81<>"",E81,X80))) -> (-) Deterioro acumulado del valor de inventarios por ajuste al valor neto realizable | Y81: =IF(X80<>X81,"",(IF(F81<>"",F81,Y80))) | Z81: =IF(Y80<>Y81,"",(IF(G81<>"",G81,Z80))) | AA81: =IF(X81<>"",CONCATENATE(W81,"_",X81,"_",Y81,"_",Z81),W81) -> INVENTARIOS_(-) Deterioro acumulado del valor de inventarios por ajuste al valor neto realizable__
D82: ACTIVOS NO CORRIENTES MANTENIDOS PARA LA VENTA | S82: =+N82 -> 0 | T82: =IF(A82<>"",A82,T81) -> ESTADO DE SITUACIÓN FINANCIERA | U82: =IF(T81<>T82,"",(IF(B82<>"",B82,U81))) -> ACTIVO | V82: =IF(U81<>U82,"",(IF(C82<>"",C82,V81))) -> ACTIVOS CORRIENTES | W82: =IF(V81<>V82,"",(IF(D82<>"",D82,W81))) -> ACTIVOS NO CORRIENTES MANTENIDOS PARA LA VENTA | X82: =IF(W81<>W82,"",(IF(E82<>"",E82,X81))) | Y82: =IF(X81<>X82,"",(IF(F82<>"",F82,Y81))) | Z82: =IF(Y81<>Y82,"",(IF(G82<>"",G82,Z81))) | AA82: =IF(X82<>"",CONCATENATE(W82,"_",X82,"_",Y82,"_",Z82),W82) -> ACTIVOS NO CORRIENTES MANTENIDOS PARA LA VENTA
E83: Costo | N83: 348 | O83: =VLOOKUP(N83,Casilleros!$A$4:$Q$830,17,FALSE) -> #REF! | S83: =+N83 -> 348 | T83: =IF(A83<>"",A83,T82) -> ESTADO DE SITUACIÓN FINANCIERA | U83: =IF(T82<>T83,"",(IF(B83<>"",B83,U82))) -> ACTIVO | V83: =IF(U82<>U83,"",(IF(C83<>"",C83,V82))) -> ACTIVOS CORRIENTES | W83: =IF(V82<>V83,"",(IF(D83<>"",D83,W82))) -> ACTIVOS NO CORRIENTES MANTENIDOS PARA LA VENTA | X83: =IF(W82<>W83,"",(IF(E83<>"",E83,X82))) -> Costo | Y83: =IF(X82<>X83,"",(IF(F83<>"",F83,Y82))) | Z83: =IF(Y82<>Y83,"",(IF(G83<>"",G83,Z82))) | AA83: =IF(X83<>"",CONCATENATE(W83,"_",X83,"_",Y83,"_",Z83),W83) -> ACTIVOS NO CORRIENTES MANTENIDOS PARA LA VENTA_Costo__
E84: (-) Deterioro acumulado del valor de activos no corrientes mantenidos para la venta | N84: 349 | O84: =VLOOKUP(N84,Casilleros!$A$4:$Q$830,17,FALSE) -> #REF! | S84: =+N84 -> 349 | T84: =IF(A84<>"",A84,T83) -> ESTADO DE SITUACIÓN FINANCIERA | U84: =IF(T83<>T84,"",(IF(B84<>"",B84,U83))) -> ACTIVO | V84: =IF(U83<>U84,"",(IF(C84<>"",C84,V83))) -> ACTIVOS CORRIENTES | W84: =IF(V83<>V84,"",(IF(D84<>"",D84,W83))) -> ACTIVOS NO CORRIENTES MANTENIDOS PARA LA VENTA | X84: =IF(W83<>W84,"",(IF(E84<>"",E84,X83))) -> (-) Deterioro acumulado del valor de activos no corrientes mantenidos para la venta | Y84: =IF(X83<>X84,"",(IF(F84<>"",F84,Y83))) | Z84: =IF(Y83<>Y84,"",(IF(G84<>"",G84,Z83))) | AA84: =IF(X84<>"",CONCATENATE(W84,"_",X84,"_",Y84,"_",Z84),W84) -> ACTIVOS NO CORRIENTES MANTENIDOS PARA LA VENTA_(-) Deterioro acumulado del valor de activos no corrientes mantenidos para la venta__
D85: ACTIVOS BIOLÓGICOS | S85: =+N85 -> 0 | T85: =IF(A85<>"",A85,T84) -> ESTADO DE SITUACIÓN FINANCIERA | U85: =IF(T84<>T85,"",(IF(B85<>"",B85,U84))) -> ACTIVO | V85: =IF(U84<>U85,"",(IF(C85<>"",C85,V84))) -> ACTIVOS CORRIENTES | W85: =IF(V84<>V85,"",(IF(D85<>"",D85,W84))) -> ACTIVOS BIOLÓGICOS | X85: =IF(W84<>W85,"",(IF(E85<>"",E85,X84))) | Y85: =IF(X84<>X85,"",(IF(F85<>"",F85,Y84))) | Z85: =IF(Y84<>Y85,"",(IF(G85<>"",G85,Z84))) | AA85: =IF(X85<>"",CONCATENATE(W85,"_",X85,"_",Y85,"_",Z85),W85) -> ACTIVOS BIOLÓGICOS
E86: PLANTAS VIVAS Y FRUTOS EN CRECIMIENTO | S86: =+N86 -> 0 | T86: =IF(A86<>"",A86,T85) -> ESTADO DE SITUACIÓN FINANCIERA | U86: =IF(T85<>T86,"",(IF(B86<>"",B86,U85))) -> ACTIVO | V86: =IF(U85<>U86,"",(IF(C86<>"",C86,V85))) -> ACTIVOS CORRIENTES | W86: =IF(V85<>V86,"",(IF(D86<>"",D86,W85))) -> ACTIVOS BIOLÓGICOS | X86: =IF(W85<>W86,"",(IF(E86<>"",E86,X85))) -> PLANTAS VIVAS Y FRUTOS EN CRECIMIENTO | Y86: =IF(X85<>X86,"",(IF(F86<>"",F86,Y85))) | Z86: =IF(Y85<>Y86,"",(IF(G86<>"",G86,Z85))) | AA86: =IF(X86<>"",CONCATENATE(W86,"_",X86,"_",Y86,"_",Z86),W86) -> ACTIVOS BIOLÓGICOS_PLANTAS VIVAS Y FRUTOS EN CRECIMIENTO__
F87: A costo | N87: 350 | O87: =VLOOKUP(N87,Casilleros!$A$4:$Q$830,17,FALSE) -> #REF! | S87: =+N87 -> 350 | T87: =IF(A87<>"",A87,T86) -> ESTADO DE SITUACIÓN FINANCIERA | U87: =IF(T86<>T87,"",(IF(B87<>"",B87,U86))) -> ACTIVO | V87: =IF(U86<>U87,"",(IF(C87<>"",C87,V86))) -> ACTIVOS CORRIENTES | W87: =IF(V86<>V87,"",(IF(D87<>"",D87,W86))) -> ACTIVOS BIOLÓGICOS | X87: =IF(W86<>W87,"",(IF(E87<>"",E87,X86))) -> PLANTAS VIVAS Y FRUTOS EN CRECIMIENTO | Y87: =IF(X86<>X87,"",(IF(F87<>"",F87,Y86))) -> A costo | Z87: =IF(Y86<>Y87,"",(IF(G87<>"",G87,Z86))) | AA87: =IF(X87<>"",CONCATENATE(W87,"_",X87,"_",Y87,"_",Z87),W87) -> ACTIVOS BIOLÓGICOS_PLANTAS VIVAS Y FRUTOS EN CRECIMIENTO_A costo_
F88: (-) Deterioro acumulado del valor de activos biológicos medidos a costo | N88: 351 | O88: =VLOOKUP(N88,Casilleros!$A$4:$Q$830,17,FALSE) -> #REF! | S88: =+N88 -> 351 | T88: =IF(A88<>"",A88,T87) -> ESTADO DE SITUACIÓN FINANCIERA | U88: =IF(T87<>T88,"",(IF(B88<>"",B88,U87))) -> ACTIVO | V88: =IF(U87<>U88,"",(IF(C88<>"",C88,V87))) -> ACTIVOS CORRIENTES | W88: =IF(V87<>V88,"",(IF(D88<>"",D88,W87))) -> ACTIVOS BIOLÓGICOS | X88: =IF(W87<>W88,"",(IF(E88<>"",E88,X87))) -> PLANTAS VIVAS Y FRUTOS EN CRECIMIENTO | Y88: =IF(X87<>X88,"",(IF(F88<>"",F88,Y87))) -> (-) Deterioro acumulado del valor de activos biológicos medidos a costo | Z88: =IF(Y87<>Y88,"",(IF(G88<>"",G88,Z87))) | AA88: =IF(X88<>"",CONCATENATE(W88,"_",X88,"_",Y88,"_",Z88),W88) -> ACTIVOS BIOLÓGICOS_PLANTAS VIVAS Y FRUTOS EN CRECIMIENTO_(-) Deterioro acumulado del valor de activos biológicos medidos a costo_
F89: A valor razonable menos los costos de venta | N89: 352 | O89: =VLOOKUP(N89,Casilleros!$A$4:$Q$830,17,FALSE) -> #REF! | S89: =+N89 -> 352 | T89: =IF(A89<>"",A89,T88) -> ESTADO DE SITUACIÓN FINANCIERA | U89: =IF(T88<>T89,"",(IF(B89<>"",B89,U88))) -> ACTIVO | V89: =IF(U88<>U89,"",(IF(C89<>"",C89,V88))) -> ACTIVOS CORRIENTES | W89: =IF(V88<>V89,"",(IF(D89<>"",D89,W88))) -> ACTIVOS BIOLÓGICOS | X89: =IF(W88<>W89,"",(IF(E89<>"",E89,X88))) -> PLANTAS VIVAS Y FRUTOS EN CRECIMIENTO | Y89: =IF(X88<>X89,"",(IF(F89<>"",F89,Y88))) -> A valor razonable menos los costos de venta | Z89: =IF(Y88<>Y89,"",(IF(G89<>"",G89,Z88))) | AA89: =IF(X89<>"",CONCATENATE(W89,"_",X89,"_",Y89,"_",Z89),W89) -> ACTIVOS BIOLÓGICOS_PLANTAS VIVAS Y FRUTOS EN CRECIMIENTO_A valor razonable menos los costos de venta_
E90: ANIMALES VIVOS | S90: =+N90 -> 0 | T90: =IF(A90<>"",A90,T89) -> ESTADO DE SITUACIÓN FINANCIERA | U90: =IF(T89<>T90,"",(IF(B90<>"",B90,U89))) -> ACTIVO | V90: =IF(U89<>U90,"",(IF(C90<>"",C90,V89))) -> ACTIVOS CORRIENTES | W90: =IF(V89<>V90,"",(IF(D90<>"",D90,W89))) -> ACTIVOS BIOLÓGICOS | X90: =IF(W89<>W90,"",(IF(E90<>"",E90,X89))) -> ANIMALES VIVOS | Y90: =IF(X89<>X90,"",(IF(F90<>"",F90,Y89))) | Z90: =IF(Y89<>Y90,"",(IF(G90<>"",G90,Z89))) | AA90: =IF(X90<>"",CONCATENATE(W90,"_",X90,"_",Y90,"_",Z90),W90) -> ACTIVOS BIOLÓGICOS_ANIMALES VIVOS__
F91: A costo | N91: 353 | O91: =VLOOKUP(N91,Casilleros!$A$4:$Q$830,17,FALSE) -> #REF! | S91: =+N91 -> 353 | T91: =IF(A91<>"",A91,T90) -> ESTADO DE SITUACIÓN FINANCIERA | U91: =IF(T90<>T91,"",(IF(B91<>"",B91,U90))) -> ACTIVO | V91: =IF(U90<>U91,"",(IF(C91<>"",C91,V90))) -> ACTIVOS CORRIENTES | W91: =IF(V90<>V91,"",(IF(D91<>"",D91,W90))) -> ACTIVOS BIOLÓGICOS | X91: =IF(W90<>W91,"",(IF(E91<>"",E91,X90))) -> ANIMALES VIVOS | Y91: =IF(X90<>X91,"",(IF(F91<>"",F91,Y90))) -> A costo | Z91: =IF(Y90<>Y91,"",(IF(G91<>"",G91,Z90))) | AA91: =IF(X91<>"",CONCATENATE(W91,"_",X91,"_",Y91,"_",Z91),W91) -> ACTIVOS BIOLÓGICOS_ANIMALES VIVOS_A costo_
F92: (-) Deterioro acumulado del valor de activos biológicos medidos a costo | N92: 354 | O92: =VLOOKUP(N92,Casilleros!$A$4:$Q$830,17,FALSE) -> #REF! | S92: =+N92 -> 354 | T92: =IF(A92<>"",A92,T91) -> ESTADO DE SITUACIÓN FINANCIERA | U92: =IF(T91<>T92,"",(IF(B92<>"",B92,U91))) -> ACTIVO | V92: =IF(U91<>U92,"",(IF(C92<>"",C92,V91))) -> ACTIVOS CORRIENTES | W92: =IF(V91<>V92,"",(IF(D92<>"",D92,W91))) -> ACTIVOS BIOLÓGICOS | X92: =IF(W91<>W92,"",(IF(E92<>"",E92,X91))) -> ANIMALES VIVOS | Y92: =IF(X91<>X92,"",(IF(F92<>"",F92,Y91))) -> (-) Deterioro acumulado del valor de activos biológicos medidos a costo | Z92: =IF(Y91<>Y92,"",(IF(G92<>"",G92,Z91))) | AA92: =IF(X92<>"",CONCATENATE(W92,"_",X92,"_",Y92,"_",Z92),W92) -> ACTIVOS BIOLÓGICOS_ANIMALES VIVOS_(-) Deterioro acumulado del valor de activos biológicos medidos a costo_
F93: A valor razonable menos los costos de venta | N93: 355 | O93: =VLOOKUP(N93,Casilleros!$A$4:$Q$830,17,FALSE) -> #REF! | S93: =+N93 -> 355 | T93: =IF(A93<>"",A93,T92) -> ESTADO DE SITUACIÓN FINANCIERA | U93: =IF(T92<>T93,"",(IF(B93<>"",B93,U92))) -> ACTIVO | V93: =IF(U92<>U93,"",(IF(C93<>"",C93,V92))) -> ACTIVOS CORRIENTES | W93: =IF(V92<>V93,"",(IF(D93<>"",D93,W92))) -> ACTIVOS BIOLÓGICOS | X93: =IF(W92<>W93,"",(IF(E93<>"",E93,X92))) -> ANIMALES VIVOS | Y93: =IF(X92<>X93,"",(IF(F93<>"",F93,Y92))) -> A valor razonable menos los costos de venta | Z93: =IF(Y92<>Y93,"",(IF(G93<>"",G93,Z92))) | AA93: =IF(X93<>"",CONCATENATE(W93,"_",X93,"_",Y93,"_",Z93),W93) -> ACTIVOS BIOLÓGICOS_ANIMALES VIVOS_A valor razonable menos los costos de venta_
D94: GASTOS PAGADOS POR ANTICIPADO (PREPAGADOS) | S94: =+N94 -> 0 | T94: =IF(A94<>"",A94,T93) -> ESTADO DE SITUACIÓN FINANCIERA | U94: =IF(T93<>T94,"",(IF(B94<>"",B94,U93))) -> ACTIVO | V94: =IF(U93<>U94,"",(IF(C94<>"",C94,V93))) -> ACTIVOS CORRIENTES | W94: =IF(V93<>V94,"",(IF(D94<>"",D94,W93))) -> GASTOS PAGADOS POR ANTICIPADO (PREPAGADOS) | X94: =IF(W93<>W94,"",(IF(E94<>"",E94,X93))) | Y94: =IF(X93<>X94,"",(IF(F94<>"",F94,Y93))) | Z94: =IF(Y93<>Y94,"",(IF(G94<>"",G94,Z93))) | AA94: =IF(X94<>"",CONCATENATE(W94,"_",X94,"_",Y94,"_",Z94),W94) -> GASTOS PAGADOS POR ANTICIPADO (PREPAGADOS)
E95: Propaganda y publicidad prepagada | N95: 356 | O95: =VLOOKUP(N95,Casilleros!$A$4:$Q$830,17,FALSE) -> #REF! | S95: =+N95 -> 356 | T95: =IF(A95<>"",A95,T94) -> ESTADO DE SITUACIÓN FINANCIERA | U95: =IF(T94<>T95,"",(IF(B95<>"",B95,U94))) -> ACTIVO | V95: =IF(U94<>U95,"",(IF(C95<>"",C95,V94))) -> ACTIVOS CORRIENTES | W95: =IF(V94<>V95,"",(IF(D95<>"",D95,W94))) -> GASTOS PAGADOS POR ANTICIPADO (PREPAGADOS) | X95: =IF(W94<>W95,"",(IF(E95<>"",E95,X94))) -> Propaganda y publicidad prepagada | Y95: =IF(X94<>X95,"",(IF(F95<>"",F95,Y94))) | Z95: =IF(Y94<>Y95,"",(IF(G95<>"",G95,Z94))) | AA95: =IF(X95<>"",CONCATENATE(W95,"_",X95,"_",Y95,"_",Z95),W95) -> GASTOS PAGADOS POR ANTICIPADO (PREPAGADOS)_Propaganda y publicidad prepagada__
E96: Arrendamientos operativos pagados por anticipado | N96: 357 | O96: =VLOOKUP(N96,Casilleros!$A$4:$Q$830,17,FALSE) -> #REF! | S96: =+N96 -> 357 | T96: =IF(A96<>"",A96,T95) -> ESTADO DE SITUACIÓN FINANCIERA | U96: =IF(T95<>T96,"",(IF(B96<>"",B96,U95))) -> ACTIVO | V96: =IF(U95<>U96,"",(IF(C96<>"",C96,V95))) -> ACTIVOS CORRIENTES | W96: =IF(V95<>V96,"",(IF(D96<>"",D96,W95))) -> GASTOS PAGADOS POR ANTICIPADO (PREPAGADOS) | X96: =IF(W95<>W96,"",(IF(E96<>"",E96,X95))) -> Arrendamientos operativos pagados por anticipado | Y96: =IF(X95<>X96,"",(IF(F96<>"",F96,Y95))) | Z96: =IF(Y95<>Y96,"",(IF(G96<>"",G96,Z95))) | AA96: =IF(X96<>"",CONCATENATE(W96,"_",X96,"_",Y96,"_",Z96),W96) -> GASTOS PAGADOS POR ANTICIPADO (PREPAGADOS)_Arrendamientos operativos pagados por anticipado__
E97: Primas de seguro pagadas por anticipado | N97: 358 | O97: =VLOOKUP(N97,Casilleros!$A$4:$Q$830,17,FALSE) -> #REF! | S97: =+N97 -> 358 | T97: =IF(A97<>"",A97,T96) -> ESTADO DE SITUACIÓN FINANCIERA | U97: =IF(T96<>T97,"",(IF(B97<>"",B97,U96))) -> ACTIVO | V97: =IF(U96<>U97,"",(IF(C97<>"",C97,V96))) -> ACTIVOS CORRIENTES | W97: =IF(V96<>V97,"",(IF(D97<>"",D97,W96))) -> GASTOS PAGADOS POR ANTICIPADO (PREPAGADOS) | X97: =IF(W96<>W97,"",(IF(E97<>"",E97,X96))) -> Primas de seguro pagadas por anticipado | Y97: =IF(X96<>X97,"",(IF(F97<>"",F97,Y96))) | Z97: =IF(Y96<>Y97,"",(IF(G97<>"",G97,Z96))) | AA97: =IF(X97<>"",CONCATENATE(W97,"_",X97,"_",Y97,"_",Z97),W97) -> GASTOS PAGADOS POR ANTICIPADO (PREPAGADOS)_Primas de seguro pagadas por anticipado__
E98: Otros | N98: 359 | O98: =VLOOKUP(N98,Casilleros!$A$4:$Q$830,17,FALSE) -> #REF! | S98: =+N98 -> 359 | T98: =IF(A98<>"",A98,T97) -> ESTADO DE SITUACIÓN FINANCIERA | U98: =IF(T97<>T98,"",(IF(B98<>"",B98,U97))) -> ACTIVO | V98: =IF(U97<>U98,"",(IF(C98<>"",C98,V97))) -> ACTIVOS CORRIENTES | W98: =IF(V97<>V98,"",(IF(D98<>"",D98,W97))) -> GASTOS PAGADOS POR ANTICIPADO (PREPAGADOS) | X98: =IF(W97<>W98,"",(IF(E98<>"",E98,X97))) -> Otros | Y98: =IF(X97<>X98,"",(IF(F98<>"",F98,Y97))) | Z98: =IF(Y97<>Y98,"",(IF(G98<>"",G98,Z97))) | AA98: =IF(X98<>"",CONCATENATE(W98,"_",X98,"_",Y98,"_",Z98),W98) -> GASTOS PAGADOS POR ANTICIPADO (PREPAGADOS)_Otros__
D99: Otros Activos Corrientes | N99: 360 | O99: =VLOOKUP(N99,Casilleros!$A$4:$Q$830,17,FALSE) -> #REF! | S99: =+N99 -> 360 | T99: =IF(A99<>"",A99,T98) -> ESTADO DE SITUACIÓN FINANCIERA | U99: =IF(T98<>T99,"",(IF(B99<>"",B99,U98))) -> ACTIVO | V99: =IF(U98<>U99,"",(IF(C99<>"",C99,V98))) -> ACTIVOS CORRIENTES | W99: =IF(V98<>V99,"",(IF(D99<>"",D99,W98))) -> Otros Activos Corrientes | X99: =IF(W98<>W99,"",(IF(E99<>"",E99,X98))) | Y99: =IF(X98<>X99,"",(IF(F99<>"",F99,Y98))) | Z99: =IF(Y98<>Y99,"",(IF(G99<>"",G99,Z98))) | AA99: =IF(X99<>"",CONCATENATE(W99,"_",X99,"_",Y99,"_",Z99),W99) -> Otros Activos Corrientes
C100: TOTAL ACTIVOS CORRIENTES | N100: 361 | O100: =SUM(O30:O99) -> #REF! | S100: =+N100 -> 361 | T100: =IF(A100<>"",A100,T99) -> ESTADO DE SITUACIÓN FINANCIERA | U100: =IF(T99<>T100,"",(IF(B100<>"",B100,U99))) -> ACTIVO | V100: =IF(U99<>U100,"",(IF(C100<>"",C100,V99))) -> TOTAL ACTIVOS CORRIENTES | W100: =IF(V99<>V100,"",(IF(D100<>"",D100,W99))) | X100: =IF(W99<>W100,"",(IF(E100<>"",E100,X99))) | Y100: =IF(X99<>X100,"",(IF(F100<>"",F100,Y99))) | Z100: =IF(Y99<>Y100,"",(IF(G100<>"",G100,Z99))) | AA100: =IF(X100<>"",CONCATENATE(W100,"_",X100,"_",Y100,"_",Z100,""),CONCATENATE(U100,"_",V100, "_",W100,"")) -> ACTIVO_TOTAL ACTIVOS CORRIENTES_
C101: ACTIVOS NO CORRIENTES | S101: =+N101 -> 0 | T101: =IF(A101<>"",A101,T100) -> ESTADO DE SITUACIÓN FINANCIERA | U101: =IF(T100<>T101,"",(IF(B101<>"",B101,U100))) -> ACTIVO | V101: =IF(U100<>U101,"",(IF(C101<>"",C101,V100))) -> ACTIVOS NO CORRIENTES | W101: =IF(V100<>V101,"",(IF(D101<>"",D101,W100))) | X101: =IF(W100<>W101,"",(IF(E101<>"",E101,X100))) | Y101: =IF(X100<>X101,"",(IF(F101<>"",F101,Y100))) | Z101: =IF(Y100<>Y101,"",(IF(G101<>"",G101,Z100))) | AA101: =IF(X101<>"",CONCATENATE(W101,"_",X101,"_",Y101,"_",Z101),W101)
...

Sheet Tipo
B1: INGRESOS | D1: N. EMPLEADOS
A2: LIMITES | B2: Desde | C2: Hasta | D2: Desde | E2: Hasta
A3: MICROEMPRESA | B3: 0 | C3: 300000 | D3: 1 | E3: 9
A4: PEQUEÑA EMPRESA | B4: =+C3+1 -> 300001 | C4: 1000000 | D4: =+E3+1 -> 10 | E4: 49
A5: MEDIANA EMPRESA | B5: =+C4+1 -> 1000001 | C5: 5000000 | D5: =+E4+1 -> 50 | E5: 199

Sheet Casilleros
A1: =RAZÓN_SOCIAL -> #REF!
A2: Detalle de casilleros F101
A3: =Ejercicio_fiscal -> #REF!
A4: casillero | B4: Descripción1 | C4: Descripción2 | D4: Descripción3 | E4: Descripción4 | F4: Descripción5 | G4: Descripción6 | H4: Descripción7 | I4: Descripción_casillero | J4: Mapeo EF | K4: Monto BC | L4: Monto IE/No objeto | M4: Monto GND | N4: Deducciones adicionales | O4: Impuestos diferidos | P4: Casilleros Informativos | Q4: Total
A5: 003 | B5: OPERACIONES CON PARTES RELACIONADAS LOCALES Y/O DEL EXTERIOR | C5: CON PARTES RELACIONADAS LOCALES | D5: Operaciones de activo | I5: CON PARTES RELACIONADAS LOCALES_Operaciones de activo_ | K5: =SUMIF(BC!$E$6:$E$347,$A5,BC!$K$6:$K$347) -> 0 | L5: =SUMIF(#REF!,$A5,#REF!)+SUMIF(#REF!,$A5,#REF!) -> #REF! | M5: =SUMIF(#REF!,Casilleros!$A5,#REF!)+SUMIF(#REF!,Casilleros!$A5,#REF!)+SUMIF(#REF!,$A5,#REF!) -> #REF! | N5: =SUMIF(#REF!,$A5,#REF!) -> #REF! | O5: =SUMIF(#REF!,$A5,#REF!)+SUMIF(#REF!,$A5,#REF!) -> #REF! | P5: =IFERROR(VLOOKUP($A5,#REF!,2,FALSE),0) -> 0 | Q5: =SUM(K5:P5) -> #REF!
A6: 004 | B6: OPERACIONES CON PARTES RELACIONADAS LOCALES Y/O DEL EXTERIOR | C6: CON PARTES RELACIONADAS LOCALES | D6: Operaciones de pasivo | I6: CON PARTES RELACIONADAS LOCALES_Operaciones de pasivo_ | K6: =SUMIF(BC!$E$6:$E$347,$A6,BC!$K$6:$K$347) -> 0 | L6: =SUMIF(#REF!,$A6,#REF!)+SUMIF(#REF!,$A6,#REF!) -> #REF! | M6: =SUMIF(#REF!,Casilleros!$A6,#REF!)+SUMIF(#REF!,Casilleros!$A6,#REF!)+SUMIF(#REF!,$A6,#REF!) -> #REF! | N6: =SUMIF(#REF!,$A6,#REF!) -> #REF! | O6: =SUMIF(#REF!,$A6,#REF!)+SUMIF(#REF!,$A6,#REF!) -> #REF! | P6: =IFERROR(VLOOKUP($A6,#REF!,2,FALSE),0) -> 0 | Q6: =SUM(K6:P6) -> #REF!
A7: 005 | B7: OPERACIONES CON PARTES RELACIONADAS LOCALES Y/O DEL EXTERIOR | C7: CON PARTES RELACIONADAS LOCALES | D7: Operaciones de ingreso | I7: CON PARTES RELACIONADAS LOCALES_Operaciones de ingreso_ | K7: =SUMIF(BC!$E$6:$E$347,$A7,BC!$K$6:$K$347) -> 0 | L7: =SUMIF(#REF!,$A7,#REF!)+SUMIF(#REF!,$A7,#REF!) -> #REF! | M7: =SUMIF(#REF!,Casilleros!$A7,#REF!)+SUMIF(#REF!,Casilleros!$A7,#REF!)+SUMIF(#REF!,$A7,#REF!) -> #REF! | N7: =SUMIF(#REF!,$A7,#REF!) -> #REF! | O7: =SUMIF(#REF!,$A7,#REF!)+SUMIF(#REF!,$A7,#REF!) -> #REF! | P7: =IFERROR(VLOOKUP($A7,#REF!,2,FALSE),0) -> 0 | Q7: =SUM(K7:P7) -> #REF!
A8: 006 | B8: OPERACIONES CON PARTES RELACIONADAS LOCALES Y/O DEL EXTERIOR | C8: CON PARTES RELACIONADAS LOCALES | D8: Operaciones de egreso | I8: CON PARTES RELACIONADAS LOCALES_Operaciones de egreso_ | K8: =SUMIF(BC!$E$6:$E$347,$A8,BC!$K$6:$K$347) -> 0 | L8: =SUMIF(#REF!,$A8,#REF!)+SUMIF(#REF!,$A8,#REF!) -> #REF! | M8: =SUMIF(#REF!,Casilleros!$A8,#REF!)+SUMIF(#REF!,Casilleros!$A8,#REF!)+SUMIF(#REF!,$A8,#REF!) -> #REF! | N8: =SUMIF(#REF!,$A8,#REF!) -> #REF! | O8: =SUMIF(#REF!,$A8,#REF!)+SUMIF(#REF!,$A8,#REF!) -> #REF! | P8: =IFERROR(VLOOKUP($A8,#REF!,2,FALSE),0) -> 0 | Q8: =SUM(K8:P8) -> #REF!
A9: 007 | B9: OPERACIONES CON PARTES RELACIONADAS LOCALES Y/O DEL EXTERIOR | C9: CON PARTES RELACIONADAS LOCALES | D9: Operaciones de regalías, servicios técnicos, administrativos, de consultoría y similares | I9: CON PARTES RELACIONADAS LOCALES_Operaciones de regalías, servicios técnicos, administrativos, de consultoría y similares_ | K9: =SUMIF(BC!$E$6:$E$347,$A9,BC!$K$6:$K$347) -> 0 | L9: =SUMIF(#REF!,$A9,#REF!)+SUMIF(#REF!,$A9,#REF!) -> #REF! | M9: =SUMIF(#REF!,Casilleros!$A9,#REF!)+SUMIF(#REF!,Casilleros!$A9,#REF!)+SUMIF(#REF!,$A9,#REF!) -> #REF! | N9: =SUMIF(#REF!,$A9,#REF!) -> #REF! | O9: =SUMIF(#REF!,$A9,#REF!)+SUMIF(#REF!,$A9,#REF!) -> #REF! | P9: =IFERROR(VLOOKUP($A9,#REF!,2,FALSE),0) -> 0 | Q9: =SUM(K9:P9) -> #REF!
A10: 008 | B10: OPERACIONES CON PARTES RELACIONADAS LOCALES Y/O DEL EXTERIOR | C10: CON PARTES RELACIONADAS EN PARAÍSOS FISCALES, JURISDICCIONES DE MENOR IMPOSICIÓN Y RÉGIMENES FISCALES PREFERENTES | D10: Operaciones de activo | I10: CON PARTES RELACIONADAS EN PARAÍSOS FISCALES, JURISDICCIONES DE MENOR IMPOSICIÓN Y RÉGIMENES FISCALES PREFERENTES_Operaciones de activo_ | K10: =SUMIF(BC!$E$6:$E$347,$A10,BC!$K$6:$K$347) -> 0 | L10: =SUMIF(#REF!,$A10,#REF!)+SUMIF(#REF!,$A10,#REF!) -> #REF! | M10: =SUMIF(#REF!,Casilleros!$A10,#REF!)+SUMIF(#REF!,Casilleros!$A10,#REF!)+SUMIF(#REF!,$A10,#REF!) -> #REF! | N10: =SUMIF(#REF!,$A10,#REF!) -> #REF! | O10: =SUMIF(#REF!,$A10,#REF!)+SUMIF(#REF!,$A10,#REF!) -> #REF! | P10: =IFERROR(VLOOKUP($A10,#REF!,2,FALSE),0) -> 0 | Q10: =SUM(K10:P10) -> #REF!
A11: 009 | B11: OPERACIONES CON PARTES RELACIONADAS LOCALES Y/O DEL EXTERIOR | C11: CON PARTES RELACIONADAS EN PARAÍSOS FISCALES, JURISDICCIONES DE MENOR IMPOSICIÓN Y RÉGIMENES FISCALES PREFERENTES | D11: Operaciones de pasivo | I11: CON PARTES RELACIONADAS EN PARAÍSOS FISCALES, JURISDICCIONES DE MENOR IMPOSICIÓN Y RÉGIMENES FISCALES PREFERENTES_Operaciones de pasivo_ | K11: =SUMIF(BC!$E$6:$E$347,$A11,BC!$K$6:$K$347) -> 0 | L11: =SUMIF(#REF!,$A11,#REF!)+SUMIF(#REF!,$A11,#REF!) -> #REF! | M11: =SUMIF(#REF!,Casilleros!$A11,#REF!)+SUMIF(#REF!,Casilleros!$A11,#REF!)+SUMIF(#REF!,$A11,#REF!) -> #REF! | N11: =SUMIF(#REF!,$A11,#REF!) -> #REF! | O11: =SUMIF(#REF!,$A11,#REF!)+SUMIF(#REF!,$A11,#REF!) -> #REF! | P11: =IFERROR(VLOOKUP($A11,#REF!,2,FALSE),0) -> 0 | Q11: =SUM(K11:P11) -> #REF!
A12: 010 | B12: OPERACIONES CON PARTES RELACIONADAS LOCALES Y/O DEL EXTERIOR | C12: CON PARTES RELACIONADAS EN PARAÍSOS FISCALES, JURISDICCIONES DE MENOR IMPOSICIÓN Y RÉGIMENES FISCALES PREFERENTES | D12: Operaciones de ingreso | I12: CON PARTES RELACIONADAS EN PARAÍSOS FISCALES, JURISDICCIONES DE MENOR IMPOSICIÓN Y RÉGIMENES FISCALES PREFERENTES_Operaciones de ingreso_ | K12: =SUMIF(BC!$E$6:$E$347,$A12,BC!$K$6:$K$347) -> 0 | L12: =SUMIF(#REF!,$A12,#REF!)+SUMIF(#REF!,$A12,#REF!) -> #REF! | M12: =SUMIF(#REF!,Casilleros!$A12,#REF!)+SUMIF(#REF!,Casilleros!$A12,#REF!)+SUMIF(#REF!,$A12,#REF!) -> #REF! | N12: =SUMIF(#REF!,$A12,#REF!) -> #REF! | O12: =SUMIF(#REF!,$A12,#REF!)+SUMIF(#REF!,$A12,#REF!) -> #REF! | P12: =IFERROR(VLOOKUP($A12,#REF!,2,FALSE),0) -> 0 | Q12: =SUM(K12:P12) -> #REF!
A13: 011 | B13: OPERACIONES CON PARTES RELACIONADAS LOCALES Y/O DEL EXTERIOR | C13: CON PARTES RELACIONADAS EN PARAÍSOS FISCALES, JURISDICCIONES DE MENOR IMPOSICIÓN Y RÉGIMENES FISCALES PREFERENTES | D13: Operaciones de egreso | I13: CON PARTES RELACIONADAS EN PARAÍSOS FISCALES, JURISDICCIONES DE MENOR IMPOSICIÓN Y RÉGIMENES FISCALES PREFERENTES_Operaciones de egreso_ | K13: =SUMIF(BC!$E$6:$E$347,$A13,BC!$K$6:$K$347) -> 0 | L13: =SUMIF(#REF!,$A13,#REF!)+SUMIF(#REF!,$A13,#REF!) -> #REF! | M13: =SUMIF(#REF!,Casilleros!$A13,#REF!)+SUMIF(#REF!,Casilleros!$A13,#REF!)+SUMIF(#REF!,$A13,#REF!) -> #REF! | N13: =SUMIF(#REF!,$A13,#REF!) -> #REF! | O13: =SUMIF(#REF!,$A13,#REF!)+SUMIF(#REF!,$A13,#REF!) -> #REF! | P13: =IFERROR(VLOOKUP($A13,#REF!,2,FALSE),0) -> 0 | Q13: =SUM(K13:P13) -> #REF!
A14: 012 | B14: OPERACIONES CON PARTES RELACIONADAS LOCALES Y/O DEL EXTERIOR | C14: CON PARTES RELACIONADAS EN PARAÍSOS FISCALES, JURISDICCIONES DE MENOR IMPOSICIÓN Y RÉGIMENES FISCALES PREFERENTES | D14: Operaciones de regalías, servicios técnicos, administrativos, de consultoría y similares | I14: CON PARTES RELACIONADAS EN PARAÍSOS FISCALES, JURISDICCIONES DE MENOR IMPOSICIÓN Y RÉGIMENES FISCALES PREFERENTES_Operaciones de regalías, servicios técnicos, administrativos, de consultoría y similares_ | K14: =SUMIF(BC!$E$6:$E$347,$A14,BC!$K$6:$K$347) -> 0 | L14: =SUMIF(#REF!,$A14,#REF!)+SUMIF(#REF!,$A14,#REF!) -> #REF! | M14: =SUMIF(#REF!,Casilleros!$A14,#REF!)+SUMIF(#REF!,Casilleros!$A14,#REF!)+SUMIF(#REF!,$A14,#REF!) -> #REF! | N14: =SUMIF(#REF!,$A14,#REF!) -> #REF! | O14: =SUMIF(#REF!,$A14,#REF!)+SUMIF(#REF!,$A14,#REF!) -> #REF! | P14: =IFERROR(VLOOKUP($A14,#REF!,2,FALSE),0) -> 0 | Q14: =SUM(K14:P14) -> #REF!
A15: 013 | B15: OPERACIONES CON PARTES RELACIONADAS LOCALES Y/O DEL EXTERIOR | C15: CON PARTES RELACIONADAS EN OTRAS JURISDICCIONES O RÉGIMENES DEL EXTERIOR | D15: Operaciones de activo | I15: CON PARTES RELACIONADAS EN OTRAS JURISDICCIONES O RÉGIMENES DEL EXTERIOR_Operaciones de activo_ | K15: =SUMIF(BC!$E$6:$E$347,$A15,BC!$K$6:$K$347) -> 0 | L15: =SUMIF(#REF!,$A15,#REF!)+SUMIF(#REF!,$A15,#REF!) -> #REF! | M15: =SUMIF(#REF!,Casilleros!$A15,#REF!)+SUMIF(#REF!,Casilleros!$A15,#REF!)+SUMIF(#REF!,$A15,#REF!) -> #REF! | N15: =SUMIF(#REF!,$A15,#REF!) -> #REF! | O15: =SUMIF(#REF!,$A15,#REF!)+SUMIF(#REF!,$A15,#REF!) -> #REF! | P15: =IFERROR(VLOOKUP($A15,#REF!,2,FALSE),0) -> 0 | Q15: =SUM(K15:P15) -> #REF!
A16: 014 | B16: OPERACIONES CON PARTES RELACIONADAS LOCALES Y/O DEL EXTERIOR | C16: CON PARTES RELACIONADAS EN OTRAS JURISDICCIONES O RÉGIMENES DEL EXTERIOR | D16: Operaciones de pasivo | I16: CON PARTES RELACIONADAS EN OTRAS JURISDICCIONES O RÉGIMENES DEL EXTERIOR_Operaciones de pasivo_ | K16: =SUMIF(BC!$E$6:$E$347,$A16,BC!$K$6:$K$347) -> 0 | L16: =SUMIF(#REF!,$A16,#REF!)+SUMIF(#REF!,$A16,#REF!) -> #REF! | M16: =SUMIF(#REF!,Casilleros!$A16,#REF!)+SUMIF(#REF!,Casilleros!$A16,#REF!)+SUMIF(#REF!,$A16,#REF!) -> #REF! | N16: =SUMIF(#REF!,$A16,#REF!) -> #REF! | O16: =SUMIF(#REF!,$A16,#REF!)+SUMIF(#REF!,$A16,#REF!) -> #REF! | P16: =IFERROR(VLOOKUP($A16,#REF!,2,FALSE),0) -> 0 | Q16: =SUM(K16:P16) -> #REF!
... A19: 017 | B19: OPERACIONES CON PARTES RELACIONADAS LOCALES Y/O DEL EXTERIOR | C19: CON PARTES RELACIONADAS EN OTRAS JURISDICCIONES O RÉGIMENES DEL EXTERIOR | D19: Operaciones de regalías, servicios técnicos, administrativos, de consultoría y similares | I19: CON PARTES RELACIONADAS EN OTRAS JURISDICCIONES O RÉGIMENES DEL EXTERIOR_Operaciones de regalías, servicios técnicos, administrativos, de consultoría y similares_ | K19: =SUMIF(BC!$E$6:$E$347,$A19,BC!$K$6:$K$347) -> 0 | L19: =SUMIF(#REF!,$A19,#REF!)+SUMIF(#REF!,$A19,#REF!) -> #REF! | M19: =SUMIF(#REF!,Casilleros!$A19,#REF!)+SUMIF(#REF!,Casilleros!$A19,#REF!)+SUMIF(#REF!,$A19,#REF!) -> #REF! | N19: =SUMIF(#REF!,$A19,#REF!) -> #REF! | O19: =SUMIF(#REF!,$A19,#REF!)+SUMIF(#REF!,$A19,#REF!) -> #REF! | P19: =IFERROR(VLOOKUP($A19,#REF!,2,FALSE),0) -> 0 | Q19: =SUM(K19:P19) -> #REF!
A20: 029 | B20: OPERACIONES CON PARTES RELACIONADAS LOCALES Y/O DEL EXTERIOR | C20: TOTAL OPERACIONES CON PARTES RELACIONADAS | I20: TOTAL OPERACIONES CON PARTES RELACIONADAS__ | K20: =SUMIF(BC!$E$6:$E$347,$A20,BC!$K$6:$K$347) -> 0 | L20: =SUMIF(#REF!,$A20,#REF!)+SUMIF(#REF!,$A20,#REF!) -> #REF! | M20: =SUMIF(#REF!,Casilleros!$A20,#REF!)+SUMIF(#REF!,Casilleros!$A20,#REF!)+SUMIF(#REF!,$A20,#REF!) -> #REF! | N20: =SUMIF(#REF!,$A20,#REF!) -> #REF! | O20: =SUMIF(#REF!,$A20,#REF!)+SUMIF(#REF!,$A20,#REF!) -> #REF! | P20: =IFERROR(VLOOKUP($A20,#REF!,2,FALSE),0) -> 0 | Q20: =SUM(K20:P20) -> #REF!
A21: 030 | B21: OPERACIONES CON PARTES RELACIONADAS LOCALES Y/O DEL EXTERIOR | C21: ¿Sujeto pasivo exento de aplicación del régimen de precios de transferencia? | I21: ¿Sujeto pasivo exento de aplicación del régimen de precios de transferencia?__ | K21: =SUMIF(BC!$E$6:$E$347,$A21,BC!$K$6:$K$347) -> 0 | L21: =SUMIF(#REF!,$A21,#REF!)+SUMIF(#REF!,$A21,#REF!) -> #REF! | M21: =SUMIF(#REF!,Casilleros!$A21,#REF!)+SUMIF(#REF!,Casilleros!$A21,#REF!)+SUMIF(#REF!,$A21,#REF!) -> #REF! | N21: =SUMIF(#REF!,$A21,#REF!) -> #REF! | O21: =SUMIF(#REF!,$A21,#REF!)+SUMIF(#REF!,$A21,#REF!) -> #REF! | P21: =IFERROR(VLOOKUP($A21,#REF!,2,FALSE),0) -> 0 | Q21: =SUM(K21:P21) -> #REF!
A22: 311 | B22: ESTADO DE SITUACIÓN FINANCIERA | C22: ACTIVO | D22: ACTIVOS CORRIENTES | E22: Efectivo y equivalentes al efectivo | I22: Efectivo y equivalentes al efectivo | J22: Efectivo y equivalentes al efectivo | K22: =SUMIF(BC!$E$6:$E$347,$A22,BC!$K$6:$K$347) -> #REF! | L22: =SUMIF(#REF!,$A22,#REF!)+SUMIF(#REF!,$A22,#REF!) -> #REF! | M22: =SUMIF(#REF!,Casilleros!$A22,#REF!)+SUMIF(#REF!,Casilleros!$A22,#REF!)+SUMIF(#REF!,$A22,#REF!) -> #REF! | N22: =SUMIF(#REF!,$A22,#REF!) -> #REF! | O22: =SUMIF(#REF!,$A22,#REF!)+SUMIF(#REF!,$A22,#REF!) -> #REF! | P22: =IFERROR(VLOOKUP($A22,#REF!,2,FALSE),0) -> 0 | Q22: =SUM(K22:P22) -> #REF!
A23: 312 | B23: ESTADO DE SITUACIÓN FINANCIERA | C23: ACTIVO | D23: ACTIVOS CORRIENTES | E23: CUENTAS Y DOCUMENTOS POR COBRAR CORRIENTES | F23: CUENTAS Y DOCUMENTOS POR COBRAR COMERCIALES CORRIENTES | G23: RELACIONADAS | H23: Locales | I23: CUENTAS Y DOCUMENTOS POR COBRAR CORRIENTES_CUENTAS Y DOCUMENTOS POR COBRAR COMERCIALES CORRIENTES_RELACIONADAS_Locales | J23: Cuentas y Documentos por cobrar corrientes | K23: =SUMIF(BC!$E$6:$E$347,$A23,BC!$K$6:$K$347) -> 0 | L23: =SUMIF(#REF!,$A23,#REF!)+SUMIF(#REF!,$A23,#REF!) -> #REF! | M23: =SUMIF(#REF!,Casilleros!$A23,#REF!)+SUMIF(#REF!,Casilleros!$A23,#REF!)+SUMIF(#REF!,$A23,#REF!) -> #REF! | N23: =SUMIF(#REF!,$A23,#REF!) -> #REF! | O23: =SUMIF(#REF!,$A23,#REF!)+SUMIF(#REF!,$A23,#REF!) -> #REF! | P23: =IFERROR(VLOOKUP($A23,#REF!,2,FALSE),0) -> 0 | Q23: =SUM(K23:P23) -> #REF!
A24: 313 | B24: ESTADO DE SITUACIÓN FINANCIERA | C24: ACTIVO | D24: ACTIVOS CORRIENTES | E24: CUENTAS Y DOCUMENTOS POR COBRAR CORRIENTES | F24: CUENTAS Y DOCUMENTOS POR COBRAR COMERCIALES CORRIENTES | G24: RELACIONADAS | H24: Del exterior | I24: CUENTAS Y DOCUMENTOS POR COBRAR CORRIENTES_CUENTAS Y DOCUMENTOS POR COBRAR COMERCIALES CORRIENTES_RELACIONADAS_Del exterior | J24: Cuentas y Documentos por cobrar corrientes | K24: =SUMIF(BC!$E$6:$E$347,$A24,BC!$K$6:$K$347) -> 0 | L24: =SUMIF(#REF!,$A24,#REF!)+SUMIF(#REF!,$A24,#REF!) -> #REF! | M24: =SUMIF(#REF!,Casilleros!$A24,#REF!)+SUMIF(#REF!,Casilleros!$A24,#REF!)+SUMIF(#REF!,$A24,#REF!) -> #REF! | N24: =SUMIF(#REF!,$A24,#REF!) -> #REF! | O24: =SUMIF(#REF!,$A24,#REF!)+SUMIF(#REF!,$A24,#REF!) -> #REF! | P24: =IFERROR(VLOOKUP($A24,#REF!,2,FALSE),0) -> 0 | Q24: =SUM(K24:P24) -> #REF!
A25: 314 | B25: ESTADO DE SITUACIÓN FINANCIERA | C25: ACTIVO | D25: ACTIVOS CORRIENTES | E25: CUENTAS Y DOCUMENTOS POR COBRAR CORRIENTES | F25: CUENTAS Y DOCUMENTOS POR COBRAR COMERCIALES CORRIENTES | G25: RELACIONADAS | H25: (-) Deterioro acumulado del valor de cuentas y documentos por cobrar comerciales por incobrabilidad (provisiones para créditos incobrables) | I25: CUENTAS Y DOCUMENTOS POR COBRAR CORRIENTES_CUENTAS Y DOCUMENTOS POR COBRAR COMERCIALES CORRIENTES_RELACIONADAS_(-) Deterioro acumulado del valor de cuentas y documentos por cobrar comerciales por incobrabilidad (provisiones para créditos incobrables) | J25: Cuentas y Documentos por cobrar corrientes | K25: =SUMIF(BC!$E$6:$E$347,$A25,BC!$K$6:$K$347) -> 0 | L25: =SUMIF(#REF!,$A25,#REF!)+SUMIF(#REF!,$A25,#REF!) -> #REF! | M25: =SUMIF(#REF!,Casilleros!$A25,#REF!)+SUMIF(#REF!,Casilleros!$A25,#REF!)+SUMIF(#REF!,$A25,#REF!) -> #REF! | N25: =SUMIF(#REF!,$A25,#REF!) -> #REF! | O25: =SUMIF(#REF!,$A25,#REF!)+SUMIF(#REF!,$A25,#REF!) -> #REF! | P25: =IFERROR(VLOOKUP($A25,#REF!,2,FALSE),0) -> 0 | Q25: =SUM(K25:P25) -> #REF!
A26: 315 | B26: ESTADO DE SITUACIÓN FINANCIERA | C26: ACTIVO | D26: ACTIVOS CORRIENTES | E26: CUENTAS Y DOCUMENTOS POR COBRAR CORRIENTES | F26: CUENTAS Y DOCUMENTOS POR COBRAR COMERCIALES CORRIENTES | G26: NO RELACIONADAS | H26: Locales | I26: CUENTAS Y DOCUMENTOS POR COBRAR CORRIENTES_CUENTAS Y DOCUMENTOS POR COBRAR COMERCIALES CORRIENTES_NO RELACIONADAS_Locales | J26: Cuentas y Documentos por cobrar corrientes | K26: =SUMIF(BC!$E$6:$E$347,$A26,BC!$K$6:$K$347) -> #REF! | L26: =SUMIF(#REF!,$A26,#REF!)+SUMIF(#REF!,$A26,#REF!) -> #REF! | M26: =SUMIF(#REF!,Casilleros!$A26,#REF!)+SUMIF(#REF!,Casilleros!$A26,#REF!)+SUMIF(#REF!,$A26,#REF!) -> #REF! | N26: =SUMIF(#REF!,$A26,#REF!) -> #REF! | O26: =SUMIF(#REF!,$A26,#REF!)+SUMIF(#REF!,$A26,#REF!) -> #REF! | P26: =IFERROR(VLOOKUP($A26,#REF!,2,FALSE),0) -> 0 | Q26: =SUM(K26:P26) -> #REF!
A27: 316 | B27: ESTADO DE SITUACIÓN FINANCIERA | C27: ACTIVO | D27: ACTIVOS CORRIENTES | E27: CUENTAS Y DOCUMENTOS POR COBRAR CORRIENTES | F27: CUENTAS Y DOCUMENTOS POR COBRAR COMERCIALES CORRIENTES | G27: NO RELACIONADAS | H27: Del exterior | I27: CUENTAS Y DOCUMENTOS POR COBRAR CORRIENTES_CUENTAS Y DOCUMENTOS POR COBRAR COMERCIALES CORRIENTES_NO RELACIONADAS_Del exterior | J27: Cuentas y Documentos por cobrar corrientes | K27: =SUMIF(BC!$E$6:$E$347,$A27,BC!$K$6:$K$347) -> 0 | L27: =SUMIF(#REF!,$A27,#REF!)+SUMIF(#REF!,$A27,#REF!) -> #REF! | M27: =SUMIF(#REF!,Casilleros!$A27,#REF!)+SUMIF(#REF!,Casilleros!$A27,#REF!)+SUMIF(#REF!,$A27,#REF!) -> #REF! | N27: =SUMIF(#REF!,$A27,#REF!) -> #REF! | O27: =SUMIF(#REF!,$A27,#REF!)+SUMIF(#REF!,$A27,#REF!) -> #REF! | P27: =IFERROR(VLOOKUP($A27,#REF!,2,FALSE),0) -> 0 | Q27: =SUM(K27:P27) -> #REF!
A28: 317 | B28: ESTADO DE SITUACIÓN FINANCIERA | C28: ACTIVO | D28: ACTIVOS CORRIENTES | E28: CUENTAS Y DOCUMENTOS POR COBRAR CORRIENTES | F28: CUENTAS Y DOCUMENTOS POR COBRAR COMERCIALES CORRIENTES | G28: NO RELACIONADAS | H28: (-) Deterioro acumulado del valor de cuentas y documentos por cobrar comerciales por incobrabilidad (provisiones para créditos incobrables) | I28: CUENTAS Y DOCUMENTOS POR COBRAR CORRIENTES_CUENTAS Y DOCUMENTOS POR COBRAR COMERCIALES CORRIENTES_NO RELACIONADAS_(-) Deterioro acumulado del valor de cuentas y documentos por cobrar comerciales por incobrabilidad (provisiones para créditos incobrables) | J28: Cuentas y Documentos por cobrar corrientes | K28: =SUMIF(BC!$E$6:$E$347,$A28,BC!$K$6:$K$347) -> #REF! | L28: =SUMIF(#REF!,$A28,#REF!)+SUMIF(#REF!,$A28,#REF!) -> #REF! | M28: =SUMIF(#REF!,Casilleros!$A28,#REF!)+SUMIF(#REF!,Casilleros!$A28,#REF!)+SUMIF(#REF!,$A28,#REF!) -> #REF! | N28: =SUMIF(#REF!,$A28,#REF!) -> #REF! | O28: =SUMIF(#REF!,$A28,#REF!)+SUMIF(#REF!,$A28,#REF!) -> #REF! | P28: =IFERROR(VLOOKUP($A28,#REF!,2,FALSE),0) -> 0 | Q28: =SUM(K28:P28) -> #REF!
A29: 318 | B29: ESTADO DE SITUACIÓN FINANCIERA | C29: ACTIVO | D29: ACTIVOS CORRIENTES | E29: CUENTAS Y DOCUMENTOS POR COBRAR CORRIENTES | F29: OTRAS CUENTAS Y DOCUMENTOS POR COBRAR CORRIENTES | G29: A ACCIONISTAS, SOCIOS, PARTICIPES, BENEFICIARIOS U OTROS TITULARES DE DERECHOS REPRESENTATIVOS DE CAPITAL | H29: Locales | I29: CUENTAS Y DOCUMENTOS POR COBRAR CORRIENTES_OTRAS CUENTAS Y DOCUMENTOS POR COBRAR CORRIENTES_A ACCIONISTAS, SOCIOS, PARTICIPES, BENEFICIARIOS U OTROS TITULARES DE DERECHOS REPRESENTATIVOS DE CAPITAL_Locales | J29: Cuentas y Documentos por cobrar corrientes | K29: =SUMIF(BC!$E$6:$E$347,$A29,BC!$K$6:$K$347) -> 0 | L29: =SUMIF(#REF!,$A29,#REF!)+SUMIF(#REF!,$A29,#REF!) -> #REF! | M29: =SUMIF(#REF!,Casilleros!$A29,#REF!)+SUMIF(#REF!,Casilleros!$A29,#REF!)+SUMIF(#REF!,$A29,#REF!) -> #REF! | N29: =SUMIF(#REF!,$A29,#REF!) -> #REF! | O29: =SUMIF(#REF!,$A29,#REF!)+SUMIF(#REF!,$A29,#REF!) -> #REF! | P29: =IFERROR(VLOOKUP($A29,#REF!,2,FALSE),0) -> 0 | Q29: =SUM(K29:P29) -> #REF!
A30: 319 | B30: ESTADO DE SITUACIÓN FINANCIERA | C30: ACTIVO | D30: ACTIVOS CORRIENTES | E30: CUENTAS Y DOCUMENTOS POR COBRAR CORRIENTES | F30: OTRAS CUENTAS Y DOCUMENTOS POR COBRAR CORRIENTES | G30: A ACCIONISTAS, SOCIOS, PARTICIPES, BENEFICIARIOS U OTROS TITULARES DE DERECHOS REPRESENTATIVOS DE CAPITAL | H30: Del exterior | I30: CUENTAS Y DOCUMENTOS POR COBRAR CORRIENTES_OTRAS CUENTAS Y DOCUMENTOS POR COBRAR CORRIENTES_A ACCIONISTAS, SOCIOS, PARTICIPES, BENEFICIARIOS U OTROS TITULARES DE DERECHOS REPRESENTATIVOS DE CAPITAL_Del exterior | J30: Cuentas y Documentos por cobrar corrientes | K30: =SUMIF(BC!$E$6:$E$347,$A30,BC!$K$6:$K$347) -> 0 | L30: =SUMIF(#REF!,$A30,#REF!)+SUMIF(#REF!,$A30,#REF!) -> #REF! | M30: =SUMIF(#REF!,Casilleros!$A30,#REF!)+SUMIF(#REF!,Casilleros!$A30,#REF!)+SUMIF(#REF!,$A30,#REF!) -> #REF! | N30: =SUMIF(#REF!,$A30,#REF!) -> #REF! | O30: =SUMIF(#REF!,$A30,#REF!)+SUMIF(#REF!,$A30,#REF!) -> #REF! | P30: =IFERROR(VLOOKUP($A30,#REF!,2,FALSE),0) -> 0 | Q30: =SUM(K30:P30) -> #REF!
A31: 320 | B31: ESTADO DE SITUACIÓN FINANCIERA | C31: ACTIVO | D31: ACTIVOS CORRIENTES | E31: CUENTAS Y DOCUMENTOS POR COBRAR CORRIENTES | F31: OTRAS CUENTAS Y DOCUMENTOS POR COBRAR CORRIENTES | G31: DIVIDENDOS POR COBRAR | H31: En efectivo | I31: CUENTAS Y DOCUMENTOS POR COBRAR CORRIENTES_OTRAS CUENTAS Y DOCUMENTOS POR COBRAR CORRIENTES_DIVIDENDOS POR COBRAR_En efectivo | J31: Cuentas y Documentos por cobrar corrientes | K31: =SUMIF(BC!$E$6:$E$347,$A31,BC!$K$6:$K$347) -> 0 | L31: =SUMIF(#REF!,$A31,#REF!)+SUMIF(#REF!,$A31,#REF!) -> #REF! | M31: =SUMIF(#REF!,Casilleros!$A31,#REF!)+SUMIF(#REF!,Casilleros!$A31,#REF!)+SUMIF(#REF!,$A31,#REF!) -> #REF! | N31: =SUMIF(#REF!,$A31,#REF!) -> #REF! | O31: =SUMIF(#REF!,$A31,#REF!)+SUMIF(#REF!,$A31,#REF!) -> #REF! | P31: =IFERROR(VLOOKUP($A31,#REF!,2,FALSE),0) -> 0 | Q31: =SUM(K31:P31) -> #REF!
A32: 321 | B32: ESTADO DE SITUACIÓN FINANCIERA | C32: ACTIVO | D32: ACTIVOS CORRIENTES | E32: CUENTAS Y DOCUMENTOS POR COBRAR CORRIENTES | F32: OTRAS CUENTAS Y DOCUMENTOS POR COBRAR CORRIENTES | G32: DIVIDENDOS POR COBRAR | H32: En activos diferentes del efectivo | I32: CUENTAS Y DOCUMENTOS POR COBRAR CORRIENTES_OTRAS CUENTAS Y DOCUMENTOS POR COBRAR CORRIENTES_DIVIDENDOS POR COBRAR_En activos diferentes del efectivo | J32: Cuentas y Documentos por cobrar corrientes | K32: =SUMIF(BC!$E$6:$E$347,$A32,BC!$K$6:$K$347) -> 0 | L32: =SUMIF(#REF!,$A32,#REF!)+SUMIF(#REF!,$A32,#REF!) -> #REF! | M32: =SUMIF(#REF!,Casilleros!$A32,#REF!)+SUMIF(#REF!,Casilleros!$A32,#REF!)+SUMIF(#REF!,$A32,#REF!) -> #REF! | N32: =SUMIF(#REF!,$A32,#REF!) -> #REF! | O32: =SUMIF(#REF!,$A32,#REF!)+SUMIF(#REF!,$A32,#REF!) -> #REF! | P32: =IFERROR(VLOOKUP($A32,#REF!,2,FALSE),0) -> 0 | Q32: =SUM(K32:P32) -> #REF!
A33: 322 | B33: ESTADO DE SITUACIÓN FINANCIERA | C33: ACTIVO | D33: ACTIVOS CORRIENTES | E33: CUENTAS Y DOCUMENTOS POR COBRAR CORRIENTES | F33: OTRAS CUENTAS Y DOCUMENTOS POR COBRAR CORRIENTES | G33: OTRAS RELACIONADAS | H33: Locales | I33: CUENTAS Y DOCUMENTOS POR COBRAR CORRIENTES_OTRAS CUENTAS Y DOCUMENTOS POR COBRAR CORRIENTES_OTRAS RELACIONADAS_Locales | J33: Cuentas y Documentos por cobrar corrientes | K33: =SUMIF(BC!$E$6:$E$347,$A33,BC!$K$6:$K$347) -> 0 | L33: =SUMIF(#REF!,$A33,#REF!)+SUMIF(#REF!,$A33,#REF!) -> #REF! | M33: =SUMIF(#REF!,Casilleros!$A33,#REF!)+SUMIF(#REF!,Casilleros!$A33,#REF!)+SUMIF(#REF!,$A33,#REF!) -> #REF! | N33: =SUMIF(#REF!,$A33,#REF!) -> #REF! | O33: =SUMIF(#REF!,$A33,#REF!)+SUMIF(#REF!,$A33,#REF!) -> #REF! | P33: =IFERROR(VLOOKUP($A33,#REF!,2,FALSE),0) -> 0 | Q33: =SUM(K33:P33) -> #REF!
A34: 323 | B34: ESTADO DE SITUACIÓN FINANCIERA | C34: ACTIVO | D34: ACTIVOS CORRIENTES | E34: CUENTAS Y DOCUMENTOS POR COBRAR CORRIENTES | F34: OTRAS CUENTAS Y DOCUMENTOS POR COBRAR CORRIENTES | G34: OTRAS RELACIONADAS | H34: Del exterior | I34: CUENTAS Y DOCUMENTOS POR COBRAR CORRIENTES_OTRAS CUENTAS Y DOCUMENTOS POR COBRAR CORRIENTES_OTRAS RELACIONADAS_Del exterior | J34: Cuentas y Documentos por cobrar corrientes | K34: =SUMIF(BC!$E$6:$E$347,$A34,BC!$K$6:$K$347) -> 0 | L34: =SUMIF(#REF!,$A34,#REF!)+SUMIF(#REF!,$A34,#REF!) -> #REF! | M34: =SUMIF(#REF!,Casilleros!$A34,#REF!)+SUMIF(#REF!,Casilleros!$A34,#REF!)+SUMIF(#REF!,$A34,#REF!) -> #REF! | N34: =SUMIF(#REF!,$A34,#REF!) -> #REF! | O34: =SUMIF(#REF!,$A34,#REF!)+SUMIF(#REF!,$A34,#REF!) -> #REF! | P34: =IFERROR(VLOOKUP($A34,#REF!,2,FALSE),0) -> 0 | Q34: =SUM(K34:P34) -> #REF!
... A38: 327 | B38: ESTADO DE SITUACIÓN FINANCIERA | C38: ACTIVO | D38: ACTIVOS CORRIENTES | E38: CUENTAS Y DOCUMENTOS POR COBRAR CORRIENTES | F38: OTRAS CUENTAS Y DOCUMENTOS POR COBRAR CORRIENTES | G38: OTRAS NO RELACIONADAS | H38: (-) Deterioro acumulado del valor de otras cuentas y documentos por cobrar por incobrabilidad (provisiones para créditos incobrables) | I38: CUENTAS Y DOCUMENTOS POR COBRAR CORRIENTES_OTRAS CUENTAS Y DOCUMENTOS POR COBRAR CORRIENTES_OTRAS NO RELACIONADAS_(-) Deterioro acumulado del valor de otras cuentas y documentos por cobrar por incobrabilidad (provisiones para créditos incobrables) | J38: Cuentas y Documentos por cobrar corrientes | K38: =SUMIF(BC!$E$6:$E$347,$A38,BC!$K$6:$K$347) -> 0 | L38: =SUMIF(#REF!,$A38,#REF!)+SUMIF(#REF!,$A38,#REF!) -> #REF! | M38: =SUMIF(#REF!,Casilleros!$A38,#REF!)+SUMIF(#REF!,Casilleros!$A38,#REF!)+SUMIF(#REF!,$A38,#REF!) -> #REF! | N38: =SUMIF(#REF!,$A38,#REF!) -> #REF! | O38: =SUMIF(#REF!,$A38,#REF!)+SUMIF(#REF!,$A38,#REF!) -> #REF! | P38: =IFERROR(VLOOKUP($A38,#REF!,2,FALSE),0) -> 0 | Q38: =SUM(K38:P38) -> #REF!
A39: 328 | B39: ESTADO DE SITUACIÓN FINANCIERA | C39: ACTIVO | D39: ACTIVOS CORRIENTES | E39: OTROS ACTIVOS FINANCIEROS CORRIENTES | F39: A costo amortizado | I39: OTROS ACTIVOS FINANCIEROS CORRIENTES_A costo amortizado__ | J39: Otros activos financieros corrientes | K39: =SUMIF(BC!$E$6:$E$347,$A39,BC!$K$6:$K$347) -> 0 | L39: =SUMIF(#REF!,$A39,#REF!)+SUMIF(#REF!,$A39,#REF!) -> #REF! | M39: =SUMIF(#REF!,Casilleros!$A39,#REF!)+SUMIF(#REF!,Casilleros!$A39,#REF!)+SUMIF(#REF!,$A39,#REF!) -> #REF! | N39: =SUMIF(#REF!,$A39,#REF!) -> #REF! | O39: =SUMIF(#REF!,$A39,#REF!)+SUMIF(#REF!,$A39,#REF!) -> #REF! | P39: =IFERROR(VLOOKUP($A39,#REF!,2,FALSE),0) -> 0 | Q39: =SUM(K39:P39) -> #REF!
A40: 329 | B40: ESTADO DE SITUACIÓN FINANCIERA | C40: ACTIVO | D40: ACTIVOS CORRIENTES | E40: OTROS ACTIVOS FINANCIEROS CORRIENTES | F40: (-) Deterioro acumulado del valor de otros activos financieros corrientes medidos a costo amortizado (provisiones para créditos incobrables) | I40: OTROS ACTIVOS FINANCIEROS CORRIENTES_(-) Deterioro acumulado del valor de otros activos financieros corrientes medidos a costo amortizado (provisiones para créditos incobrables)__ | J40: Otros activos financieros corrientes | K40: =SUMIF(BC!$E$6:$E$347,$A40,BC!$K$6:$K$347) -> 0 | L40: =SUMIF(#REF!,$A40,#REF!)+SUMIF(#REF!,$A40,#REF!) -> #REF! | M40: =SUMIF(#REF!,Casilleros!$A40,#REF!)+SUMIF(#REF!,Casilleros!$A40,#REF!)+SUMIF(#REF!,$A40,#REF!) -> #REF! | N40: =SUMIF(#REF!,$A40,#REF!) -> #REF! | O40: =SUMIF(#REF!,$A40,#REF!)+SUMIF(#REF!,$A40,#REF!) -> #REF! | P40: =IFERROR(VLOOKUP($A40,#REF!,2,FALSE),0) -> 0 | Q40: =SUM(K40:P40) -> #REF!
A41: 330 | B41: ESTADO DE SITUACIÓN FINANCIERA | C41: ACTIVO | D41: ACTIVOS CORRIENTES | E41: OTROS ACTIVOS FINANCIEROS CORRIENTES | F41: A valor razonable | I41: OTROS ACTIVOS FINANCIEROS CORRIENTES_A valor razonable__ | J41: Otros activos financieros corrientes | K41: =SUMIF(BC!$E$6:$E$347,$A41,BC!$K$6:$K$347) -> 0 | L41: =SUMIF(#REF!,$A41,#REF!)+SUMIF(#REF!,$A41,#REF!) -> #REF! | M41: =SUMIF(#REF!,Casilleros!$A41,#REF!)+SUMIF(#REF!,Casilleros!$A41,#REF!)+SUMIF(#REF!,$A41,#REF!) -> #REF! | N41: =SUMIF(#REF!,$A41,#REF!) -> #REF! | O41: =SUMIF(#REF!,$A41,#REF!)+SUMIF(#REF!,$A41,#REF!) -> #REF! | P41: =IFERROR(VLOOKUP($A41,#REF!,2,FALSE),0) -> 0 | Q41: =SUM(K41:P41) -> #REF!
A42: 331 | B42: ESTADO DE SITUACIÓN FINANCIERA | C42: ACTIVO | D42: ACTIVOS CORRIENTES | E42: PORCIÓN CORRIENTE DE ARRENDAMIENTOS FINANCIEROS POR COBRAR | F42: Relacionadas | I42: PORCIÓN CORRIENTE DE ARRENDAMIENTOS FINANCIEROS POR COBRAR_Relacionadas__ | J42: Porción corriente de arrendamientos financieros por cobrar | K42: =SUMIF(BC!$E$6:$E$347,$A42,BC!$K$6:$K$347) -> 0 | L42: =SUMIF(#REF!,$A42,#REF!)+SUMIF(#REF!,$A42,#REF!) -> #REF! | M42: =SUMIF(#REF!,Casilleros!$A42,#REF!)+SUMIF(#REF!,Casilleros!$A42,#REF!)+SUMIF(#REF!,$A42,#REF!) -> #REF! | N42: =SUMIF(#REF!,$A42,#REF!) -> #REF! | O42: =SUMIF(#REF!,$A42,#REF!)+SUMIF(#REF!,$A42,#REF!) -> #REF! | P42: =IFERROR(VLOOKUP($A42,#REF!,2,FALSE),0) -> 0 | Q42: =SUM(K42:P42) -> #REF!
A43: 332 | B43: ESTADO DE SITUACIÓN FINANCIERA | C43: ACTIVO | D43: ACTIVOS CORRIENTES | E43: PORCIÓN CORRIENTE DE ARRENDAMIENTOS FINANCIEROS POR COBRAR | F43: No relacionadas | I43: PORCIÓN CORRIENTE DE ARRENDAMIENTOS FINANCIEROS POR COBRAR_No relacionadas__ | J43: Porción corriente de arrendamientos financieros por cobrar | K43: =SUMIF(BC!$E$6:$E$347,$A43,BC!$K$6:$K$347) -> 0 | L43: =SUMIF(#REF!,$A43,#REF!)+SUMIF(#REF!,$A43,#REF!) -> #REF! | M43: =SUMIF(#REF!,Casilleros!$A43,#REF!)+SUMIF(#REF!,Casilleros!$A43,#REF!)+SUMIF(#REF!,$A43,#REF!) -> #REF! | N43: =SUMIF(#REF!,$A43,#REF!) -> #REF! | O43: =SUMIF(#REF!,$A43,#REF!)+SUMIF(#REF!,$A43,#REF!) -> #REF! | P43: =IFERROR(VLOOKUP($A43,#REF!,2,FALSE),0) -> 0 | Q43: =SUM(K43:P43) -> #REF!
A44: 333 | B44: ESTADO DE SITUACIÓN FINANCIERA | C44: ACTIVO | D44: ACTIVOS CORRIENTES | E44: IMPORTE BRUTO ADEUDADO POR LOS CLIENTES POR EL TRABAJO EJECUTADO EN CONTRATOS DE CONSTRUCCIÓN | F44: Relacionadas | I44: IMPORTE BRUTO ADEUDADO POR LOS CLIENTES POR EL TRABAJO EJECUTADO EN CONTRATOS DE CONSTRUCCIÓN_Relacionadas__ | J44: Importe bruto adeudado por los clientes por el trabajo ejecutado en contratos de construcción | K44: =SUMIF(BC!$E$6:$E$347,$A44,BC!$K$6:$K$347) -> 0 | L44: =SUMIF(#REF!,$A44,#REF!)+SUMIF(#REF!,$A44,#REF!) -> #REF! | M44: =SUMIF(#REF!,Casilleros!$A44,#REF!)+SUMIF(#REF!,Casilleros!$A44,#REF!)+SUMIF(#REF!,$A44,#REF!) -> #REF! | N44: =SUMIF(#REF!,$A44,#REF!) -> #REF! | O44: =SUMIF(#REF!,$A44,#REF!)+SUMIF(#REF!,$A44,#REF!) -> #REF! | P44: =IFERROR(VLOOKUP($A44,#REF!,2,FALSE),0) -> 0 | Q44: =SUM(K44:P44) -> #REF!
A45: 334 | B45: ESTADO DE SITUACIÓN FINANCIERA | C45: ACTIVO | D45: ACTIVOS CORRIENTES | E45: IMPORTE BRUTO ADEUDADO POR LOS CLIENTES POR EL TRABAJO EJECUTADO EN CONTRATOS DE CONSTRUCCIÓN | F45: No relacionadas | I45: IMPORTE BRUTO ADEUDADO POR LOS CLIENTES POR EL TRABAJO EJECUTADO EN CONTRATOS DE CONSTRUCCIÓN_No relacionadas__ | J45: Importe bruto adeudado por los clientes por el trabajo ejecutado en contratos de construcción | K45: =SUMIF(BC!$E$6:$E$347,$A45,BC!$K$6:$K$347) -> 0 | L45: =SUMIF(#REF!,$A45,#REF!)+SUMIF(#REF!,$A45,#REF!) -> #REF! | M45: =SUMIF(#REF!,Casilleros!$A45,#REF!)+SUMIF(#REF!,Casilleros!$A45,#REF!)+SUMIF(#REF!,$A45,#REF!) -> #REF! | N45: =SUMIF(#REF!,$A45,#REF!) -> #REF! | O45: =SUMIF(#REF!,$A45,#REF!)+SUMIF(#REF!,$A45,#REF!) -> #REF! | P45: =IFERROR(VLOOKUP($A45,#REF!,2,FALSE),0) -> 0 | Q45: =SUM(K45:P45) -> #REF!
A46: 335 | B46: ESTADO DE SITUACIÓN FINANCIERA | C46: ACTIVO | D46: ACTIVOS CORRIENTES | E46: ACTIVOS POR IMPUESTOS CORRIENTES | F46: Crédito tributario a favor del sujeto pasivo (ISD) | I46: ACTIVOS POR IMPUESTOS CORRIENTES_Crédito tributario a favor del sujeto pasivo (ISD)__ | J46: Activos por impuestos corrientes | K46: =SUMIF(BC!$E$6:$E$347,$A46,BC!$K$6:$K$347) -> 0 | L46: =SUMIF(#REF!,$A46,#REF!)+SUMIF(#REF!,$A46,#REF!) -> #REF! | M46: =SUMIF(#REF!,Casilleros!$A46,#REF!)+SUMIF(#REF!,Casilleros!$A46,#REF!)+SUMIF(#REF!,$A46,#REF!) -> #REF! | N46: =SUMIF(#REF!,$A46,#REF!) -> #REF! | O46: =SUMIF(#REF!,$A46,#REF!)+SUMIF(#REF!,$A46,#REF!) -> #REF! | P46: =IFERROR(VLOOKUP($A46,#REF!,2,FALSE),0) -> 0 | Q46: =SUM(K46:P46) -> #REF!
A47: 336 | B47: ESTADO DE SITUACIÓN FINANCIERA | C47: ACTIVO | D47: ACTIVOS CORRIENTES | E47: ACTIVOS POR IMPUESTOS CORRIENTES | F47: Crédito tributario a favor del sujeto pasivo (IVA) | I47: ACTIVOS POR IMPUESTOS CORRIENTES_Crédito tributario a favor del sujeto pasivo (IVA)__ | J47: Activos por impuestos corrientes | K47: =SUMIF(BC!$E$6:$E$347,$A47,BC!$K$6:$K$347) -> 0 | L47: =SUMIF(#REF!,$A47,#REF!)+SUMIF(#REF!,$A47,#REF!) -> #REF! | M47: =SUMIF(#REF!,Casilleros!$A47,#REF!)+SUMIF(#REF!,Casilleros!$A47,#REF!)+SUMIF(#REF!,$A47,#REF!) -> #REF! | N47: =SUMIF(#REF!,$A47,#REF!) -> #REF! | O47: =SUMIF(#REF!,$A47,#REF!)+SUMIF(#REF!,$A47,#REF!) -> #REF! | P47: =IFERROR(VLOOKUP($A47,#REF!,2,FALSE),0) -> 0 | Q47: =SUM(K47:P47) -> #REF!
A48: 337 | B48: ESTADO DE SITUACIÓN FINANCIERA | C48: ACTIVO | D48: ACTIVOS CORRIENTES | E48: ACTIVOS POR IMPUESTOS CORRIENTES | F48: Crédito tributario a favor del sujeto pasivo (Impuesto a la Renta) | I48: ACTIVOS POR IMPUESTOS CORRIENTES_Crédito tributario a favor del sujeto pasivo (Impuesto a la Renta) __ | J48: Activos por impuestos corrientes | K48: =SUMIF(BC!$E$6:$E$347,$A48,BC!$K$6:$K$347) -> #REF! | L48: =SUMIF(#REF!,$A48,#REF!)+SUMIF(#REF!,$A48,#REF!) -> #REF! | M48: =SUMIF(#REF!,Casilleros!$A48,#REF!)+SUMIF(#REF!,Casilleros!$A48,#REF!)+SUMIF(#REF!,$A48,#REF!) -> #REF! | N48: =SUMIF(#REF!,$A48,#REF!) -> #REF! | O48: =SUMIF(#REF!,$A48,#REF!)+SUMIF(#REF!,$A48,#REF!) -> #REF! | P48: =IFERROR(VLOOKUP($A48,#REF!,2,FALSE),0) -> 0 | Q48: =SUM(K48:P48) -> #REF!
A49: 338 | B49: ESTADO DE SITUACIÓN FINANCIERA | C49: ACTIVO | D49: ACTIVOS CORRIENTES | E49: ACTIVOS POR IMPUESTOS CORRIENTES | F49: Otros | I49: ACTIVOS POR IMPUESTOS CORRIENTES_Otros__ | J49: Activos por impuestos corrientes | K49: =SUMIF(BC!$E$6:$E$347,$A49,BC!$K$6:$K$347) -> 0 | L49: =SUMIF(#REF!,$A49,#REF!)+SUMIF(#REF!,$A49,#REF!) -> #REF! | M49: =SUMIF(#REF!,Casilleros!$A49,#REF!)+SUMIF(#REF!,Casilleros!$A49,#REF!)+SUMIF(#REF!,$A49,#REF!) -> #REF! | N49: =SUMIF(#REF!,$A49,#REF!) -> #REF! | O49: =SUMIF(#REF!,$A49,#REF!)+SUMIF(#REF!,$A49,#REF!) -> #REF! | P49: =IFERROR(VLOOKUP($A49,#REF!,2,FALSE),0) -> 0 | Q49: =SUM(K49:P49) -> #REF!
A50: 339 | B50: ESTADO DE SITUACIÓN FINANCIERA | C50: ACTIVO | D50: ACTIVOS CORRIENTES | E50: INVENTARIOS | F50: Mercaderías en tránsito | I50: INVENTARIOS_Mercaderías en tránsito__ | J50: Inventarios | K50: =SUMIF(BC!$E$6:$E$347,$A50,BC!$K$6:$K$347) -> 0 | L50: =SUMIF(#REF!,$A50,#REF!)+SUMIF(#REF!,$A50,#REF!) -> #REF! | M50: =SUMIF(#REF!,Casilleros!$A50,#REF!)+SUMIF(#REF!,Casilleros!$A50,#REF!)+SUMIF(#REF!,$A50,#REF!) -> #REF! | N50: =SUMIF(#REF!,$A50,#REF!) -> #REF! | O50: =SUMIF(#REF!,$A50,#REF!)+SUMIF(#REF!,$A50,#REF!) -> #REF! | P50: =IFERROR(VLOOKUP($A50,#REF!,2,FALSE),0) -> 0 | Q50: =SUM(K50:P50) -> #REF!
... A60: 349 | B60: ESTADO DE SITUACIÓN FINANCIERA | C60: ACTIVO | D60: ACTIVOS CORRIENTES | E60: ACTIVOS NO CORRIENTES MANTENIDOS PARA LA VENTA | F60: (-) Deterioro acumulado del valor de activos no corrientes mantenidos para la venta | I60: ACTIVOS NO CORRIENTES MANTENIDOS PARA LA VENTA_(-) Deterioro acumulado del valor de activos no corrientes mantenidos para la venta__ | J60: Activos no corrientes mantenidos para la venta | K60: =SUMIF(BC!$E$6:$E$347,$A60,BC!$K$6:$K$347) -> 0 | L60: =SUMIF(#REF!,$A60,#REF!)+SUMIF(#REF!,$A60,#REF!) -> #REF! | M60: =SUMIF(#REF!,Casilleros!$A60,#REF!)+SUMIF(#REF!,Casilleros!$A60,#REF!)+SUMIF(#REF!,$A60,#REF!) -> #REF! | N60: =SUMIF(#REF!,$A60,#REF!) -> #REF! | O60: =SUMIF(#REF!,$A60,#REF!)+SUMIF(#REF!,$A60,#REF!) -> #REF! | P60: =IFERROR(VLOOKUP($A60,#REF!,2,FALSE),0) -> 0 | Q60: =SUM(K60:P60) -> #REF!
A61: 350 | B61: ESTADO DE SITUACIÓN FINANCIERA | C61: ACTIVO | D61: ACTIVOS CORRIENTES | E61: ACTIVOS BIOLÓGICOS | F61: PLANTAS VIVAS Y FRUTOS EN CRECIMIENTO | G61: A costo | I61: ACTIVOS BIOLÓGICOS_PLANTAS VIVAS Y FRUTOS EN CRECIMIENTO_A costo_ | J61: Activos biológicos | K61: =SUMIF(BC!$E$6:$E$347,$A61,BC!$K$6:$K$347) -> 0 | L61: =SUMIF(#REF!,$A61,#REF!)+SUMIF(#REF!,$A61,#REF!) -> #REF! | M61: =SUMIF(#REF!,Casilleros!$A61,#REF!)+SUMIF(#REF!,Casilleros!$A61,#REF!)+SUMIF(#REF!,$A61,#REF!) -> #REF! | N61: =SUMIF(#REF!,$A61,#REF!) -> #REF! | O61: =SUMIF(#REF!,$A61,#REF!)+SUMIF(#REF!,$A61,#REF!) -> #REF! | P61: =IFERROR(VLOOKUP($A61,#REF!,2,FALSE),0) -> 0 | Q61: =SUM(K61:P61) -> #REF!
A62: 351 | B62: ESTADO DE SITUACIÓN FINANCIERA | C62: ACTIVO | D62: ACTIVOS CORRIENTES | E62: ACTIVOS BIOLÓGICOS | F62: PLANTAS VIVAS Y FRUTOS EN CRECIMIENTO | G62: (-) Deterioro acumulado del valor de activos biológicos medidos a costo | I62: ACTIVOS BIOLÓGICOS_PLANTAS VIVAS Y FRUTOS EN CRECIMIENTO_(-) Deterioro acumulado del valor de activos biológicos medidos a costo_ | J62: Activos biológicos | K62: =SUMIF(BC!$E$6:$E$347,$A62,BC!$K$6:$K$347) -> 0 | L62: =SUMIF(#REF!,$A62,#REF!)+SUMIF(#REF!,$A62,#REF!) -> #REF! | M62: =SUMIF(#REF!,Casilleros!$A62,#REF!)+SUMIF(#REF!,Casilleros!$A62,#REF!)+SUMIF(#REF!,$A62,#REF!) -> #REF! | N62: =SUMIF(#REF!,$A62,#REF!) -> #REF! | O62: =SUMIF(#REF!,$A62,#REF!)+SUMIF(#REF!,$A62,#REF!) -> #REF! | P62: =IFERROR(VLOOKUP($A62,#REF!,2,FALSE),0) -> 0 | Q62: =SUM(K62:P62) -> #REF!
A63: 352 | B63: ESTADO DE SITUACIÓN FINANCIERA | C63: ACTIVO | D63: ACTIVOS CORRIENTES | E63: ACTIVOS BIOLÓGICOS | F63: PLANTAS VIVAS Y FRUTOS EN CRECIMIENTO | G63: A valor razonable menos los costos de venta | I63: ACTIVOS BIOLÓGICOS_PLANTAS VIVAS Y FRUTOS EN CRECIMIENTO_A valor razonable menos los costos de venta_ | J63: Activos biológicos | K63: =SUMIF(BC!$E$6:$E$347,$A63,BC!$K$6:$K$347) -> 0 | L63: =SUMIF(#REF!,$A63,#REF!)+SUMIF(#REF!,$A63,#REF!) -> #REF! | M63: =SUMIF(#REF!,Casilleros!$A63,#REF!)+SUMIF(#REF!,Casilleros!$A63,#REF!)+SUMIF(#REF!,$A63,#REF!) -> #REF! | N63: =SUMIF(#REF!,$A63,#REF!) -> #REF! | O63: =SUMIF(#REF!,$A63,#REF!)+SUMIF(#REF!,$A63,#REF!) -> #REF! | P63: =IFERROR(VLOOKUP($A63,#REF!,2,FALSE),0) -> 0 | Q63: =SUM(K63:P63) -> #REF!
A64: 353 | B64: ESTADO DE SITUACIÓN FINANCIERA | C64: ACTIVO | D64: ACTIVOS CORRIENTES | E64: ACTIVOS BIOLÓGICOS | F64: ANIMALES VIVOS | G64: A costo | I64: ACTIVOS BIOLÓGICOS_ANIMALES VIVOS_A costo_ | J64: Activos biológicos | K64: =SUMIF(BC!$E$6:$E$347,$A64,BC!$K$6:$K$347) -> 0 | L64: =SUMIF(#REF!,$A64,#REF!)+SUMIF(#REF!,$A64,#REF!) -> #REF! | M64: =SUMIF(#REF!,Casilleros!$A64,#REF!)+SUMIF(#REF!,Casilleros!$A64,#REF!)+SUMIF(#REF!,$A64,#REF!) -> #REF! | N64: =SUMIF(#REF!,$A64,#REF!) -> #REF! | O64: =SUMIF(#REF!,$A64,#REF!)+SUMIF(#REF!,$A64,#REF!) -> #REF! | P64: =IFERROR(VLOOKUP($A64,#REF!,2,FALSE),0) -> 0 | Q64: =SUM(K64:P64) -> #REF!
A65: 354 | B65: ESTADO DE SITUACIÓN FINANCIERA | C65: ACTIVO | D65: ACTIVOS CORRIENTES | E65: ACTIVOS BIOLÓGICOS | F65: ANIMALES VIVOS | G65: (-) Deterioro acumulado del valor de activos biológicos medidos a costo | I65: ACTIVOS BIOLÓGICOS_ANIMALES VIVOS_(-) Deterioro acumulado del valor de activos biológicos medidos a costo_ | J65: Activos biológicos | K65: =SUMIF(BC!$E$6:$E$347,$A65,BC!$K$6:$K$347) -> 0 | L65: =SUMIF(#REF!,$A65,#REF!)+SUMIF(#REF!,$A65,#REF!) -> #REF! | M65: =SUMIF(#REF!,Casilleros!$A65,#REF!)+SUMIF(#REF!,Casilleros!$A65,#REF!)+SUMIF(#REF!,$A65,#REF!) -> #REF! | N65: =SUMIF(#REF!,$A65,#REF!) -> #REF! | O65: =SUMIF(#REF!,$A65,#REF!)+SUMIF(#REF!,$A65,#REF!) -> #REF! | P65: =IFERROR(VLOOKUP($A65,#REF!,2,FALSE),0) -> 0 | Q65: =SUM(K65:P65) -> #REF!
A66: 355 | B66: ESTADO DE SITUACIÓN FINANCIERA | C66: ACTIVO | D66: ACTIVOS CORRIENTES | E66: ACTIVOS BIOLÓGICOS | F66: ANIMALES VIVOS | G66: A valor razonable menos los costos de venta | I66: ACTIVOS BIOLÓGICOS_ANIMALES VIVOS_A valor razonable menos los costos de venta_ | J66: Activos biológicos | K66: =SUMIF(BC!$E$6:$E$347,$A66,BC!$K$6:$K$347) -> 0 | L66: =SUMIF(#REF!,$A66,#REF!)+SUMIF(#REF!,$A66,#REF!) -> #REF! | M66: =SUMIF(#REF!,Casilleros!$A66,#REF!)+SUMIF(#REF!,Casilleros!$A66,#REF!)+SUMIF(#REF!,$A66,#REF!) -> #REF! | N66: =SUMIF(#REF!,$A66,#REF!) -> #REF! | O66: =SUMIF(#REF!,$A66,#REF!)+SUMIF(#REF!,$A66,#REF!) -> #REF! | P66: =IFERROR(VLOOKUP($A66,#REF!,2,FALSE),0) -> 0 | Q66: =SUM(K66:P66) -> #REF!
A67: 356 | B67: ESTADO DE SITUACIÓN FINANCIERA | C67: ACTIVO | D67: ACTIVOS CORRIENTES | E67: GASTOS PAGADOS POR ANTICIPADO (PREPAGADOS) | F67: Propaganda y publicidad prepagada | I67: GASTOS PAGADOS POR ANTICIPADO (PREPAGADOS)_Propaganda y publicidad prepagada__ | J67: Gastos pagados por anticipado (prepagados) | K67: =SUMIF(BC!$E$6:$E$347,$A67,BC!$K$6:$K$347) -> 0 | L67: =SUMIF(#REF!,$A67,#REF!)+SUMIF(#REF!,$A67,#REF!) -> #REF! | M67: =SUMIF(#REF!,Casilleros!$A67,#REF!)+SUMIF(#REF!,Casilleros!$A67,#REF!)+SUMIF(#REF!,$A67,#REF!) -> #REF! | N67: =SUMIF(#REF!,$A67,#REF!) -> #REF! | O67: =SUMIF(#REF!,$A67,#REF!)+SUMIF(#REF!,$A67,#REF!) -> #REF! | P67: =IFERROR(VLOOKUP($A67,#REF!,2,FALSE),0) -> 0 | Q67: =SUM(K67:P67) -> #REF!
A68: 357 | B68: ESTADO DE SITUACIÓN FINANCIERA | C68: ACTIVO | D68: ACTIVOS CORRIENTES | E68: GASTOS PAGADOS POR ANTICIPADO (PREPAGADOS) | F68: Arrendamientos operativos pagados por anticipado | I68: GASTOS PAGADOS POR ANTICIPADO (PREPAGADOS)_Arrendamientos operativos pagados por anticipado__ | J68: Gastos pagados por anticipado (prepagados) | K68: =SUMIF(BC!$E$6:$E$347,$A68,BC!$K$6:$K$347) -> 0 | L68: =SUMIF(#REF!,$A68,#REF!)+SUMIF(#REF!,$A68,#REF!) -> #REF! | M68: =SUMIF(#REF!,Casilleros!$A68,#REF!)+SUMIF(#REF!,Casilleros!$A68,#REF!)+SUMIF(#REF!,$A68,#REF!) -> #REF! | N68: =SUMIF(#REF!,$A68,#REF!) -> #REF! | O68: =SUMIF(#REF!,$A68,#REF!)+SUMIF(#REF!,$A68,#REF!) -> #REF! | P68: =IFERROR(VLOOKUP($A68,#REF!,2,FALSE),0) -> 0 | Q68: =SUM(K68:P68) -> #REF!
A69: 358 | B69: ESTADO DE SITUACIÓN FINANCIERA | C69: ACTIVO | D69: ACTIVOS CORRIENTES | E69: GASTOS PAGADOS POR ANTICIPADO (PREPAGADOS) | F69: Primas de seguro pagadas por anticipado | I69: GASTOS PAGADOS POR ANTICIPADO (PREPAGADOS)_Primas de seguro pagadas por anticipado__ | J69: Gastos pagados por anticipado (prepagados) | K69: =SUMIF(BC!$E$6:$E$347,$A69,BC!$K$6:$K$347) -> 0 | L69: =SUMIF(#REF!,$A69,#REF!)+SUMIF(#REF!,$A69,#REF!) -> #REF! | M69: =SUMIF(#REF!,Casilleros!$A69,#REF!)+SUMIF(#REF!,Casilleros!$A69,#REF!)+SUMIF(#REF!,$A69,#REF!) -> #REF! | N69: =SUMIF(#REF!,$A69,#REF!) -> #REF! | O69: =SUMIF(#REF!,$A69,#REF!)+SUMIF(#REF!,$A69,#REF!) -> #REF! | P69: =IFERROR(VLOOKUP($A69,#REF!,2,FALSE),0) -> 0 | Q69: =SUM(K69:P69) -> #REF!
A70: 359 | B70: ESTADO DE SITUACIÓN FINANCIERA | C70: ACTIVO | D70: ACTIVOS CORRIENTES | E70: GASTOS PAGADOS POR ANTICIPADO (PREPAGADOS) | F70: Otros | I70: GASTOS PAGADOS POR ANTICIPADO (PREPAGADOS)_Otros__ | J70: Gastos pagados por anticipado (prepagados) | K70: =SUMIF(BC!$E$6:$E$347,$A70,BC!$K$6:$K$347) -> 0 | L70: =SUMIF(#REF!,$A70,#REF!)+SUMIF(#REF!,$A70,#REF!) -> #REF! | M70: =SUMIF(#REF!,Casilleros!$A70,#REF!)+SUMIF(#REF!,Casilleros!$A70,#REF!)+SUMIF(#REF!,$A70,#REF!) -> #REF! | N70: =SUMIF(#REF!,$A70,#REF!) -> #REF! | O70: =SUMIF(#REF!,$A70,#REF!)+SUMIF(#REF!,$A70,#REF!) -> #REF! | P70: =IFERROR(VLOOKUP($A70,#REF!,2,FALSE),0) -> 0 | Q70: =SUM(K70:P70) -> #REF!
A71: 360 | B71: ESTADO DE SITUACIÓN FINANCIERA | C71: ACTIVO | D71: ACTIVOS CORRIENTES | E71: Otros Activos Corrientes | I71: Otros Activos Corrientes | J71: Otros activos corrientes | K71: =SUMIF(BC!$E$6:$E$347,$A71,BC!$K$6:$K$347) -> #REF! | L71: =SUMIF(#REF!,$A71,#REF!)+SUMIF(#REF!,$A71,#REF!) -> #REF! | M71: =SUMIF(#REF!,Casilleros!$A71,#REF!)+SUMIF(#REF!,Casilleros!$A71,#REF!)+SUMIF(#REF!,$A71,#REF!) -> #REF! | N71: =SUMIF(#REF!,$A71,#REF!) -> #REF! | O71: =SUMIF(#REF!,$A71,#REF!)+SUMIF(#REF!,$A71,#REF!) -> #REF! | P71: =IFERROR(VLOOKUP($A71,#REF!,2,FALSE),0) -> 0 | Q71: =SUM(K71:P71) -> #REF!
A72: 361 | B72: ESTADO DE SITUACIÓN FINANCIERA | C72: ACTIVO | D72: TOTAL ACTIVOS CORRIENTES | I72: ACTIVO_TOTAL ACTIVOS CORRIENTES_ | K72: =SUMIF(BC!$E$6:$E$347,$A72,BC!$K$6:$K$347) -> 0 | L72: =SUMIF(#REF!,$A72,#REF!)+SUMIF(#REF!,$A72,#REF!) -> #REF! | M72: =SUMIF(#REF!,Casilleros!$A72,#REF!)+SUMIF(#REF!,Casilleros!$A72,#REF!)+SUMIF(#REF!,$A72,#REF!) -> #REF! | N72: =SUMIF(#REF!,$A72,#REF!) -> #REF! | O72: =SUMIF(#REF!,$A72,#REF!)+SUMIF(#REF!,$A72,#REF!) -> #REF! | P72: =IFERROR(VLOOKUP($A72,#REF!,2,FALSE),0) -> 0 | Q72: =SUM(K72:P72) -> #REF!
A73: 362 | B73: ESTADO DE SITUACIÓN FINANCIERA | C73: ACTIVO | D73: ACTIVOS NO CORRIENTES | E73: PROPIEDADES, PLANTA Y EQUIPO | F73: TERRENOS | G73: Costo histórico antes de reexpresiones o revaluaciones | I73: PROPIEDADES, PLANTA Y EQUIPO_TERRENOS_Costo histórico antes de reexpresiones o revaluaciones_ | J73: Propiedades, planta y equipo | K73: =SUMIF(BC!$E$6:$E$347,$A73,BC!$K$6:$K$347) -> #REF! | L73: =SUMIF(#REF!,$A73,#REF!)+SUMIF(#REF!,$A73,#REF!) -> #REF! | M73: =SUMIF(#REF!,Casilleros!$A73,#REF!)+SUMIF(#REF!,Casilleros!$A73,#REF!)+SUMIF(#REF!,$A73,#REF!) -> #REF! | N73: =SUMIF(#REF!,$A73,#REF!) -> #REF! | O73: =SUMIF(#REF!,$A73,#REF!)+SUMIF(#REF!,$A73,#REF!) -> #REF! | P73: =IFERROR(VLOOKUP($A73,#REF!,2,FALSE),0) -> 0 | Q73: =SUM(K73:P73) -> #REF!
A74: 363 | B74: ESTADO DE SITUACIÓN FINANCIERA | C74: ACTIVO | D74: ACTIVOS NO CORRIENTES | E74: PROPIEDADES, PLANTA Y EQUIPO | F74: TERRENOS | G74: Ajuste acumulado por reexpresiones o revaluaciones | I74: PROPIEDADES, PLANTA Y EQUIPO_TERRENOS_Ajuste acumulado por reexpresiones o revaluaciones_ | J74: Propiedades, planta y equipo | K74: =SUMIF(BC!$E$6:$E$347,$A74,BC!$K$6:$K$347) -> #REF! | L74: =SUMIF(#REF!,$A74,#REF!)+SUMIF(#REF!,$A74,#REF!) -> #REF! | M74: =SUMIF(#REF!,Casilleros!$A74,#REF!)+SUMIF(#REF!,Casilleros!$A74,#REF!)+SUMIF(#REF!,$A74,#REF!) -> #REF! | N74: =SUMIF(#REF!,$A74,#REF!) -> #REF! | O74: =SUMIF(#REF!,$A74,#REF!)+SUMIF(#REF!,$A74,#REF!) -> #REF! | P74: =IFERROR(VLOOKUP($A74,#REF!,2,FALSE),0) -> 0 | Q74: =SUM(K74:P74) -> #REF!
A75: 364 | B75: ESTADO DE SITUACIÓN FINANCIERA | C75: ACTIVO | D75: ACTIVOS NO CORRIENTES | E75: PROPIEDADES, PLANTA Y EQUIPO | F75: EDIFICIOS Y OTROS INMUEBLES (EXCEPTO TERRENOS) | G75: Costo histórico antes de reexpresiones o revaluaciones | I75: PROPIEDADES, PLANTA Y EQUIPO_EDIFICIOS Y OTROS INMUEBLES (EXCEPTO TERRENOS)_Costo histórico antes de reexpresiones o revaluaciones _ | J75: Propiedades, planta y equipo | K75: =SUMIF(BC!$E$6:$E$347,$A75,BC!$K$6:$K$347) -> #REF! | L75: =SUMIF(#REF!,$A75,#REF!)+SUMIF(#REF!,$A75,#REF!) -> #REF! | M75: =SUMIF(#REF!,Casilleros!$A75,#REF!)+SUMIF(#REF!,Casilleros!$A75,#REF!)+SUMIF(#REF!,$A75,#REF!) -> #REF! | N75: =SUMIF(#REF!,$A75,#REF!) -> #REF! | O75: =SUMIF(#REF!,$A75,#REF!)+SUMIF(#REF!,$A75,#REF!) -> #REF! | P75: =IFERROR(VLOOKUP($A75,#REF!,2,FALSE),0) -> 0 | Q75: =SUM(K75:P75) -> #REF!
A76: 365 | B76: ESTADO DE SITUACIÓN FINANCIERA | C76: ACTIVO | D76: ACTIVOS NO CORRIENTES | E76: PROPIEDADES, PLANTA Y EQUIPO | F76: EDIFICIOS Y OTROS INMUEBLES (EXCEPTO TERRENOS) | G76: Ajuste acumulado por reexpresiones o revaluaciones | I76: PROPIEDADES, PLANTA Y EQUIPO_EDIFICIOS Y OTROS INMUEBLES (EXCEPTO TERRENOS)_Ajuste acumulado por reexpresiones o revaluaciones_ | J76: Propiedades, planta y equipo | K76: =SUMIF(BC!$E$6:$E$347,$A76,BC!$K$6:$K$347) -> #REF! | L76: =SUMIF(#REF!,$A76,#REF!)+SUMIF(#REF!,$A76,#REF!) -> #REF! | M76: =SUMIF(#REF!,Casilleros!$A76,#REF!)+SUMIF(#REF!,Casilleros!$A76,#REF!)+SUMIF(#REF!,$A76,#REF!) -> #REF! | N76: =SUMIF(#REF!,$A76,#REF!) -> #REF! | O76: =SUMIF(#REF!,$A76,#REF!)+SUMIF(#REF!,$A76,#REF!) -> #REF! | P76: =IFERROR(VLOOKUP($A76,#REF!,2,FALSE),0) -> 0 | Q76: =SUM(K76:P76) -> #REF!
A77: 366 | B77: ESTADO DE SITUACIÓN FINANCIERA | C77: ACTIVO | D77: ACTIVOS NO CORRIENTES | E77: PROPIEDADES, PLANTA Y EQUIPO | F77: NAVES, AERONAVES, BARCAZAS Y SIMILARES | G77: Costo histórico antes de reexpresiones o revaluaciones | I77: PROPIEDADES, PLANTA Y EQUIPO_NAVES, AERONAVES, BARCAZAS Y SIMILARES_Costo histórico antes de reexpresiones o revaluaciones_ | J77: Propiedades, planta y equipo | K77: =SUMIF(BC!$E$6:$E$347,$A77,BC!$K$6:$K$347) -> 0 | L77: =SUMIF(#REF!,$A77,#REF!)+SUMIF(#REF!,$A77,#REF!) -> #REF! | M77: =SUMIF(#REF!,Casilleros!$A77,#REF!)+SUMIF(#REF!,Casilleros!$A77,#REF!)+SUMIF(#REF!,$A77,#REF!) -> #REF! | N77: =SUMIF(#REF!,$A77,#REF!) -> #REF! | O77: =SUMIF(#REF!,$A77,#REF!)+SUMIF(#REF!,$A77,#REF!) -> #REF! | P77: =IFERROR(VLOOKUP($A77,#REF!,2,FALSE),0) -> 0 | Q77: =SUM(K77:P77) -> #REF!
A78: 367 | B78: ESTADO DE SITUACIÓN FINANCIERA | C78: ACTIVO | D78: ACTIVOS NO CORRIENTES | E78: PROPIEDADES, PLANTA Y EQUIPO | F78: NAVES, AERONAVES, BARCAZAS Y SIMILARES | G78: Ajuste acumulado por reexpresiones o revaluaciones | I78: PROPIEDADES, PLANTA Y EQUIPO_NAVES, AERONAVES, BARCAZAS Y SIMILARES_Ajuste acumulado por reexpresiones o revaluaciones_ | J78: Propiedades, planta y equipo | K78: =SUMIF(BC!$E$6:$E$347,$A78,BC!$K$6:$K$347) -> 0 | L78: =SUMIF(#REF!,$A78,#REF!)+SUMIF(#REF!,$A78,#REF!) -> #REF! | M78: =SUMIF(#REF!,Casilleros!$A78,#REF!)+SUMIF(#REF!,Casilleros!$A78,#REF!)+SUMIF(#REF!,$A78,#REF!) -> #REF! | N78: =SUMIF(#REF!,$A78,#REF!) -> #REF! | O78: =SUMIF(#REF!,$A78,#REF!)+SUMIF(#REF!,$A78,#REF!) -> #REF! | P78: =IFERROR(VLOOKUP($A78,#REF!,2,FALSE),0) -> 0 | Q78: =SUM(K78:P78) -> #REF!
A79: 368 | B79: ESTADO DE SITUACIÓN FINANCIERA | C79: ACTIVO | D79: ACTIVOS NO CORRIENTES | E79: PROPIEDADES, PLANTA Y EQUIPO | F79: MAQUINARIA, EQUIPO, INSTALACIONES Y ADECUACIONES | G79: Costo histórico antes de reexpresiones o revaluaciones | I79: PROPIEDADES, PLANTA Y EQUIPO_MAQUINARIA, EQUIPO, INSTALACIONES Y ADECUACIONES_Costo histórico antes de reexpresiones o revaluaciones _ | J79: Propiedades, planta y equipo | K79: =SUMIF(BC!$E$6:$E$347,$A79,BC!$K$6:$K$347) -> #REF! | L79: =SUMIF(#REF!,$A79,#REF!)+SUMIF(#REF!,$A79,#REF!) -> #REF! | M79: =SUMIF(#REF!,Casilleros!$A79,#REF!)+SUMIF(#REF!,Casilleros!$A79,#REF!)+SUMIF(#REF!,$A79,#REF!) -> #REF! | N79: =SUMIF(#REF!,$A79,#REF!) -> #REF! | O79: =SUMIF(#REF!,$A79,#REF!)+SUMIF(#REF!,$A79,#REF!) -> #REF! | P79: =IFERROR(VLOOKUP($A79,#REF!,2,FALSE),0) -> 0 | Q79: =SUM(K79:P79) -> #REF!
A80: 369 | B80: ESTADO DE SITUACIÓN FINANCIERA | C80: ACTIVO | D80: ACTIVOS NO CORRIENTES | E80: PROPIEDADES, PLANTA Y EQUIPO | F80: MAQUINARIA, EQUIPO, INSTALACIONES Y ADECUACIONES | G80: Ajuste acumulado por reexpresiones o revaluaciones | I80: PROPIEDADES, PLANTA Y EQUIPO_MAQUINARIA, EQUIPO, INSTALACIONES Y ADECUACIONES_Ajuste acumulado por reexpresiones o revaluaciones_ | J80: Propiedades, planta y equipo | K80: =SUMIF(BC!$E$6:$E$347,$A80,BC!$K$6:$K$347) -> 0 | L80: =SUMIF(#REF!,$A80,#REF!)+SUMIF(#REF!,$A80,#REF!) -> #REF! | M80: =SUMIF(#REF!,Casilleros!$A80,#REF!)+SUMIF(#REF!,Casilleros!$A80,#REF!)+SUMIF(#REF!,$A80,#REF!) -> #REF! | N80: =SUMIF(#REF!,$A80,#REF!) -> #REF! | O80: =SUMIF(#REF!,$A80,#REF!)+SUMIF(#REF!,$A80,#REF!) -> #REF! | P80: =IFERROR(VLOOKUP($A80,#REF!,2,FALSE),0) -> 0 | Q80: =SUM(K80:P80) -> #REF!
A81: 370 | B81: ESTADO DE SITUACIÓN FINANCIERA | C81: ACTIVO | D81: ACTIVOS NO CORRIENTES | E81: PROPIEDADES, PLANTA Y EQUIPO | F81: PLANTAS PRODUCTORAS (AGRICULTURA) | G81: Costo histórico antes de reexpresiones o revaluaciones | I81: PROPIEDADES, PLANTA Y EQUIPO_PLANTAS PRODUCTORAS (AGRICULTURA)_Costo histórico antes de reexpresiones o revaluaciones_ | J81: Propiedades, planta y equipo | K81: =SUMIF(BC!$E$6:$E$347,$A81,BC!$K$6:$K$347) -> 0 | L81: =SUMIF(#REF!,$A81,#REF!)+SUMIF(#REF!,$A81,#REF!) -> #REF! | M81: =SUMIF(#REF!,Casilleros!$A81,#REF!)+SUMIF(#REF!,Casilleros!$A81,#REF!)+SUMIF(#REF!,$A81,#REF!) -> #REF! | N81: =SUMIF(#REF!,$A81,#REF!) -> #REF! | O81: =SUMIF(#REF!,$A81,#REF!)+SUMIF(#REF!,$A81,#REF!) -> #REF! | P81: =IFERROR(VLOOKUP($A81,#REF!,2,FALSE),0) -> 0 | Q81: =SUM(K81:P81) -> #REF!
A82: 371 | B82: ESTADO DE SITUACIÓN FINANCIERA | C82: ACTIVO | D82: ACTIVOS NO CORRIENTES | E82: PROPIEDADES, PLANTA Y EQUIPO | F82: PLANTAS PRODUCTORAS (AGRICULTURA) | G82: Ajuste acumulado por reexpresiones o revaluaciones | I82: PROPIEDADES, PLANTA Y EQUIPO_PLANTAS PRODUCTORAS (AGRICULTURA)_Ajuste acumulado por reexpresiones o revaluaciones_ | J82: Propiedades, planta y equipo | K82: =SUMIF(BC!$E$6:$E$347,$A82,BC!$K$6:$K$347) -> 0 | L82: =SUMIF(#REF!,$A82,#REF!)+SUMIF(#REF!,$A82,#REF!) -> #REF! | M82: =SUMIF(#REF!,Casilleros!$A82,#REF!)+SUMIF(#REF!,Casilleros!$A82,#REF!)+SUMIF(#REF!,$A82,#REF!) -> #REF! | N82: =SUMIF(#REF!,$A82,#REF!) -> #REF! | O82: =SUMIF(#REF!,$A82,#REF!)+SUMIF(#REF!,$A82,#REF!) -> #REF! | P82: =IFERROR(VLOOKUP($A82,#REF!,2,FALSE),0) -> 0 | Q82: =SUM(K82:P82) -> #REF!
A83: 372 | B83: ESTADO DE SITUACIÓN FINANCIERA | C83: ACTIVO | D83: ACTIVOS NO CORRIENTES | E83: PROPIEDADES, PLANTA Y EQUIPO | F83: Construcciones en Curso y Otros Activos en Tránsito | I83: PROPIEDADES, PLANTA Y EQUIPO_Construcciones en Curso y Otros Activos en Tránsito__ | J83: Propiedades, planta y equipo | K83: =SUMIF(BC!$E$6:$E$347,$A83,BC!$K$6:$K$347) -> #REF! | L83: =SUMIF(#REF!,$A83,#REF!)+SUMIF(#REF!,$A83,#REF!) -> #REF! | M83: =SUMIF(#REF!,Casilleros!$A83,#REF!)+SUMIF(#REF!,Casilleros!$A83,#REF!)+SUMIF(#REF!,$A83,#REF!) -> #REF! | N83: =SUMIF(#REF!,$A83,#REF!) -> #REF! | O83: =SUMIF(#REF!,$A83,#REF!)+SUMIF(#REF!,$A83,#REF!) -> #REF! | P83: =IFERROR(VLOOKUP($A83,#REF!,2,FALSE),0) -> 0 | Q83: =SUM(K83:P83) -> #REF!
A84: 373 | B84: ESTADO DE SITUACIÓN FINANCIERA | C84: ACTIVO | D84: ACTIVOS NO CORRIENTES | E84: PROPIEDADES, PLANTA Y EQUIPO | F84: Muebles y enseres | I84: PROPIEDADES, PLANTA Y EQUIPO_Muebles y enseres__ | J84: Propiedades, planta y equipo | K84: =SUMIF(BC!$E$6:$E$347,$A84,BC!$K$6:$K$347) -> #REF! | L84: =SUMIF(#REF!,$A84,#REF!)+SUMIF(#REF!,$A84,#REF!) -> #REF! | M84: =SUMIF(#REF!,Casilleros!$A84,#REF!)+SUMIF(#REF!,Casilleros!$A84,#REF!)+SUMIF(#REF!,$A84,#REF!) -> #REF! | N84: =SUMIF(#REF!,$A84,#REF!) -> #REF! | O84: =SUMIF(#REF!,$A84,#REF!)+SUMIF(#REF!,$A84,#REF!) -> #REF! | P84: =IFERROR(VLOOKUP($A84,#REF!,2,FALSE),0) -> 0 | Q84: =SUM(K84:P84) -> #REF!
A85: 374 | B85: ESTADO DE SITUACIÓN FINANCIERA | C85: ACTIVO | D85: ACTIVOS NO CORRIENTES | E85: PROPIEDADES, PLANTA Y EQUIPO | F85: Equipo de Computación | H85: equipo de computación | I85: PROPIEDADES, PLANTA Y EQUIPO_Equipo de Computación__equipo de computación | J85: Propiedades, planta y equipo | K85: =SUMIF(BC!$E$6:$E$347,$A85,BC!$K$6:$K$347) -> #REF! | L85: =SUMIF(#REF!,$A85,#REF!)+SUMIF(#REF!,$A85,#REF!) -> #REF! | M85: =SUMIF(#REF!,Casilleros!$A85,#REF!)+SUMIF(#REF!,Casilleros!$A85,#REF!)+SUMIF(#REF!,$A85,#REF!) -> #REF! | N85: =SUMIF(#REF!,$A85,#REF!) -> #REF! | O85: =SUMIF(#REF!,$A85,#REF!)+SUMIF(#REF!,$A85,#REF!) -> #REF! | P85: =IFERROR(VLOOKUP($A85,#REF!,2,FALSE),0) -> 0 | Q85: =SUM(K85:P85) -> #REF!
A86: 375 | B86: ESTADO DE SITUACIÓN FINANCIERA | C86: ACTIVO | D86: ACTIVOS NO CORRIENTES | E86: PROPIEDADES, PLANTA Y EQUIPO | F86: Vehículos, Equipo de Transporte y Caminero Móvil | H86: equipo de computación | I86: PROPIEDADES, PLANTA Y EQUIPO_Vehículos, Equipo de Transporte y Caminero Móvil__equipo de computación | J86: Propiedades, planta y equipo | K86: =SUMIF(BC!$E$6:$E$347,$A86,BC!$K$6:$K$347) -> #REF! | L86: =SUMIF(#REF!,$A86,#REF!)+SUMIF(#REF!,$A86,#REF!) -> #REF! | M86: =SUMIF(#REF!,Casilleros!$A86,#REF!)+SUMIF(#REF!,Casilleros!$A86,#REF!)+SUMIF(#REF!,$A86,#REF!) -> #REF! | N86: =SUMIF(#REF!,$A86,#REF!) -> #REF! | O86: =SUMIF(#REF!,$A86,#REF!)+SUMIF(#REF!,$A86,#REF!) -> #REF! | P86: =IFERROR(VLOOKUP($A86,#REF!,2,FALSE),0) -> 0 | Q86: =SUM(K86:P86) -> #REF!
A87: 376 | B87: ESTADO DE SITUACIÓN FINANCIERA | C87: ACTIVO | D87: ACTIVOS NO CORRIENTES | E87: PROPIEDADES, PLANTA Y EQUIPO | F87: PROPIEDADES, PLANTA Y EQUIPO POR CONTRATOS DE ARRENDAMIENTO FINANCIERO | G87: Terrenos | I87: PROPIEDADES, PLANTA Y EQUIPO_PROPIEDADES, PLANTA Y EQUIPO POR CONTRATOS DE ARRENDAMIENTO FINANCIERO_Terrenos_ | J87: Propiedades, planta y equipo | K87: =SUMIF(BC!$E$6:$E$347,$A87,BC!$K$6:$K$347) -> 0 | L87: =SUMIF(#REF!,$A87,#REF!)+SUMIF(#REF!,$A87,#REF!) -> #REF! | M87: =SUMIF(#REF!,Casilleros!$A87,#REF!)+SUMIF(#REF!,Casilleros!$A87,#REF!)+SUMIF(#REF!,$A87,#REF!) -> #REF! | N87: =SUMIF(#REF!,$A87,#REF!) -> #REF! | O87: =SUMIF(#REF!,$A87,#REF!)+SUMIF(#REF!,$A87,#REF!) -> #REF! | P87: =IFERROR(VLOOKUP($A87,#REF!,2,FALSE),0) -> 0 | Q87: =SUM(K87:P87) -> #REF!
A88: 377 | B88: ESTADO DE SITUACIÓN FINANCIERA | C88: ACTIVO | D88: ACTIVOS NO CORRIENTES | E88: PROPIEDADES, PLANTA Y EQUIPO | F88: PROPIEDADES, PLANTA Y EQUIPO POR CONTRATOS DE ARRENDAMIENTO FINANCIERO | G88: Edificios y otros inmuebles (excepto terrenos) | I88: PROPIEDADES, PLANTA Y EQUIPO_PROPIEDADES, PLANTA Y EQUIPO POR CONTRATOS DE ARRENDAMIENTO FINANCIERO_Edificios y otros inmuebles (excepto terrenos)_ | J88: Propiedades, planta y equipo | K88: =SUMIF(BC!$E$6:$E$347,$A88,BC!$K$6:$K$347) -> 0 | L88: =SUMIF(#REF!,$A88,#REF!)+SUMIF(#REF!,$A88,#REF!) -> #REF! | M88: =SUMIF(#REF!,Casilleros!$A88,#REF!)+SUMIF(#REF!,Casilleros!$A88,#REF!)+SUMIF(#REF!,$A88,#REF!) -> #REF! | N88: =SUMIF(#REF!,$A88,#REF!) -> #REF! | O88: =SUMIF(#REF!,$A88,#REF!)+SUMIF(#REF!,$A88,#REF!) -> #REF! | P88: =IFERROR(VLOOKUP($A88,#REF!,2,FALSE),0) -> 0 | Q88: =SUM(K88:P88) -> #REF!
A89: 378 | B89: ESTADO DE SITUACIÓN FINANCIERA | C89: ACTIVO | D89: ACTIVOS NO CORRIENTES | E89: PROPIEDADES, PLANTA Y EQUIPO | F89: PROPIEDADES, PLANTA Y EQUIPO POR CONTRATOS DE ARRENDAMIENTO FINANCIERO | G89: Naves, aeronaves, barcazas y similares | I89: PROPIEDADES, PLANTA Y EQUIPO_PROPIEDADES, PLANTA Y EQUIPO POR CONTRATOS DE ARRENDAMIENTO FINANCIERO_Naves, aeronaves, barcazas y similares_ | J89: Propiedades, planta y equipo | K89: =SUMIF(BC!$E$6:$E$347,$A89,BC!$K$6:$K$347) -> 0 | L89: =SUMIF(#REF!,$A89,#REF!)+SUMIF(#REF!,$A89,#REF!) -> #REF! | M89: =SUMIF(#REF!,Casilleros!$A89,#REF!)+SUMIF(#REF!,Casilleros!$A89,#REF!)+SUMIF(#REF!,$A89,#REF!) -> #REF! | N89: =SUMIF(#REF!,$A89,#REF!) -> #REF! | O89: =SUMIF(#REF!,$A89,#REF!)+SUMIF(#REF!,$A89,#REF!) -> #REF! | P89: =IFERROR(VLOOKUP($A89,#REF!,2,FALSE),0) -> 0 | Q89: =SUM(K89:P89) -> #REF!
A90: 379 | B90: ESTADO DE SITUACIÓN FINANCIERA | C90: ACTIVO | D90: ACTIVOS NO CORRIENTES | E90: PROPIEDADES, PLANTA Y EQUIPO | F90: PROPIEDADES, PLANTA Y EQUIPO POR CONTRATOS DE ARRENDAMIENTO FINANCIERO | G90: Maquinaria, equipo, instalaciones y adecuaciones | I90: PROPIEDADES, PLANTA Y EQUIPO_PROPIEDADES, PLANTA Y EQUIPO POR CONTRATOS DE ARRENDAMIENTO FINANCIERO_Maquinaria, equipo, instalaciones y adecuaciones_ | J90: Propiedades, planta y equipo | K90: =SUMIF(BC!$E$6:$E$347,$A90,BC!$K$6:$K$347) -> 0 | L90: =SUMIF(#REF!,$A90,#REF!)+SUMIF(#REF!,$A90,#REF!) -> #REF! | M90: =SUMIF(#REF!,Casilleros!$A90,#REF!)+SUMIF(#REF!,Casilleros!$A90,#REF!)+SUMIF(#REF!,$A90,#REF!) -> #REF! | N90: =SUMIF(#REF!,$A90,#REF!) -> #REF! | O90: =SUMIF(#REF!,$A90,#REF!)+SUMIF(#REF!,$A90,#REF!) -> #REF! | P90: =IFERROR(VLOOKUP($A90,#REF!,2,FALSE),0) -> 0 | Q90: =SUM(K90:P90) -> #REF!
A91: 380 | B91: ESTADO DE SITUACIÓN FINANCIERA | C91: ACTIVO | D91: ACTIVOS NO CORRIENTES | E91: PROPIEDADES, PLANTA Y EQUIPO | F91: PROPIEDADES, PLANTA Y EQUIPO POR CONTRATOS DE ARRENDAMIENTO FINANCIERO | G91: Equipo de computación | I91: PROPIEDADES, PLANTA Y EQUIPO_PROPIEDADES, PLANTA Y EQUIPO POR CONTRATOS DE ARRENDAMIENTO FINANCIERO_Equipo de computación_ | J91: Propiedades, planta y equipo | K91: =SUMIF(BC!$E$6:$E$347,$A91,BC!$K$6:$K$347) -> 0 | L91: =SUMIF(#REF!,$A91,#REF!)+SUMIF(#REF!,$A91,#REF!) -> #REF! | M91: =SUMIF(#REF!,Casilleros!$A91,#REF!)+SUMIF(#REF!,Casilleros!$A91,#REF!)+SUMIF(#REF!,$A91,#REF!) -> #REF! | N91: =SUMIF(#REF!,$A91,#REF!) -> #REF! | O91: =SUMIF(#REF!,$A91,#REF!)+SUMIF(#REF!,$A91,#REF!) -> #REF! | P91: =IFERROR(VLOOKUP($A91,#REF!,2,FALSE),0) -> 0 | Q91: =SUM(K91:P91) -> #REF!
A92: 381 | B92: ESTADO DE SITUACIÓN FINANCIERA | C92: ACTIVO | D92: ACTIVOS NO CORRIENTES | E92: PROPIEDADES, PLANTA Y EQUIPO | F92: PROPIEDADES, PLANTA Y EQUIPO POR CONTRATOS DE ARRENDAMIENTO FINANCIERO | G92: Vehículos, equipo de transporte y caminero móvil | I92: PROPIEDADES, PLANTA Y EQUIPO_PROPIEDADES, PLANTA Y EQUIPO POR CONTRATOS DE ARRENDAMIENTO FINANCIERO_Vehículos, equipo de transporte y caminero móvil_ | J92: Propiedades, planta y equipo | K92: =SUMIF(BC!$E$6:$E$347,$A92,BC!$K$6:$K$347) -> 0 | L92: =SUMIF(#REF!,$A92,#REF!)+SUMIF(#REF!,$A92,#REF!) -> #REF! | M92: =SUMIF(#REF!,Casilleros!$A92,#REF!)+SUMIF(#REF!,Casilleros!$A92,#REF!)+SUMIF(#REF!,$A92,#REF!) -> #REF! | N92: =SUMIF(#REF!,$A92,#REF!) -> #REF! | O92: =SUMIF(#REF!,$A92,#REF!)+SUMIF(#REF!,$A92,#REF!) -> #REF! | P92: =IFERROR(VLOOKUP($A92,#REF!,2,FALSE),0) -> 0 | Q92: =SUM(K92:P92) -> #REF!
A93: 382 | B93: ESTADO DE SITUACIÓN FINANCIERA | C93: ACTIVO | D93: ACTIVOS NO CORRIENTES | E93: PROPIEDADES, PLANTA Y EQUIPO | F93: PROPIEDADES, PLANTA Y EQUIPO POR CONTRATOS DE ARRENDAMIENTO FINANCIERO | G93: Otros | I93: PROPIEDADES, PLANTA Y EQUIPO_PROPIEDADES, PLANTA Y EQUIPO POR CONTRATOS DE ARRENDAMIENTO FINANCIERO_Otros_ | J93: Propiedades, planta y equipo | K93: =SUMIF(BC!$E$6:$E$347,$A93,BC!$K$6:$K$347) -> 0 | L93: =SUMIF(#REF!,$A93,#REF!)+SUMIF(#REF!,$A93,#REF!) -> #REF! | M93: =SUMIF(#REF!,Casilleros!$A93,#REF!)+SUMIF(#REF!,Casilleros!$A93,#REF!)+SUMIF(#REF!,$A93,#REF!) -> #REF! | N93: =SUMIF(#REF!,$A93,#REF!) -> #REF! | O93: =SUMIF(#REF!,$A93,#REF!)+SUMIF(#REF!,$A93,#REF!) -> #REF! | P93: =IFERROR(VLOOKUP($A93,#REF!,2,FALSE),0) -> 0 | Q93: =SUM(K93:P93) -> #REF!
A94: 383 | B94: ESTADO DE SITUACIÓN FINANCIERA | C94: ACTIVO | D94: ACTIVOS NO CORRIENTES | E94: PROPIEDADES, PLANTA Y EQUIPO | F94: Otras Propiedades, Planta y Equipo | I94: PROPIEDADES, PLANTA Y EQUIPO_Otras Propiedades, Planta y Equipo__ | J94: Propiedades, planta y equipo | K94: =SUMIF(BC!$E$6:$E$347,$A94,BC!$K$6:$K$347) -> 0 | L94: =SUMIF(#REF!,$A94,#REF!)+SUMIF(#REF!,$A94,#REF!) -> #REF! | M94: =SUMIF(#REF!,Casilleros!$A94,#REF!)+SUMIF(#REF!,Casilleros!$A94,#REF!)+SUMIF(#REF!,$A94,#REF!) -> #REF! | N94: =SUMIF(#REF!,$A94,#REF!) -> #REF! | O94: =SUMIF(#REF!,$A94,#REF!)+SUMIF(#REF!,$A94,#REF!) -> #REF! | P94: =IFERROR(VLOOKUP($A94,#REF!,2,FALSE),0) -> 0 | Q94: =SUM(K94:P94) -> #REF!
A95: 384 | B95: ESTADO DE SITUACIÓN FINANCIERA | C95: ACTIVO | D95: ACTIVOS NO CORRIENTES | E95: PROPIEDADES, PLANTA Y EQUIPO | F95: (-) DEPRECIACIÒN ACUMULADA DE PROPIEDADES, PLANTA Y EQUIPO | G95: Del costo histórico antes de reexpresiones o revaluaciones | I95: PROPIEDADES, PLANTA Y EQUIPO_(-) DEPRECIACIÒN ACUMULADA DE PROPIEDADES, PLANTA Y EQUIPO_Del costo histórico antes de reexpresiones o revaluaciones_ | J95: Propiedades, planta y equipo | K95: =SUMIF(BC!$E$6:$E$347,$A95,BC!$K$6:$K$347) -> #REF! | L95: =SUMIF(#REF!,$A95,#REF!)+SUMIF(#REF!,$A95,#REF!) -> #REF! | M95: =SUMIF(#REF!,Casilleros!$A95,#REF!)+SUMIF(#REF!,Casilleros!$A95,#REF!)+SUMIF(#REF!,$A95,#REF!) -> #REF! | N95: =SUMIF(#REF!,$A95,#REF!) -> #REF! | O95: =SUMIF(#REF!,$A95,#REF!)+SUMIF(#REF!,$A95,#REF!) -> #REF! | P95: =IFERROR(VLOOKUP($A95,#REF!,2,FALSE),0) -> 0 | Q95: =SUM(K95:P95) -> #REF!
A96: 385 | B96: ESTADO DE SITUACIÓN FINANCIERA | C96: ACTIVO | D96: ACTIVOS NO CORRIENTES | E96: PROPIEDADES, PLANTA Y EQUIPO | F96: (-) DEPRECIACIÒN ACUMULADA DE PROPIEDADES, PLANTA Y EQUIPO | G96: Del ajuste acumulado por reexpresiones o revaluaciones | I96: PROPIEDADES, PLANTA Y EQUIPO_(-) DEPRECIACIÒN ACUMULADA DE PROPIEDADES, PLANTA Y EQUIPO_Del ajuste acumulado por reexpresiones o revaluaciones_ | J96: Propiedades, planta y equipo | K96: =SUMIF(BC!$E$6:$E$347,$A96,BC!$K$6:$K$347) -> #REF! | L96: =SUMIF(#REF!,$A96,#REF!)+SUMIF(#REF!,$A96,#REF!) -> #REF! | M96: =SUMIF(#REF!,Casilleros!$A96,#REF!)+SUMIF(#REF!,Casilleros!$A96,#REF!)+SUMIF(#REF!,$A96,#REF!) -> #REF! | N96: =SUMIF(#REF!,$A96,#REF!) -> #REF! | O96: =SUMIF(#REF!,$A96,#REF!)+SUMIF(#REF!,$A96,#REF!) -> #REF! | P96: =IFERROR(VLOOKUP($A96,#REF!,2,FALSE),0) -> 0 | Q96: =SUM(K96:P96) -> #REF!
A97: 386 | B97: ESTADO DE SITUACIÓN FINANCIERA | C97: ACTIVO | D97: ACTIVOS NO CORRIENTES | E97: PROPIEDADES, PLANTA Y EQUIPO | F97: (-) Deterioro acumulado del valor de propiedades, planta y equipo | I97: PROPIEDADES, PLANTA Y EQUIPO_(-) Deterioro acumulado del valor de propiedades, planta y equipo__ | J97: Propiedades, planta y equipo | K97: =SUMIF(BC!$E$6:$E$347,$A97,BC!$K$6:$K$347) -> 0 | L97: =SUMIF(#REF!,$A97,#REF!)+SUMIF(#REF!,$A97,#REF!) -> #REF! | M97: =SUMIF(#REF!,Casilleros!$A97,#REF!)+SUMIF(#REF!,Casilleros!$A97,#REF!)+SUMIF(#REF!,$A97,#REF!) -> #REF! | N97: =SUMIF(#REF!,$A97,#REF!) -> #REF! | O97: =SUMIF(#REF!,$A97,#REF!)+SUMIF(#REF!,$A97,#REF!) -> #REF! | P97: =IFERROR(VLOOKUP($A97,#REF!,2,FALSE),0) -> 0 | Q97: =SUM(K97:P97) -> #REF!
A98: 387 | B98: ESTADO DE SITUACIÓN FINANCIERA | C98: ACTIVO | D98: ACTIVOS NO CORRIENTES | E98: ACTIVOS INTANGIBLES | F98: Plusvalía o goodwill (derecho de llave) | I98: ACTIVOS INTANGIBLES_Plusvalía o goodwill (derecho de llave)__ | J98: Activos intangibles | K98: =SUMIF(BC!$E$6:$E$347,$A98,BC!$K$6:$K$347) -> 0 | L98: =SUMIF(#REF!,$A98,#REF!)+SUMIF(#REF!,$A98,#REF!) -> #REF! | M98: =SUMIF(#REF!,Casilleros!$A98,#REF!)+SUMIF(#REF!,Casilleros!$A98,#REF!)+SUMIF(#REF!,$A98,#REF!) -> #REF! | N98: =SUMIF(#REF!,$A98,#REF!) -> #REF! | O98: =SUMIF(#REF!,$A98,#REF!)+SUMIF(#REF!,$A98,#REF!) -> #REF! | P98: =IFERROR(VLOOKUP($A98,#REF!,2,FALSE),0) -> 0 | Q98: =SUM(K98:P98) -> #REF!
A99: 388 | B99: ESTADO DE SITUACIÓN FINANCIERA | C99: ACTIVO | D99: ACTIVOS NO CORRIENTES | E99: ACTIVOS INTANGIBLES | F99: Marcas, patentes, licencias y otros similares | I99: ACTIVOS INTANGIBLES_Marcas, patentes, licencias y otros similares__ | J99: Activos intangibles | K99: =SUMIF(BC!$E$6:$E$347,$A99,BC!$K$6:$K$347) -> 0 | L99: =SUMIF(#REF!,$A99,#REF!)+SUMIF(#REF!,$A99,#REF!) -> #REF! | M99: =SUMIF(#REF!,Casilleros!$A99,#REF!)+SUMIF(#REF!,Casilleros!$A99,#REF!)+SUMIF(#REF!,$A99,#REF!) -> #REF! | N99: =SUMIF(#REF!,$A99,#REF!) -> #REF! | O99: =SUMIF(#REF!,$A99,#REF!)+SUMIF(#REF!,$A99,#REF!) -> #REF! | P99: =IFERROR(VLOOKUP($A99,#REF!,2,FALSE),0) -> 0 | Q99: =SUM(K99:P99) -> #REF!
A100: 389 | B100: ESTADO DE SITUACIÓN FINANCIERA | C100: ACTIVO | D100: ACTIVOS NO CORRIENTES | E100: ACTIVOS INTANGIBLES | F100: Adecuaciones y mejoras en bienes arrendados mediante arrendamiento operativo | I100: ACTIVOS INTANGIBLES_Adecuaciones y mejoras en bienes arrendados mediante arrendamiento operativo__ | J100: Activos intangibles | K100: =SUMIF(BC!$E$6:$E$347,$A100,BC!$K$6:$K$347) -> 0 | L100: =SUMIF(#REF!,$A100,#REF!)+SUMIF(#REF!,$A100,#REF!) -> #REF! | M100: =SUMIF(#REF!,Casilleros!$A100,#REF!)+SUMIF(#REF!,Casilleros!$A100,#REF!)+SUMIF(#REF!,$A100,#REF!) -> #REF! | N100: =SUMIF(#REF!,$A100,#REF!) -> #REF! | O100: =SUMIF(#REF!,$A100,#REF!)+SUMIF(#REF!,$A100,#REF!) -> #REF! | P100: =IFERROR(VLOOKUP($A100,#REF!,2,FALSE),0) -> 0 | Q100: =SUM(K100:P100) -> #REF!
A101: 390 | B101: ESTADO DE SITUACIÓN FINANCIERA | C101: ACTIVO | D101: ACTIVOS NO CORRIENTES | E101: ACTIVOS INTANGIBLES | F101: Derechos en acuerdos de concesión | I101: ACTIVOS INTANGIBLES_Derechos en acuerdos de concesión__ | J101: Activos intangibles | K101: =SUMIF(BC!$E$6:$E$347,$A101,BC!$K$6:$K$347) -> 0 | L101: =SUMIF(#REF!,$A101,#REF!)+SUMIF(#REF!,$A101,#REF!) -> #REF! | M101: =SUMIF(#REF!,Casilleros!$A101,#REF!)+SUMIF(#REF!,Casilleros!$A101,#REF!)+SUMIF(#REF!,$A101,#REF!) -> #REF! | N101: =SUMIF(#REF!,$A101,#REF!) -> #REF! | O101: =SUMIF(#REF!,$A101,#REF!)+SUMIF(#REF!,$A101,#REF!) -> #REF! | P101: =IFERROR(VLOOKUP($A101,#REF!,2,FALSE),0) -> 0 | Q101: =SUM(K101:P101) -> #REF!
A102: 391 | B102: ESTADO DE SITUACIÓN FINANCIERA | C102: ACTIVO | D102: ACTIVOS NO CORRIENTES | E102: ACTIVOS INTANGIBLES | F102: Otros | I102: ACTIVOS INTANGIBLES_Otros__ | J102: Activos intangibles | K102: =SUMIF(BC!$E$6:$E$347,$A102,BC!$K$6:$K$347) -> 0 | L102: =SUMIF(#REF!,$A102,#REF!)+SUMIF(#REF!,$A102,#REF!) -> #REF! | M102: =SUMIF(#REF!,Casilleros!$A102,#REF!)+SUMIF(#REF!,Casilleros!$A102,#REF!)+SUMIF(#REF!,$A102,#REF!) -> #REF! | N102: =SUMIF(#REF!,$A102,#REF!) -> #REF! | O102: =SUMIF(#REF!,$A102,#REF!)+SUMIF(#REF!,$A102,#REF!) -> #REF! | P102: =IFERROR(VLOOKUP($A102,#REF!,2,FALSE),0) -> 0 | Q102: =SUM(K102:P102) -> #REF!
A103: 392 | B103: ESTADO DE SITUACIÓN FINANCIERA | C103: ACTIVO | D103: ACTIVOS NO CORRIENTES | E103: ACTIVOS INTANGIBLES | F103: (-) Amortización acumulada de activos intangibles | I103: ACTIVOS INTANGIBLES_(-) Amortización acumulada de activos intangibles__ | J103: Activos intangibles | K103: =SUMIF(BC!$E$6:$E$347,$A103,BC!$K$6:$K$347) -> 0 | L103: =SUMIF(#REF!,$A103,#REF!)+SUMIF(#REF!,$A103,#REF!) -> #REF! | M103: =SUMIF(#REF!,Casilleros!$A103,#REF!)+SUMIF(#REF!,Casilleros!$A103,#REF!)+SUMIF(#REF!,$A103,#REF!) -> #REF! | N103: =SUMIF(#REF!,$A103,#REF!) -> #REF! | O103: =SUMIF(#REF!,$A103,#REF!)+SUMIF(#REF!,$A103,#REF!) -> #REF! | P103: =IFERROR(VLOOKUP($A103,#REF!,2,FALSE),0) -> 0 | Q103: =SUM(K103:P103) -> #REF!
A104: 393 | B104: ESTADO DE SITUACIÓN FINANCIERA | C104: ACTIVO | D104: ACTIVOS NO CORRIENTES | E104: ACTIVOS INTANGIBLES | F104: (-) Deterioro acumulado de activos intangibles | I104: ACTIVOS INTANGIBLES_(-) Deterioro acumulado de activos intangibles__ | J104: Activos intangibles | K104: =SUMIF(BC!$E$6:$E$347,$A104,BC!$K$6:$K$347) -> 0 | L104: =SUMIF(#REF!,$A104,#REF!)+SUMIF(#REF!,$A104,#REF!) -> #REF! | M104: =SUMIF(#REF!,Casilleros!$A104,#REF!)+SUMIF(#REF!,Casilleros!$A104,#REF!)+SUMIF(#REF!,$A104,#REF!) -> #REF! | N104: =SUMIF(#REF!,$A104,#REF!) -> #REF! | O104: =SUMIF(#REF!,$A104,#REF!)+SUMIF(#REF!,$A104,#REF!) -> #REF! | P104: =IFERROR(VLOOKUP($A104,#REF!,2,FALSE),0) -> 0 | Q104: =SUM(K104:P104) -> #REF!
A105: 394 | B105: ESTADO DE SITUACIÓN FINANCIERA | C105: ACTIVO | D105: ACTIVOS NO CORRIENTES | E105: PROPIEDADES DE INVERSIÓN | F105: TERRENOS | G105: A costo | I105: PROPIEDADES DE INVERSIÓN_TERRENOS_A costo_ | J105: Propiedades de inversión | K105: =SUMIF(BC!$E$6:$E$347,$A105,BC!$K$6:$K$347) -> 0 | L105: =SUMIF(#REF!,$A105,#REF!)+SUMIF(#REF!,$A105,#REF!) -> #REF! | M105: =SUMIF(#REF!,Casilleros!$A105,#REF!)+SUMIF(#REF!,Casilleros!$A105,#REF!)+SUMIF(#REF!,$A105,#REF!) -> #REF! | N105: =SUMIF(#REF!,$A105,#REF!) -> #REF! | O105: =SUMIF(#REF!,$A105,#REF!)+SUMIF(#REF!,$A105,#REF!) -> #REF! | P105: =IFERROR(VLOOKUP($A105,#REF!,2,FALSE),0) -> 0 | Q105: =SUM(K105:P105) -> #REF!
A106: 395 | B106: ESTADO DE SITUACIÓN FINANCIERA | C106: ACTIVO | D106: ACTIVOS NO CORRIENTES | E106: PROPIEDADES DE INVERSIÓN | F106: TERRENOS | G106: A valor razonable | I106: PROPIEDADES DE INVERSIÓN_TERRENOS_A valor razonable_ | J106: Propiedades de inversión | K106: =SUMIF(BC!$E$6:$E$347,$A106,BC!$K$6:$K$347) -> 0 | L106: =SUMIF(#REF!,$A106,#REF!)+SUMIF(#REF!,$A106,#REF!) -> #REF! | M106: =SUMIF(#REF!,Casilleros!$A106,#REF!)+SUMIF(#REF!,Casilleros!$A106,#REF!)+SUMIF(#REF!,$A106,#REF!) -> #REF! | N106: =SUMIF(#REF!,$A106,#REF!) -> #REF! | O106: =SUMIF(#REF!,$A106,#REF!)+SUMIF(#REF!,$A106,#REF!) -> #REF! | P106: =IFERROR(VLOOKUP($A106,#REF!,2,FALSE),0) -> 0 | Q106: =SUM(K106:P106) -> #REF!
